Workbook
Name RealceValor: IFERROR(IF('NOME + Nº'!#REF!="Sim", TRUE, FALSE),FALSE)

Sheet Programação Individual
C2: Descrição do bloco: | J2: Victor Barros Pedreira Ferreira (VMordekai) | P2: Atualizada em: | R2: ='NOME + Nº'!D5 -> 45182
B3: BETA | C3: ATENÇÃO: VERSÃO BETA = PRECIFICAÇÃO POR PROCESSOS! Se você estiver usando essas planilhas, entre em contato para dicas, sugestões ou atualizações. Versão nas descrições. | J3: e-mail: vmordekai@hotmail.com. Tel & Whatssap: (41) 99758-4893 | P3: VERSÃO | R3: ='NOME + Nº'!D4 -> 2023.17.3 000
C6: Leitura dos dados | AB6: Supondo Dados de Operação Ao Mês do Revendedor | AH6: Dias úteis
C7: valores fixos (escritos pelo usuário) | G7: A B C | J7: ='NOME + Nº'!C8 -> REF. NOME + Nº - 15H x 10B x 5L (cm) | U7: DADOS GERAIS DA REFERÊNCIA | AH7: 24
C8: valores calculados ou dependentes de outra célula | G8: A B C | J8: T1 | K8: CONDIÇÃO | L8: EXEMPLO "ARRANJO POR PROCESSOS"
K9: Preço de Venda | N9: =N32/N22 -> 326.73998
C10: Notas e observações | G10: A B C | K10: Metas | P10: Arranjo da Produção | V10: Custo de produção/ Unidade | Y10: ='NOME + Nº'!H123+'NOME + Nº'!K176 -> 121.51078 | AD10: Despesas Físicas
C11: Neutras | G11: A B C | K11: Orçamentos da Produção /Unidade
C12: Alternativas (CLIQUE NO BOTÃO). Ex. "SIM" ou "NÃO" | G12: NÃO | K12: Margem de Contribuição (MC) | N12: =SUM(G39:G41) -> 0.3 | P12: CELULAR | V12: Operação | X12: RELÓGIO | AE12: Aluguel | AH12: 2000
C13: Correto | G13: A B C | K13: Custo de produção/ Unidade | N13: =IF(P12=G31,0,Y10) -> 121.51078 | V13: PROCESSOS | X13: h | Y13: min | Z13: seg | AE13: Eletricidade | AH13: 500
C14: Incorreto | G14: A B C | K14: Tempo de Produção (em horas) /Unidade | O14: RELÓGIO | V14: ¹Principal | X14: ='Arranjo PROCESSOS'!BC12 -> 0 | Y14: ='Arranjo PROCESSOS'!BD12 -> 41 | Z14: ='Arranjo PROCESSOS'!BE12 -> 50 | AE14: Telefonia | AH14: 180
C15: Controles de cálculos, números livres, encerramento de tabela ou parte | G15: A B C | N15: Segundos | O15: h | P15: min | Q15: seg | V15: ²Secundária | X15: ='Arranjo PROCESSOS'!BC13 -> 0.69722222 | Y15: ='Arranjo PROCESSOS'!BD13 -> 0 | Z15: ='Arranjo PROCESSOS'!BE13 -> 0 | AE15: Seguro | AH15: 200
K16: ¹Operação Principal | M16: Costura | N16: =O16*((60^2))+(P16*60)+Q16 -> 1800 | O16: =IF(P12=G31,X24,IF(P12=G29,X14,X19)) -> 0 | P16: =IF(P12=G31,Y24,IF(P12=G29,Y14,Y19)) -> 30 | Q16: =IF(P12=G31,Z24,IF(P12=G29,Z14,Z19)) -> 0 | V16: ³Pausa programadas (funcionário/dia) | Y16: 45 | Z16: 0 | AE16: Outros | AH16: 80
C17: Destaques livres ou estéticos | G17: Cores diversas | K17: ²Operação Secundária | M17: Auxiliar | N17: =(O17*(60^2))+(P17*60)+Q17 -> 600 | O17: =IF(P12=G31,X25,IF(P12=G29,X15,X20)) -> 0 | P17: =IF(P12=G31,Y25,IF(P12=G29,Y15,Y20)) -> 10 | Q17: =IF(P12=G31,Z25,IF(P12=G29,Z15,Z20)) -> 0 | AF17: Subtotal | AH17: =SUM(AH12:AH16) -> 2960
K18: ³Tempo improdutivo (funcionário/dia) | N18: =(O18*(60^2))+(P18*60)+Q18 -> 2700 | O18: =IF(P12=G31,X26,IF(P12=G29,X16,X21)) -> 0 | P18: =IF(P12=G31,Y26,IF(P12=G29,Y16,Y21)) -> 45 | Q18: =IF(P12=G31,Z26,IF(P12=G29,Z16,Z21)) -> 0 | V18: CELULAR | X18: h | Y18: min | Z18: seg | AD18: Funcionários
K19: 1800 | V19: =V14 -> ¹Principal | X19: ='Arranjo CELULAR'!P54 -> 0 | Y19: ='Arranjo CELULAR'!Q54 -> 30 | Z19: ='Arranjo CELULAR'!R54 -> 0
K20: Estatísticas da Produção | V20: =V15 -> ²Secundária | X20: ='Arranjo CELULAR'!P56 -> 0 | Y20: ='Arranjo CELULAR'!Q56 -> 10 | Z20: ='Arranjo CELULAR'!R56 -> 0 | AE20: Quantidade | AH20: 4
B21: VMORDEKAI | K21: Capacidade Efetiva desse produto (%) | N21: 0.7 | V21: =V16 -> ³Pausa programadas (funcionário/dia) | Y21: 45 | Z21: 0 | AE21: Média salarial mensal bruta | AH21: 2300
K22: Quantidade produzida por mês | N22: =N23*N26*N21 -> 520.674 | AE22: Outros | AH22: 600
K23: Produção/dia | N23: =(N38)*N39*N21/N16 -> 33.81 | P23: PRODUÇÃO DE LOTE | V23: UTILIZAÇÃO | X23: h | Y23: min | Z23: seg | AF23: Subtotal | AH23: =(AH21*AH20)+AH22 -> 9800
D24: Mês de referência: | F24: (mês) | K24: Carrinhos de abastecimento/dia | N24: =(N38)*N21/K19 -> 11.27 | P24: TEMPO PARA FAZER | R24: 75 | T24: Unidades | V24: =V19 -> ¹Principal | X24: 1 | Y24: 0 | Z24: 0 | AD24: Outras Despesas ou Investimentos
D25: Última atualização | F25: (data) | K25: Total de produtos recolhidos por Carrinhos | N25: =N23/N24 -> 3 | P25: TOTAL | R25: =R24/N23 -> 2.2182786 | T25: DIAS | V25: =V20 -> ²Secundária | X25: 0 | Y25: 20 | Z25: ='Arranjo CELULAR'!R61 -> 0
K26: Dias úteis de Produção | N26: =G36 -> 22 | V26: =V21 -> ³Pausa programadas (funcionário/dia) | Y26: 45 | Z26: 0 | AE26: publicidade e propaganda | AH26: 200
B27: PRECIFICAÇÃO POR PROCESSOS? | G27: NÃO | K27: Custos (Insumos, Matéria-Prima) | N27: =N13*N22 -> 63267.502 | AE27: Empréstimos e Taxas | AH27: 1000
K28: *Despesas Físicas | N28: =SUM(G309:G314) -> 11760 | AE28: Outros | AH28: 0
C29: Arranjo da Produção | G29: PROCESSOS | K29: Despesas com Funcionários | N29: =F68 -> 53337.891 | AF29: Subtotal | AH29: =SUM(AH26:AH28) -> 1200
G30: CELULAR | K30: Outras Despesas | N30: =SUM(G318:G320) -> 2500
G31: UTILIZAÇÃO | K31: Despesa Total | N31: =SUM(N27:N30) -> 130865.39 | AG31: TOTAL | AH31: =AH17+AH29+AH23 -> 13960
K32: Montante | N32: =N31+(N31*N12) -> 170125.01
C33: =B3 -> BETA | D33: Dados gerais da empresa | K33: Receita Mensal | N33: =N32-N31 -> 39259.618
AC34: Preço de venda direto e sugestão de revenda | AH34: Parâmetros do Revendedor
K35: Funcionarios | AC35: =J7 -> REF. NOME + Nº - 15H x 10B x 5L (cm)
D36: Dias úteis/mês em operação | G36: 22 | K36: Operador Principal | AB36: =J8 -> T1 | AC36: =L8 -> EXEMPLO "ARRANJO POR PROCESSOS" | AH36: Ao Mês | AJ36: Vendas por dia
C37: OPERAÇÃO | D37: Utilização da Capacidade (%) | G37: 0.7 | M37: h | N37: s | AF37: Preços | AG37: fator (%) | AH37: Valor (R$) | AI37: Quant.
D38: └Tolerância da Capacidade (%) | G38: 0.1 | K38: Carga horária por funcionário/dia | M38: =G72 -> 8.8 | N38: =(M38*60*60)-N18 -> 28980 | AC38: Preço sugerido para revenda | AF38: =AF40*AG38/AG40 -> 594.07268 | AG38: 100 | AH38: =AG38*AH43/AG43 -> 93066.667 | AI38: =AH38/AF38 -> 156.65872 | AJ38: =AI38/AH7 -> 6.5274467
D39: Impostos Totais | G39: 0.05 | K39: Quantidade de Costureiras (os) | N39: =G73 -> 3 | AB39: fatores | AC39: (-) Impostos s/Vendas | AF39: =(AF40*AG39)/AG40 -> 59.407268 | AG39: 10 | AH39: =AH43*AG39/AG43 -> 9306.6667
D40: MCAE* | G40: 0.1 | AC40: (-) Custo das Mercadorias Vendidas | AF40: =N9 -> 326.73998 | AG40: 55 | AH40: =AH43*AG40/AG43 -> 51186.667
D41: Lucro Desejado (%) | G41: 0.15 | K41: ¹ Operação deve estar com margem de tolerância | AC41: (-) Despesas Variáveis | AF41: =(AF40*AG41)/AG40 -> 59.407268 | AG41: 10 | AH41: =AH43*AG41/AG43 -> 9306.6667
D42: *MCAE - Margem de Contribuição para Ações Estratégicas | K42: ² Não determina a Produção OU a Operação que pode ser terceirizada | AC42: (=) Margem de Contribuição (Final) | AF42: =(AF40*AG42)/AG40 -> 148.51817 | AG42: =AG38-(SUM(AG39:AG41)) -> 25 | AH42: =AG42*AH43/AG43 -> 23266.667
D43: MARK-UP | K43: ³ Paradas programadas e não programadas, exemplo: 30 min e 15 min, respectivamente | AC43: (-) Despesas Fixas | AF43: =(AF40*AG43)/45 -> 108.91333 | AG43: 15 | AH43: =AH31 -> 13960
K44: * Despesas estimadas na cidade de Curitiba, Paraná. | AC44: (=) Lucro | AF44: =(AF40*AG44)/AG40 -> 59.407268 | AG44: =AG42-AG43 -> 10 | AH44: =AH43*AG44/AG43 -> 9306.6667
D45: MARK-UP POR PROCESSOS (HORA-OPERAÇÃO) | G45: =N50/1 -> 258.4382 | AC45: fonte: | AD45: http://revistapegn.globo.com/Revista/Common/0,,EMI91389-17198,00-COMO+CALCULAR+A+MARGEM+DE+LUCRO+DE+UM+PRODUTO.html
C48: Funcionarios | J48: =J7 -> REF. NOME + Nº - 15H x 10B x 5L (cm)
J49: T2 | K49: CONDIÇÃO | L49: CUSTO DE UTILIZAÇÃO
D50: Salário Mínimo Vigente | G50: 1320 | K50: Preço de Venda | N50: =N73/N63 -> 258.4382
C51: Total | K51: Metas | P51: Arranjo da Produção
F52: Valor | G52: % | K52: Orçamentos da Produção /Unidade
C53: expediente de trabalho* | F53: =(G91*G92)+(G110*G111)+(G72*G73)+(G128*G129)+(G146*G147)+(G164*G165)+(G182*G183)+(G200*G201)+(G218*G219)+(G236*G237)+(G254*G255)+(G272*G273)+(G290*G291) -> 115.2 | K53: Margem de Contribuição (MC) | N53: =SUM(G39:G41) -> 0.3 | P53: UTILIZAÇÃO
C54: funcionarios, quantidade | F54: =G92+G111+G73+G129+G147+G165+G183+G201+G219+G237+G255+G273+G291 -> 16 | K54: Custo de produção/ Unidade | N54: =IF(P53=G31,0,Y10) -> 0
C55: Salário Bruto Médio | F55: =((G74*G73)+(G93*G92)+(G112*G111)+(G130*G129)+(G148*G147)+(G166*G165)+(G184*G183)+(G202*G201)+(G220*G219)+(G238*G237)+(G256*G255)+(G274*G273)+(G292*G291))/F54 -> 2145 | K55: Tempo de Produção (em horas) /Unidade | O55: RELÓGIO
C56: Vale Transporte | F56: =G94+G113+G75+G131+G149+G167+G185+G203+G221+G239+G257+G275+G293 -> 2904 | N56: segundos | O56: h | P56: min | Q56: seg
C57: Outro Benefícios | F57: =G95+G114+G76+G132+G150+G168+G186+G204+G222+G240+G258+G276+G294 -> 450 | K57: ¹Operação Principal | M57: Costura | N57: =O57*((60^2))+(P57*60)+Q57 -> 3600 | O57: =IF(P53=G31,X24,IF(P53=G29,X14,X19)) -> 1 | P57: =IF(P53=G31,Y24,IF(P53=G29,Y14,Y19)) -> 0 | Q57: =IF(P53=G31,Z24,IF(P53=G29,Z14,Z19)) -> 0
C58: Vale Refeição | Alimentação | F58: =G96+G115+G77+G133+G151+G169+G187+G205+G223+G241+G259+G277+G295 -> 3520 | K58: ²Operação Secundária | M58: Auxiliar | N58: =(O58*(60^2))+(P58*60)+Q58 -> 1200 | O58: =IF(P53=G31,X25,IF(P53=G29,X15,X20)) -> 0 | P58: =IF(P53=G31,Y25,IF(P53=G29,Y15,Y20)) -> 20 | Q58: =IF(P53=G31,Z25,IF(P53=G29,Z15,Z20)) -> 0
C59: Plano de Saúde | F59: =G97+G116+G78+G134+G152+G170+G188+G206+G224+G242+G260+G278+G296 -> 450 | G59: =G390 -> 1.4761804 | K59: ³Tempo improdutivo (funcionário/dia) | N59: =(O59*(60^2))+(P59*60)+Q59 -> 2700 | O59: =IF(P53=G31,X26,IF(P53=G29,X16,X21)) -> 0 | P59: =IF(P53=G31,Y26,IF(P53=G29,Y16,Y21)) -> 45 | Q59: =IF(P53=G31,Z26,IF(P53=G29,Z16,Z21)) -> 0
C60: Desconto Vale Transporte | F60: =G98+G117+G79+G135+G153+G171+G189+G207+G225+G243+G261+G279+G297 -> -174.2424 | G60: =G391 -> -6.0000827 | K60: 1800
C61: FGTS | F61: =G99+G118+G80+G136+G154+G172+G190+G208+G226+G244+G262+G280+G298 -> 2167.4429 | G61: =G392 -> 8.0000118 | K61: Estatísticas da Produção
C62: 13º Salário | F62: =G100+G119+G81+G137+G155+G173+G191+G209+G227+G245+G263+G281+G299 -> 2656.5 | G62: =G393 -> 8.3333333 | K62: Capacidade Efetiva desse produto (%) | N62: 0.8
C63: 13º Salário - FGTS | F63: =G101+G120+G82+G138+G156+G174+G192+G210+G228+G246+G264+G282+G300 -> 164.11419 | G63: =G394 -> 0.66664305 | K63: Quantidade produzida por mês | N63: =N64*N67*N62 -> 340.032
C64: Férias | F64: =G102+G121+G83+G139+G157+G175+G193+G211+G229+G247+G265+G283+G301 -> 2656.5 | G64: =G395 -> 8.3333333 | K64: Produção/dia | N64: =(N79)*N80*N62/N57 -> 19.32 | P64: PRODUÇÃO DE LOTE
C65: 1/3 Férias | F65: =G103+G122+G84+G140+G158+G176+G194+G212+G230+G248+G266+G284+G302 -> 885.53137 | G65: =G396 -> 2.7778762 | K65: Carrinhos de abastecimento/dia | N65: =(N79)*N62/K60 -> 12.88 | P65: TEMPO PARA FAZER | R65: 1 | T65: Unidades
C66: Férias - FGTS | F66: =G104+G123+G85+G141+G159+G177+G195+G213+G231+G249+G267+G285+G303 -> 218.84314 | G66: =G397 -> 0.88895581 | K66: Total de produtos recolhidos por Carrinhos | N66: =N64/N65 -> 1.5 | P66: TOTAL | R66: =R65/N64 -> 0.051759834 | T66: DIAS
C67: Outros | F67: =G105+G124+G86+G142+G160+G178+G196+G214+G232+G250+G268+G286+G304 -> 1581.7197 | G67: =G398 -> 2.9523607 | K67: Dias úteis de Produção | N67: =G36 -> 22
E68: Total | F68: =G106+G125+G87+G143+G161+G179+G197+G215+G233+G251+G269+G287+G305 -> 53337.891 | K68: Custos (Insumos, Matéria-Prima) | N68: =N54*N63 -> 0
D69: *Depende da categoria | Vide o final da tabela | K69: *Despesas Físicas | N69: =SUM(G309:G314) -> 11760
B70: Operação Principal | E70: Costura | K70: Despesas com Funcionários | N70: =F68 -> 53337.891
C71: 1 | D71: Costureir@ | K71: Outras Despesas | N71: =SUM(G318:G320) -> 2500
D72: Expediente de trabalho | G72: =((4*((12-8)+(18-13)))+(1*((12-8)+(17-13))))/5 -> 8.8 | K72: Despesa Total | N72: =SUM(N68:N71) -> 67597.891
D73: Funcionários, quantidade | G73: 3 | K73: Montante | N73: =N72+(N72*N53) -> 87877.258
D74: Salário Bruto | G74: =G50*B79/100 -> 1980 | K74: Receita Mensal | N74: =N73-N72 -> 20279.367 | AC74: Preço de venda direto e sugestão de revenda | AH74: Parâmetros do Revendedor
B75: Referência Salário Mínimo (%) | D75: Vale Transporte | G75: =G36*F352 -> 242 | AC75: =J48 -> REF. NOME + Nº - 15H x 10B x 5L (cm)
D76: Outro Benefícios | G76: 50 | K76: Funcionarios | AB76: =J49 -> T2 | AC76: =L49 -> CUSTO DE UTILIZAÇÃO | AH76: Ao Mês | AJ76: Vendas por dia
D77: Vale Refeição | Alimentação | G77: 320 | K77: Operador Principal | AF77: Preços | AG77: fator (%) | AH77: Valor (R$) | AI77: Quant.
D78: Plano de Saúde | G78: 50 | M78: h | N78: s | AC78: Preço sugerido para revenda | AF78: =AF80*AG78/AG80 -> 469.88763 | AG78: 100 | AH78: =AG78*AH83/AG83 -> 93066.667 | AI78: =AH78/AF78 -> 198.06154 | AJ78: =AI78/AH7 -> 8.252564
B79: 150 | D79: Desconto Vale Transporte | G79: =G75*G60/100 -> -14.5202 | K79: Carga horária por funcionário/dia | M79: =M38 -> 8.8 | N79: =(M79*60*60)-N59 -> 28980 | AB79: fatores | AC79: (-) Impostos s/Vendas | AF79: =(AF80*AG79)/AG80 -> 46.988763 | AG79: 10 | AH79: =AH83*AG79/AG83 -> 9306.6667
D80: FGTS | G80: =IF(B83="CLT",G74*G61/100,E407) -> 158.40023 | K80: Quantidade de Costureiras (os) | N80: =G73 -> 3 | AC80: (-) Custo das Mercadorias Vendidas | AF80: =N50 -> 258.4382 | AG80: 55 | AH80: =AH83*AG80/AG83 -> 51186.667
B81: REGIME | D81: 13º Salário | G81: =G74*G62/100 -> 165 | AC81: (-) Despesas Variáveis | AF81: =(AF80*AG81)/AG80 -> 46.988763 | AG81: 10 | AH81: =AH83*AG81/AG83 -> 9306.6667
D82: 13º Salário - FGTS | G82: =IF(B83="CLT",G74*G63/100,0) -> 13.199532 | K82: ¹ Operação deve estar com margem de tolerância | AC82: (=) Margem de Contribuição (Final) | AF82: =(AF80*AG82)/AG80 -> 117.47191 | AG82: =AG78-(SUM(AG79:AG81)) -> 25 | AH82: =AG82*AH83/AG83 -> 23266.667
B83: CLT | D83: Férias | G83: =G74*G64/100 -> 165 | K83: ² Não determina a Produção OU a Operação que pode ser terceirizada | AC83: (-) Despesas Fixas | AF83: =(AF80*AG83)/45 -> 86.146066 | AG83: 15 | AH83: =AH31 -> 13960
D84: 1/3 Férias | G84: =G74*G65/100 -> 55.001949 | K84: ³ Paradas programadas e não programadas, 30 min e 15 min, respectivamente | AC84: (=) Lucro | AF84: =(AF80*AG84)/AG80 -> 46.988763 | AG84: =AG82-AG83 -> 10 | AH84: =AH83*AG84/AG83 -> 9306.6667
D85: Férias - FGTS | G85: =IF(B83="CLT",G74*G66/100,0) -> 17.601325 | K85: * Despesas estimadas na cidade de Curitiba, Paraná. | AC85: fonte: | AD85: http://revistapegn.globo.com/Revista/Common/0,,EMI91389-17198,00-COMO+CALCULAR+A+MARGEM+DE+LUCRO+DE+UM+PRODUTO.html
D86: Outros | G86: =G74*G67/100 -> 58.456742
F87: Total | G87: =SUM(G74:G86)*G73 -> 9780.4187
G88: =G74*100/G50 -> 150
B89: Operação Secundária | E89: Auxiliar
C90: 2 | D90: Aux. de Costura | Cortador (a)
D91: Expediente de trabalho | G91: =((4*((12-8)+(18-13)))+(1*((12-8)+(17-13))))/5 -> 8.8
D92: Funcionários, quantidade | G92: 1
D93: Salário Bruto | G93: =G50*B98/100 -> 1716
B94: Referência Salário Mínimo (%) | D94: Vale Transporte | G94: =G36*F352 -> 242
D95: Outro Benefícios | G95: 50
D96: Vale Refeição | Alimentação | G96: 320
D97: Plano de Saúde | G97: 50
B98: 130 | D98: Desconto Vale Transporte | G98: =G94*G60/100 -> -14.5202
D99: FGTS | G99: =IF(B102="CLT",G93*G61/100,E407) -> 137.2802
B100: REGIME | D100: 13º Salário | G100: =G93*G62/100 -> 143
D101: 13º Salário - FGTS | G101: =IF(B102="CLT",G93*G63/100,0) -> 11.439595
B102: CLT | D102: Férias | G102: =G93*G64/100 -> 143
D103: 1/3 Férias | G103: =G93*G65/100 -> 47.668355
D104: Férias - FGTS | G104: =IF(B102="CLT",G93*G66/100,0) -> 15.254482
D105: Outros | G105: =G93*G67/100 -> 50.66251
...

Sheet NOME + Nº
B2: ='Programação Individual'!B21 -> VMORDEKAI
B4: Versão da Planilha | D4: 2023.17.3 000 | I4: Modelista | J4: Victor Ferreira | L4: 45182
B5: By Victor Ferreira | D5: 45182 | I5: Dados: | J5: Victor Ferreira | L5: 45182
B7: NOME | C7: NOME + Nº
B8: REFERÊNCIA | C8: =IF(C7=0,"Informe o nome da referência!",CONCATENATE(LEFT(B8,3),". ",C7," - ",D13,"H x ",D14,"B x ",D15,"L (cm)")) -> REF. NOME + Nº - 15H x 10B x 5L (cm)
B10: 1 | C10: DESCRIÇÃO GERAL
B12: DIMENSÕES (cm) | F12: OBSERVAÇÕES ADICIONAIS | J12: LEGENDA DE PRAZOS
B13: Altura (H - Altura máxima) | D13: 15 | F13: DESCRIÇÃO | H13: VALOR | J13: Validade do Orçamento
B14: Base (B - Vista Frontal) | D14: 10 | J14: STATUS | K14: DIAS | L14: (HOJE - PRAZO)
B15: Largura (L - Vista Lateral) | D15: 5 | J15: Prazo Máximo | K15: 90 | L15: =TODAY()-K15 -> 45650
B16: (Outro parâmetro) | J16: Fase Inicial | K16: 7 | L16: =TODAY()-K16 -> 45733
B17: (Outro parâmetro) | J17: Desenvolvimento | K17: 30 | L17: =TODAY()-K17 -> 45710
B18: Margem | D18: 1 | J18: Limite | K18: 60 | L18: =TODAY()-K18 -> 45680
B19: Alça | D19: SIM | E19: =IF(D19="SIM","1","0") -> 1 | J19: Dead Line | K19: 90 | L19: =TODAY()-K19 -> 45650
B20: Alça Dupla | D20: NÃO | E20: =IF(D20="SIM","2","1") -> 1
B21: Alça Largura | D21: 3
B22: Vivo | D22: NÃO | E22: =IF(D22="SIM","1","0") -> 0
B23: Entretela | D23: NÃO | E23: =IF(D23="SIM","1","0") -> 0
B24: Forro | D24: NÃO | E24: =IF(D24="SIM","1","0") -> 0
B25: Couro | D25: NÃO | E25: =IF(D25="SIM","1","0") -> 0
B26: Tec. Vivo | D26: NÃO | E26: =IF(D26="SIM","1","0") -> 0
B27: Estrutura | D27: NÃO | E27: =IF(D27="SIM","1","0") -> 0
B28: Reforço | D28: NÃO | E28: =IF(D28="SIM","1","0") -> 0
B30: =B10+1 -> 2 | C30: TECIDOS
B31: PLANILHAS REVISADAS?
B32: MODELAGEM | C32: SIM | F32: TIPO DE ORÇAMENTO POR: | H32: =IF(E42=0,D47,IF(E42=(1+IF(D23="SIM","1","0")+IF(D24="SIM","1","0")+IF(D25="SIM","1","0")+IF(D26="SIM","1","0")+IF(D27="SIM","1","0")),D48,D49)) -> MOLDES | I32: =IF(H32=D47,E47, IF(H32=D48,E48, IF(H32=D49,E49,"0"))) -> INDIVIDUAL
B33: ENFESTO | C33: NÃO
D34: Descrição | E34: TIPO | F34: FORNECEDOR | G34: QUANTIDADE* | H34: Valor (R$) | I34: Data FORNECENOR | J34: Largura (cm) | K34: Consumo | L34: Observações
B35: Tec. Externo | D35: Aquablock | E35: MOLDES | F35: BRASILUSA | G35: =ENFESTO!AU274/H128 -> 0 | H35: 49.9 | I35: 45133 | J35: 140 | K35: =IF(E35=D47,MODELAGEM!EG14,IF(H50=1,H35*G35,"ERRO")) -> 8.9467765
B36: =B23 -> Entretela | D36: 80 | E36: MOLDES | F36: VOLUNTÁRIOS | G36: =ENFESTO!AU275/H128 -> 0 | H36: 16 | I36: 45133 | J36: 75 | K36: =IF(J36>0,IF(E36=D47, (MODELAGEM!EG15)*E23,IF(H50=1,H36*G36*E23,"ERRO")),0) -> 0
B37: =B24 -> Forro | D37: Suede | E37: MOLDES | F37: BRASILUSA | G37: =ENFESTO!AU276/H128 -> 0 | H37: 19.9 | I37: 45133 | J37: 140 | K37: =IF(J37>0,IF(E37=D47, (MODELAGEM!EG16)*E24, IF(H50=1,H37*G37*E24,"ERRO")),0) -> 0
B38: =B25 -> Couro | D38: Couro Legítimo Fly | E38: MOLDES | F38: ROMA PLÁSTICOS | G38: =ENFESTO!AU277/H128 -> 0 | H38: 74.9 | I38: 45133 | J38: 100 | K38: =IF(J38>0,IF(E38=D47, (MODELAGEM!EG17)*E25, IF(H50=1, H38*G38*E25,"ERRO")),0) -> 0
B39: =B26 -> Tec. Vivo | D39: =D35 -> Aquablock | E39: MOLDES | F39: =F35 -> BRASILUSA | G39: =ENFESTO!AU278/H128 -> 0 | H39: =H35 -> 49.9 | I39: =I35 -> 45133 | J39: =J35 -> 140 | K39: =IF(J39>0,IF(E39=D47, (MODELAGEM!EG18)*E26, IF(H50=1, H39*G39*E26,"ERRO")),0) -> 0
B40: =B27 -> Estrutura | D40: Placa Plástica | E40: MOLDES | F40: ROMA PLÁSTICOS | G40: =ENFESTO!AU279/H128 -> 0 | H40: 20.12 | I40: 45182 | J40: 28 | K40: =IF(J40>0,IF(E40=D47, (MODELAGEM!EG19)*E27, IF(H50=1,H40*G40*E27,"ERRO")),0) -> 0
B41: =B28 -> Reforço | D41: TNT 120 | E41: MOLDES | F41: ROMA PLÁSTICOS | G41: =ENFESTO!AU281/H129 -> 0 | H41: 7.9 | I41: 45133 | J41: 140 | K41: =IF(J41>0,IF(E41=D47, (MODELAGEM!EG20)*E28, IF(H50=1,H41*G41*E28,"ERRO")),0) -> 0
E42: =IF(E35=D47,"0","1")+IF(D23="SIM",IF(E36=D47,"0","1"),"0")+IF(D24="SIM",IF(E37=D47,"0","1"),"0")+IF(D25="SIM",IF(E38=D47,"0","1"),"0")+IF(D26="SIM",IF(E39=D47,"0","1"),"0")+IF(D27="SIM",IF(E40=D47,"0","1"),"0") -> 0 | F42: *QUANTIDADE: peças fechadas ou metro por ENFESTO | I42: =IF(SUM(I35:I40)>0,SMALL(I35:I40,1),TODAY()) -> 45133 | J42: Consumo | K42: =K35+IF(D23="SIM",K36,0)+IF(D24="SIM",K37,0)+IF(D25="SIM",K38,0)+IF(D26="SIM",K39,0)+IF(D27="SIM",K40,0)+IF(D28="SIM",K41,0) -> 8.9467765
D44: Descrição
D45: TIPO DE ORÇAMENTO DE TECIDOS POR:
D46: Tipos | E46: Recomendação | G46: Características
D47: MOLDES | E47: INDIVIDUAL | G47: Máximo de aproveitamento | J47: Considera moldes CORTADOS individualmente
D48: ENFESTO | E48: LOTE OU EXCLUSIVO | G48: Aproveitamento limitado pelo LOTE | J48: Considera consumo total do material
D49: MISTO | E49: CONDICIONAL | G49: Varia por material empregado | J49: Características mistas
E50: MODELAGEM | F50: =IF(C32="SIM",1,0) -> 1 | G50: × | H50: =IF(C33="SIM",1,0) -> 0 | I50: ENFESTO
B52: =B30+1 -> 3 | C52: AVIAMENTOS
C54: VIVO PRONTO: | E54: NÃO | G54: Preços da planilha AVIAMENTOS: | J54: SIM
E56: DESCRIÇÃO | F56: Valor (R$) | G56: Informação | H56: FORNECEDOR | I56: Data de Orçamento do FORNECEDOR | J56: Valor Automático | K56: Quant (m)* | L56: Consumo*
C58: =IF(E54="NÃO","CORDÃO PARA VIVO:","VIVO PRONTO:") -> CORDÃO PARA VIVO: | E58: Cordão Algodão São José 5mm 50m | F58: 0 | G58: =IF(E58<>0,LOOKUP(E58,ListaDeEstoque[DESCRIÇÃO],ListaDeEstoque[Largura e Dimensões]),"") -> 0 | H58: =IF(E58<>0,IF((LOOKUP(E58,ListaDeEstoque[DESCRIÇÃO],ListaDeEstoque[CÓD. do FORNECEDOR]))<>0,IF(LOOKUP(E58,ListaDeEstoque[DESCRIÇÃO],ListaDeEstoque[FORNECEDOR])=0,"NI",LOOKUP(E58,ListaDeEstoque[DESCRIÇÃO],ListaDeEstoque[FORNECEDOR])),"NI"),"") -> NI | I58: =IF(E58<>0,LOOKUP(E58,ListaDeEstoque[DESCRIÇÃO],ListaDeEstoque[Data do último ORÇAMENTO DO FORNECEDOR]),"") -> 44862 | J58: =IF(E58<>0,LOOKUP(E58,ListaDeEstoque[DESCRIÇÃO],ListaDeEstoque[Preço unitário]),0) -> 2.49 | K58: =(MODELAGEM!AG36+MODELAGEM!Z37)*MODELAGEM!AG37/100 -> 1.0624778 | L58: =IF(J54="SIM",IF(D22="SIM",K58*J58,0),K58*F58) -> 0
C59: =IF(E54="NÃO",MODELAGEM!AC33,"") -> MATERIAL: | E59: =IF(E54="NÃO",MODELAGEM!AE33,"") -> Tec. Vivo | F59: =IF(D54="NÃO",MODELAGEM!AF33,"") | G59: =IF(E54="NÃO","**","") -> ** | H59: =IF(E54="NÃO","**","") -> ** | I59: =IF(E54="NÃO","**","") -> ** | J59: =IF(E54="NÃO",MODELAGEM!AG33,"") -> 49.9 | K59: =IF(E54="NÃO",MODELAGEM!AG43/MODELAGEM!AG38,"") -> 0.023053096 | L59: =IF(E54="NÃO","**","") -> **
D60: Observações | K60: Consumo | L60: =SUM(L58:L59) -> 0
C62: ALÇA PRONTA: | E62: NÃO
C64: ALÇA Equivalente | D64: LARGURA | E64: Quant (m)* | F64: Observações | G64: FORNECEDOR | H64: Data de Orçamento do FORNECEDOR | I64: Preços da planilha AVIAMENTOS | J64: Valor (R$) | K64: Valor Automático | L64: Consumo**
B65: Nº
B66: 1 | C66: Alça ANNA B 30mm | D66: =LOOKUP(C66,MODELAGEM!Y21:Y25,MODELAGEM!AA21:AA25) -> #N/A | E66: =MODELAGEM!S291 -> 0.124 | G66: =IF(C66<>0,IF((LOOKUP(C66,ListaDeEstoque[DESCRIÇÃO],ListaDeEstoque[CÓD. do FORNECEDOR]))<>0,IF(LOOKUP(C66,ListaDeEstoque[DESCRIÇÃO],ListaDeEstoque[FORNECEDOR])=0,"NI",LOOKUP(C66,ListaDeEstoque[DESCRIÇÃO],ListaDeEstoque[FORNECEDOR])),"NI"),"") -> #N/A | H66: =IF(C66<>0,LOOKUP(C66,ListaDeEstoque[DESCRIÇÃO],ListaDeEstoque[Data do último ORÇAMENTO DO FORNECEDOR]),"") -> #N/A | I66: SIM | J66: 0 | K66: =IF(E62="SIM",MODELAGEM!Z21,"**") -> ** | L66: =IF(I66="SIM",IF(E62="SIM",K66*E66,"**"),J66*E66) -> **
B67: 2 | D67: =LOOKUP(C67,MODELAGEM!Y22:Y26,MODELAGEM!AA22:AA26) -> 0 | E67: =MODELAGEM!S292 -> 0 | G67: =IF(C67<>0,IF((LOOKUP(C67,ListaDeEstoque[DESCRIÇÃO],ListaDeEstoque[CÓD. do FORNECEDOR]))<>0,IF(LOOKUP(C67,ListaDeEstoque[DESCRIÇÃO],ListaDeEstoque[FORNECEDOR])=0,"NI",LOOKUP(C67,ListaDeEstoque[DESCRIÇÃO],ListaDeEstoque[FORNECEDOR])),"NI"),"") | H67: =IF(C67<>0,LOOKUP(C67,ListaDeEstoque[DESCRIÇÃO],ListaDeEstoque[Data do último ORÇAMENTO DO FORNECEDOR]),"") | I67: SIM | J67: 0 | K67: =IF(E62="SIM",MODELAGEM!Z22,"**") -> ** | L67: =IF(I67="SIM",IF(E62="SIM",K67*E67,"**"),J67*E67) -> **
B68: 3 | D68: =LOOKUP(C68,MODELAGEM!Y23:Y27,MODELAGEM!AA23:AA27) -> 0 | E68: =MODELAGEM!S293 -> 0 | G68: =IF(C68<>0,IF((LOOKUP(C68,ListaDeEstoque[DESCRIÇÃO],ListaDeEstoque[CÓD. do FORNECEDOR]))<>0,IF(LOOKUP(C68,ListaDeEstoque[DESCRIÇÃO],ListaDeEstoque[FORNECEDOR])=0,"NI",LOOKUP(C68,ListaDeEstoque[DESCRIÇÃO],ListaDeEstoque[FORNECEDOR])),"NI"),"") | H68: =IF(C68<>0,LOOKUP(C68,ListaDeEstoque[DESCRIÇÃO],ListaDeEstoque[Data do último ORÇAMENTO DO FORNECEDOR]),"") | I68: SIM | J68: 0 | K68: =IF(E62="SIM",MODELAGEM!Z23,"**") -> ** | L68: =IF(I68="SIM",IF(E62="SIM",K68*E68,"**"),J68*E68) -> **
B69: 4 | D69: =LOOKUP(C69,MODELAGEM!Y24:Y28,MODELAGEM!AA24:AA28) -> 0 | E69: =MODELAGEM!S294 -> 0 | G69: =IF(C69<>0,IF((LOOKUP(C69,ListaDeEstoque[DESCRIÇÃO],ListaDeEstoque[CÓD. do FORNECEDOR]))<>0,IF(LOOKUP(C69,ListaDeEstoque[DESCRIÇÃO],ListaDeEstoque[FORNECEDOR])=0,"NI",LOOKUP(C69,ListaDeEstoque[DESCRIÇÃO],ListaDeEstoque[FORNECEDOR])),"NI"),"") | H69: =IF(C69<>0,LOOKUP(C69,ListaDeEstoque[DESCRIÇÃO],ListaDeEstoque[Data do último ORÇAMENTO DO FORNECEDOR]),"") | I69: SIM | J69: 0 | K69: =IF(E62="SIM",MODELAGEM!Z24,"**") -> ** | L69: =IF(I69="SIM",IF(E62="SIM",K69*E69,"**"),J69*E69) -> **
B70: 5 | D70: =LOOKUP(C70,MODELAGEM!Y25:Y29,MODELAGEM!AA25:AA29) -> 0 | E70: =MODELAGEM!S295 -> 0 | G70: =IF(C70<>0,IF((LOOKUP(C70,ListaDeEstoque[DESCRIÇÃO],ListaDeEstoque[CÓD. do FORNECEDOR]))<>0,IF(LOOKUP(C70,ListaDeEstoque[DESCRIÇÃO],ListaDeEstoque[FORNECEDOR])=0,"NI",LOOKUP(C70,ListaDeEstoque[DESCRIÇÃO],ListaDeEstoque[FORNECEDOR])),"NI"),"") | H70: =IF(C70<>0,LOOKUP(C70,ListaDeEstoque[DESCRIÇÃO],ListaDeEstoque[Data do último ORÇAMENTO DO FORNECEDOR]),"") | I70: SIM | K70: =IF(E62="SIM",MODELAGEM!Z25,"**") -> ** | L70: =IF(I70="SIM",IF(E62="SIM",K70*E70,"**"),J70*E70) -> **
B71: 6 | D71: =LOOKUP(C71,MODELAGEM!Y26:Y30,MODELAGEM!AA26:AA30) -> 0 | E71: =MODELAGEM!S296 -> 0 | G71: =IF(C71<>0,IF((LOOKUP(C71,ListaDeEstoque[DESCRIÇÃO],ListaDeEstoque[CÓD. do FORNECEDOR]))<>0,IF(LOOKUP(C71,ListaDeEstoque[DESCRIÇÃO],ListaDeEstoque[FORNECEDOR])=0,"NI",LOOKUP(C71,ListaDeEstoque[DESCRIÇÃO],ListaDeEstoque[FORNECEDOR])),"NI"),"") | H71: =IF(C71<>0,LOOKUP(C71,ListaDeEstoque[DESCRIÇÃO],ListaDeEstoque[Data do último ORÇAMENTO DO FORNECEDOR]),"") | I71: SIM | K71: =IF(E62="SIM",MODELAGEM!Z26,"**") -> ** | L71: =IF(I71="SIM",IF(E62="SIM",K71*E71,"**"),J71*E71) -> **
H72: =IF(SUM(H66:H71)>0,SMALL(H66:H71,1),TODAY()) -> #N/A | K72: Consumo | L72: =IF(E62="SIM",SUM(L66:L71),MODELAGEM!EI22) -> 0.73108758
F73: *Valores (em azul) definidos na planilha de MODELAGEM
F74: =IF(E62="NÃO","** Valores de acordo com material específico definido na MODELAGEM","**Na planilha MODELAGEM, verificar possibilidade de moldes duplicados") -> ** Valores de acordo com material específico definido na MODELAGEM
C76: OUTROS AVIAMENTOS
C77: Nome | E77: Quant* | F77: Observações | G77: FORNECEDOR | H77: Data de Orçamento do FORNECEDOR | I77: Preços da planilha AVIAMENTOS | J77: Valor (R$) | K77: Valor Automático | L77: TOTAL
B78: Nº
B79: 1 | C79: Caneta Mágica | E79: 0.05 | F79: 5% de uma caneta por peça | G79: =IF(C79<>0,IF((LOOKUP(C79,ListaDeEstoque[DESCRIÇÃO],ListaDeEstoque[CÓD. do FORNECEDOR]))<>0,IF(LOOKUP(C79,ListaDeEstoque[DESCRIÇÃO],ListaDeEstoque[FORNECEDOR])=0,"NI",LOOKUP(C79,ListaDeEstoque[DESCRIÇÃO],ListaDeEstoque[FORNECEDOR])),"NI"),"") -> NI | H79: =IF(C79<>0,LOOKUP(C79,ListaDeEstoque[DESCRIÇÃO],ListaDeEstoque[Data do último ORÇAMENTO DO FORNECEDOR]),"") -> 44531 | I79: SIM | J79: 0 | K79: =IF(C79<>0,LOOKUP(C79,ListaDeEstoque[DESCRIÇÃO],ListaDeEstoque[Preço unitário]),0) -> 0.48 | L79: =IF(I79="SIM",K79*E79,J79*E79) -> 0.024
B80: 2 | C80: Rebite N.1 (5,5mm) (Níquel) (macho e fêmea) | E80: 5 | G80: =IF(C80<>0,IF((LOOKUP(C80,ListaDeEstoque[DESCRIÇÃO],ListaDeEstoque[CÓD. do FORNECEDOR]))<>0,IF(LOOKUP(C80,ListaDeEstoque[DESCRIÇÃO],ListaDeEstoque[FORNECEDOR])=0,"NI",LOOKUP(C80,ListaDeEstoque[DESCRIÇÃO],ListaDeEstoque[FORNECEDOR])),"NI"),"") -> NI | H80: =IF(C80<>0,LOOKUP(C80,ListaDeEstoque[DESCRIÇÃO],ListaDeEstoque[Data do último ORÇAMENTO DO FORNECEDOR]),"") -> 44862 | I80: SIM | J80: 0 | K80: =IF(C80<>0,LOOKUP(C80,ListaDeEstoque[DESCRIÇÃO],ListaDeEstoque[Preço unitário]),0) -> 20.8 | L80: =IF(I80="SIM",K80*E80,J80*E80) -> 104
B81: 3 | C81: Ziper Nylon (pacote) 30mm | E81: 2 | G81: =IF(C81<>0,IF((LOOKUP(C81,ListaDeEstoque[DESCRIÇÃO],ListaDeEstoque[CÓD. do FORNECEDOR]))<>0,IF(LOOKUP(C81,ListaDeEstoque[DESCRIÇÃO],ListaDeEstoque[FORNECEDOR])=0,"NI",LOOKUP(C81,ListaDeEstoque[DESCRIÇÃO],ListaDeEstoque[FORNECEDOR])),"NI"),"") -> NI | H81: =IF(C81<>0,LOOKUP(C81,ListaDeEstoque[DESCRIÇÃO],ListaDeEstoque[Data do último ORÇAMENTO DO FORNECEDOR]),"") -> 44862 | I81: SIM | J81: 0 | K81: =IF(C81<>0,LOOKUP(C81,ListaDeEstoque[DESCRIÇÃO],ListaDeEstoque[Preço unitário]),0) -> 1.34 | L81: =IF(I81="SIM",K81*E81,J81*E81) -> 2.68
B82: 4 | G82: =IF(C82<>0,IF((LOOKUP(C82,ListaDeEstoque[DESCRIÇÃO],ListaDeEstoque[CÓD. do FORNECEDOR]))<>0,IF(LOOKUP(C82,ListaDeEstoque[DESCRIÇÃO],ListaDeEstoque[FORNECEDOR])=0,"NI",LOOKUP(C82,ListaDeEstoque[DESCRIÇÃO],ListaDeEstoque[FORNECEDOR])),"NI"),"") | H82: =IF(C82<>0,LOOKUP(C82,ListaDeEstoque[DESCRIÇÃO],ListaDeEstoque[Data do último ORÇAMENTO DO FORNECEDOR]),"") | I82: SIM | J82: 0 | K82: =IF(C82<>0,LOOKUP(C82,ListaDeEstoque[DESCRIÇÃO],ListaDeEstoque[Preço unitário]),0) -> 0 | L82: =IF(I82="SIM",K82*E82,J82*E82) -> 0
B83: 5 | G83: =IF(C83<>0,IF((LOOKUP(C83,ListaDeEstoque[DESCRIÇÃO],ListaDeEstoque[CÓD. do FORNECEDOR]))<>0,IF(LOOKUP(C83,ListaDeEstoque[DESCRIÇÃO],ListaDeEstoque[FORNECEDOR])=0,"NI",LOOKUP(C83,ListaDeEstoque[DESCRIÇÃO],ListaDeEstoque[FORNECEDOR])),"NI"),"") | H83: =IF(C83<>0,LOOKUP(C83,ListaDeEstoque[DESCRIÇÃO],ListaDeEstoque[Data do último ORÇAMENTO DO FORNECEDOR]),"") | I83: SIM | J83: 0 | K83: =IF(C83<>0,LOOKUP(C83,ListaDeEstoque[DESCRIÇÃO],ListaDeEstoque[Preço unitário]),0) -> 0 | L83: =IF(I83="SIM",K83*E83,J83*E83) -> 0
B84: 6 | G84: =IF(C84<>0,IF((LOOKUP(C84,ListaDeEstoque[DESCRIÇÃO],ListaDeEstoque[CÓD. do FORNECEDOR]))<>0,IF(LOOKUP(C84,ListaDeEstoque[DESCRIÇÃO],ListaDeEstoque[FORNECEDOR])=0,"NI",LOOKUP(C84,ListaDeEstoque[DESCRIÇÃO],ListaDeEstoque[FORNECEDOR])),"NI"),"") | H84: =IF(C84<>0,LOOKUP(C84,ListaDeEstoque[DESCRIÇÃO],ListaDeEstoque[Data do último ORÇAMENTO DO FORNECEDOR]),"") | I84: SIM | J84: 0 | K84: =IF(C84<>0,LOOKUP(C84,ListaDeEstoque[DESCRIÇÃO],ListaDeEstoque[Preço unitário]),0) -> 0 | L84: =IF(I84="SIM",K84*E84,J84*E84) -> 0
B85: 7 | G85: =IF(C85<>0,IF((LOOKUP(C85,ListaDeEstoque[DESCRIÇÃO],ListaDeEstoque[CÓD. do FORNECEDOR]))<>0,IF(LOOKUP(C85,ListaDeEstoque[DESCRIÇÃO],ListaDeEstoque[FORNECEDOR])=0,"NI",LOOKUP(C85,ListaDeEstoque[DESCRIÇÃO],ListaDeEstoque[FORNECEDOR])),"NI"),"") | H85: =IF(C85<>0,LOOKUP(C85,ListaDeEstoque[DESCRIÇÃO],ListaDeEstoque[Data do último ORÇAMENTO DO FORNECEDOR]),"") | I85: SIM | J85: 0 | K85: =IF(C85<>0,LOOKUP(C85,ListaDeEstoque[DESCRIÇÃO],ListaDeEstoque[Preço unitário]),0) -> 0 | L85: =IF(I85="SIM",K85*E85,J85*E85) -> 0
B86: 8 | G86: =IF(C86<>0,IF((LOOKUP(C86,ListaDeEstoque[DESCRIÇÃO],ListaDeEstoque[CÓD. do FORNECEDOR]))<>0,IF(LOOKUP(C86,ListaDeEstoque[DESCRIÇÃO],ListaDeEstoque[FORNECEDOR])=0,"NI",LOOKUP(C86,ListaDeEstoque[DESCRIÇÃO],ListaDeEstoque[FORNECEDOR])),"NI"),"") | H86: =IF(C86<>0,LOOKUP(C86,ListaDeEstoque[DESCRIÇÃO],ListaDeEstoque[Data do último ORÇAMENTO DO FORNECEDOR]),"") | I86: SIM | J86: 0 | K86: =IF(C86<>0,LOOKUP(C86,ListaDeEstoque[DESCRIÇÃO],ListaDeEstoque[Preço unitário]),0) -> 0 | L86: =IF(I86="SIM",K86*E86,J86*E86) -> 0
B87: 9 | G87: =IF(C87<>0,IF((LOOKUP(C87,ListaDeEstoque[DESCRIÇÃO],ListaDeEstoque[CÓD. do FORNECEDOR]))<>0,IF(LOOKUP(C87,ListaDeEstoque[DESCRIÇÃO],ListaDeEstoque[FORNECEDOR])=0,"NI",LOOKUP(C87,ListaDeEstoque[DESCRIÇÃO],ListaDeEstoque[FORNECEDOR])),"NI"),"") | H87: =IF(C87<>0,LOOKUP(C87,ListaDeEstoque[DESCRIÇÃO],ListaDeEstoque[Data do último ORÇAMENTO DO FORNECEDOR]),"") | I87: SIM | J87: 0 | K87: =IF(C87<>0,LOOKUP(C87,ListaDeEstoque[DESCRIÇÃO],ListaDeEstoque[Preço unitário]),0) -> 0 | L87: =IF(I87="SIM",K87*E87,J87*E87) -> 0
B88: 10 | G88: =IF(C88<>0,IF((LOOKUP(C88,ListaDeEstoque[DESCRIÇÃO],ListaDeEstoque[CÓD. do FORNECEDOR]))<>0,IF(LOOKUP(C88,ListaDeEstoque[DESCRIÇÃO],ListaDeEstoque[FORNECEDOR])=0,"NI",LOOKUP(C88,ListaDeEstoque[DESCRIÇÃO],ListaDeEstoque[FORNECEDOR])),"NI"),"") | H88: =IF(C88<>0,LOOKUP(C88,ListaDeEstoque[DESCRIÇÃO],ListaDeEstoque[Data do último ORÇAMENTO DO FORNECEDOR]),"") | I88: SIM | J88: 0 | K88: =IF(C88<>0,LOOKUP(C88,ListaDeEstoque[DESCRIÇÃO],ListaDeEstoque[Preço unitário]),0) -> 0 | L88: =IF(I88="SIM",K88*E88,J88*E88) -> 0
B89: 11 | G89: =IF(C89<>0,IF((LOOKUP(C89,ListaDeEstoque[DESCRIÇÃO],ListaDeEstoque[CÓD. do FORNECEDOR]))<>0,IF(LOOKUP(C89,ListaDeEstoque[DESCRIÇÃO],ListaDeEstoque[FORNECEDOR])=0,"NI",LOOKUP(C89,ListaDeEstoque[DESCRIÇÃO],ListaDeEstoque[FORNECEDOR])),"NI"),"") | H89: =IF(C89<>0,LOOKUP(C89,ListaDeEstoque[DESCRIÇÃO],ListaDeEstoque[Data do último ORÇAMENTO DO FORNECEDOR]),"") | I89: SIM | J89: 0 | K89: =IF(C89<>0,LOOKUP(C89,ListaDeEstoque[DESCRIÇÃO],ListaDeEstoque[Preço unitário]),0) -> 0 | L89: =IF(I89="SIM",K89*E89,J89*E89) -> 0
B90: 12 | G90: =IF(C90<>0,IF((LOOKUP(C90,ListaDeEstoque[DESCRIÇÃO],ListaDeEstoque[CÓD. do FORNECEDOR]))<>0,IF(LOOKUP(C90,ListaDeEstoque[DESCRIÇÃO],ListaDeEstoque[FORNECEDOR])=0,"NI",LOOKUP(C90,ListaDeEstoque[DESCRIÇÃO],ListaDeEstoque[FORNECEDOR])),"NI"),"") | H90: =IF(C90<>0,LOOKUP(C90,ListaDeEstoque[DESCRIÇÃO],ListaDeEstoque[Data do último ORÇAMENTO DO FORNECEDOR]),"") | I90: SIM | J90: 0 | K90: =IF(C90<>0,LOOKUP(C90,ListaDeEstoque[DESCRIÇÃO],ListaDeEstoque[Preço unitário]),0) -> 0 | L90: =IF(I90="SIM",K90*E90,J90*E90) -> 0
B91: 13 | G91: =IF(C91<>0,IF((LOOKUP(C91,ListaDeEstoque[DESCRIÇÃO],ListaDeEstoque[CÓD. do FORNECEDOR]))<>0,IF(LOOKUP(C91,ListaDeEstoque[DESCRIÇÃO],ListaDeEstoque[FORNECEDOR])=0,"NI",LOOKUP(C91,ListaDeEstoque[DESCRIÇÃO],ListaDeEstoque[FORNECEDOR])),"NI"),"") | H91: =IF(C91<>0,LOOKUP(C91,ListaDeEstoque[DESCRIÇÃO],ListaDeEstoque[Data do último ORÇAMENTO DO FORNECEDOR]),"") | I91: SIM | J91: 0 | K91: =IF(C91<>0,LOOKUP(C91,ListaDeEstoque[DESCRIÇÃO],ListaDeEstoque[Preço unitário]),0) -> 0 | L91: =IF(I91="SIM",K91*E91,J91*E91) -> 0
B92: 14 | G92: =IF(C92<>0,IF((LOOKUP(C92,ListaDeEstoque[DESCRIÇÃO],ListaDeEstoque[CÓD. do FORNECEDOR]))<>0,IF(LOOKUP(C92,ListaDeEstoque[DESCRIÇÃO],ListaDeEstoque[FORNECEDOR])=0,"NI",LOOKUP(C92,ListaDeEstoque[DESCRIÇÃO],ListaDeEstoque[FORNECEDOR])),"NI"),"") | H92: =IF(C92<>0,LOOKUP(C92,ListaDeEstoque[DESCRIÇÃO],ListaDeEstoque[Data do último ORÇAMENTO DO FORNECEDOR]),"") | I92: SIM | J92: 0 | K92: =IF(C92<>0,LOOKUP(C92,ListaDeEstoque[DESCRIÇÃO],ListaDeEstoque[Preço unitário]),0) -> 0 | L92: =IF(I92="SIM",K92*E92,J92*E92) -> 0
B93: 15 | G93: =IF(C93<>0,IF((LOOKUP(C93,ListaDeEstoque[DESCRIÇÃO],ListaDeEstoque[CÓD. do FORNECEDOR]))<>0,IF(LOOKUP(C93,ListaDeEstoque[DESCRIÇÃO],ListaDeEstoque[FORNECEDOR])=0,"NI",LOOKUP(C93,ListaDeEstoque[DESCRIÇÃO],ListaDeEstoque[FORNECEDOR])),"NI"),"") | H93: =IF(C93<>0,LOOKUP(C93,ListaDeEstoque[DESCRIÇÃO],ListaDeEstoque[Data do último ORÇAMENTO DO FORNECEDOR]),"") | I93: SIM | J93: 0 | K93: =IF(C93<>0,LOOKUP(C93,ListaDeEstoque[DESCRIÇÃO],ListaDeEstoque[Preço unitário]),0) -> 0 | L93: =IF(I93="SIM",K93*E93,J93*E93) -> 0
... B103: 25 | G103: =IF(C103<>0,IF((LOOKUP(C103,ListaDeEstoque[DESCRIÇÃO],ListaDeEstoque[CÓD. do FORNECEDOR]))<>0,IF(LOOKUP(C103,ListaDeEstoque[DESCRIÇÃO],ListaDeEstoque[FORNECEDOR])=0,"NI",LOOKUP(C103,ListaDeEstoque[DESCRIÇÃO],ListaDeEstoque[FORNECEDOR])),"NI"),"") | H103: =IF(C103<>0,LOOKUP(C103,ListaDeEstoque[DESCRIÇÃO],ListaDeEstoque[Data do último ORÇAMENTO DO FORNECEDOR]),"") | I103: SIM | J103: 0 | K103: =IF(C103<>0,LOOKUP(C103,ListaDeEstoque[DESCRIÇÃO],ListaDeEstoque[Preço unitário]),0) -> 0 | L103: =IF(I103="SIM",K103*E103,J103*E103) -> 0
D104: *Medidas em metro ou em quantidade escalar de peças | H104: =IF(SUM(H79:H103)>0,SMALL(H79:H103,1),TODAY()) -> 44531 | K104: Consumo | L104: =SUM(L79:L103) -> 106.704
B106: =B52+1 -> 4 | C106: EMBALAGENS (DE PRODUÇÃO)
B108: QUANTIDADE DE PEÇAS NA MESMA EMBALAGEM: | E108: 1
C110: Nome | E110: Quant* | F110: Observações | G110: FORNECEDOR | H110: Data de Orçamento do FORNECEDOR | I110: Preços da planilha AVIAMENTOS | J110: Valor (R$) | K110: Valor Automático | L110: TOTAL
B111: Nº
B112: 1 | C112: Cartão Agradecimento ANNA B | E112: 1 | G112: =IF(C112<>0,IF((LOOKUP(C112,ListaDeEstoque[DESCRIÇÃO],ListaDeEstoque[CÓD. do FORNECEDOR]))<>0,IF(LOOKUP(C112,ListaDeEstoque[DESCRIÇÃO],ListaDeEstoque[FORNECEDOR])=0,"NI",LOOKUP(C112,ListaDeEstoque[DESCRIÇÃO],ListaDeEstoque[FORNECEDOR])),"NI"),"") -> NI | H112: =IF(C112<>0,LOOKUP(C112,ListaDeEstoque[DESCRIÇÃO],ListaDeEstoque[Data do último ORÇAMENTO DO FORNECEDOR]),"") -> 44862 | I112: SIM | J112: 0 | K112: =IF(C112<>0,LOOKUP(C112,ListaDeEstoque[DESCRIÇÃO],ListaDeEstoque[Preço unitário]),0) -> 2.49 | L112: =IF(I112="SIM",K112*E112,J112*E112) -> 2.49
B113: 2 | C113: Embalagem Plastica | E113: 1 | G113: =IF(C113<>0,IF((LOOKUP(C113,ListaDeEstoque[DESCRIÇÃO],ListaDeEstoque[CÓD. do FORNECEDOR]))<>0,IF(LOOKUP(C113,ListaDeEstoque[DESCRIÇÃO],ListaDeEstoque[FORNECEDOR])=0,"NI",LOOKUP(C113,ListaDeEstoque[DESCRIÇÃO],ListaDeEstoque[FORNECEDOR])),"NI"),"") -> NI | H113: =IF(C113<>0,LOOKUP(C113,ListaDeEstoque[DESCRIÇÃO],ListaDeEstoque[Data do último ORÇAMENTO DO FORNECEDOR]),"") -> 44692 | I113: SIM | J113: 0 | K113: =IF(C113<>0,LOOKUP(C113,ListaDeEstoque[DESCRIÇÃO],ListaDeEstoque[Preço unitário]),0) -> 0.85 | L113: =IF(I113="SIM",K113*E113,J113*E113) -> 0.85
B114: 3 | C114: Etiqueta Adesiva LAÇO | E114: 1 | G114: =IF(C114<>0,IF((LOOKUP(C114,ListaDeEstoque[DESCRIÇÃO],ListaDeEstoque[CÓD. do FORNECEDOR]))<>0,IF(LOOKUP(C114,ListaDeEstoque[DESCRIÇÃO],ListaDeEstoque[FORNECEDOR])=0,"NI",LOOKUP(C114,ListaDeEstoque[DESCRIÇÃO],ListaDeEstoque[FORNECEDOR])),"NI"),"") -> NI | H114: =IF(C114<>0,LOOKUP(C114,ListaDeEstoque[DESCRIÇÃO],ListaDeEstoque[Data do último ORÇAMENTO DO FORNECEDOR]),"") -> 44531 | I114: SIM | J114: 0 | K114: =IF(C114<>0,LOOKUP(C114,ListaDeEstoque[DESCRIÇÃO],ListaDeEstoque[Preço unitário]),0) -> 2.5 | L114: =IF(I114="SIM",K114*E114,J114*E114) -> 2.5
B115: 4 | C115: Papel Seda | E115: 1 | G115: =IF(C115<>0,IF((LOOKUP(C115,ListaDeEstoque[DESCRIÇÃO],ListaDeEstoque[CÓD. do FORNECEDOR]))<>0,IF(LOOKUP(C115,ListaDeEstoque[DESCRIÇÃO],ListaDeEstoque[FORNECEDOR])=0,"NI",LOOKUP(C115,ListaDeEstoque[DESCRIÇÃO],ListaDeEstoque[FORNECEDOR])),"NI"),"") -> NI | H115: =IF(C115<>0,LOOKUP(C115,ListaDeEstoque[DESCRIÇÃO],ListaDeEstoque[Data do último ORÇAMENTO DO FORNECEDOR]),"") -> 43252 | I115: SIM | J115: 0 | K115: =IF(C115<>0,LOOKUP(C115,ListaDeEstoque[DESCRIÇÃO],ListaDeEstoque[Preço unitário]),0) -> 0.02 | L115: =IF(I115="SIM",K115*E115,J115*E115) -> 0.02
B116: 5 | G116: =IF(C116<>0,IF((LOOKUP(C116,ListaDeEstoque[DESCRIÇÃO],ListaDeEstoque[CÓD. do FORNECEDOR]))<>0,IF(LOOKUP(C116,ListaDeEstoque[DESCRIÇÃO],ListaDeEstoque[FORNECEDOR])=0,"NI",LOOKUP(C116,ListaDeEstoque[DESCRIÇÃO],ListaDeEstoque[FORNECEDOR])),"NI"),"") | H116: =IF(C116<>0,LOOKUP(C116,ListaDeEstoque[DESCRIÇÃO],ListaDeEstoque[Data do último ORÇAMENTO DO FORNECEDOR]),"") | I116: SIM | J116: 0 | K116: =IF(C116<>0,LOOKUP(C116,ListaDeEstoque[DESCRIÇÃO],ListaDeEstoque[Preço unitário]),0) -> 0 | L116: =IF(I116="SIM",K116*E116,J116*E116) -> 0
B117: 6 | G117: =IF(C117<>0,IF((LOOKUP(C117,ListaDeEstoque[DESCRIÇÃO],ListaDeEstoque[CÓD. do FORNECEDOR]))<>0,IF(LOOKUP(C117,ListaDeEstoque[DESCRIÇÃO],ListaDeEstoque[FORNECEDOR])=0,"NI",LOOKUP(C117,ListaDeEstoque[DESCRIÇÃO],ListaDeEstoque[FORNECEDOR])),"NI"),"") | H117: =IF(C117<>0,LOOKUP(C117,ListaDeEstoque[DESCRIÇÃO],ListaDeEstoque[Data do último ORÇAMENTO DO FORNECEDOR]),"") | I117: SIM | J117: 0 | K117: =IF(C117<>0,LOOKUP(C117,ListaDeEstoque[DESCRIÇÃO],ListaDeEstoque[Preço unitário]),0) -> 0 | L117: =IF(I117="SIM",K117*E117,J117*E117) -> 0
B118: 7 | G118: =IF(C118<>0,IF((LOOKUP(C118,ListaDeEstoque[DESCRIÇÃO],ListaDeEstoque[CÓD. do FORNECEDOR]))<>0,IF(LOOKUP(C118,ListaDeEstoque[DESCRIÇÃO],ListaDeEstoque[FORNECEDOR])=0,"NI",LOOKUP(C118,ListaDeEstoque[DESCRIÇÃO],ListaDeEstoque[FORNECEDOR])),"NI"),"") | H118: =IF(C118<>0,LOOKUP(C118,ListaDeEstoque[DESCRIÇÃO],ListaDeEstoque[Data do último ORÇAMENTO DO FORNECEDOR]),"") | I118: SIM | J118: 0 | K118: =IF(C118<>0,LOOKUP(C118,ListaDeEstoque[DESCRIÇÃO],ListaDeEstoque[Preço unitário]),0) -> 0 | L118: =IF(I118="SIM",K118*E118,J118*E118) -> 0
B119: 8 | G119: =IF(C119<>0,IF((LOOKUP(C119,ListaDeEstoque[DESCRIÇÃO],ListaDeEstoque[CÓD. do FORNECEDOR]))<>0,IF(LOOKUP(C119,ListaDeEstoque[DESCRIÇÃO],ListaDeEstoque[FORNECEDOR])=0,"NI",LOOKUP(C119,ListaDeEstoque[DESCRIÇÃO],ListaDeEstoque[FORNECEDOR])),"NI"),"") | H119: =IF(C119<>0,LOOKUP(C119,ListaDeEstoque[DESCRIÇÃO],ListaDeEstoque[Data do último ORÇAMENTO DO FORNECEDOR]),"") | I119: SIM | J119: 0 | K119: =IF(C119<>0,LOOKUP(C119,ListaDeEstoque[DESCRIÇÃO],ListaDeEstoque[Preço unitário]),0) -> 0 | L119: =IF(I119="SIM",K119*E119,J119*E119) -> 0
D120: *Medidas em metro ou em quantidade escalar de peças | H120: =IF(SUM(H112:H119)>0,SMALL(H112:H119,1),TODAY()) -> 43252 | K120: Consumo | L120: =SUM(L112:L119)/E108 -> 5.86
E123: CUSTOS SUBTOTAL INDIVIDUAL: | H123: =K42+L60+L104+L120+IF(D19="NÃO",0,IF(E62="SIM",L72,0)) -> 121.51078
B125: =B106+1 -> 5 | C125: PRECIFICAÇÃO
E127: Mínimo sugerido (LOTE IDEAL): | H127: =MODELAGEM!K8 -> 35
E128: Quantidade a Ser Produzida (LOTE REAL): | H128: 20
E129: Consumo de Material: | H129: =H128*H123 -> 2430.2155
E130: MARKUP - Fator Multiplicador: | H130: 3.5
...

Sheet CÓPIA (exportar imagem)
D5: CÓPIA PARA EXPORTAÇÃO - PREÇO: Planilha de Precificação
D6: ='Programação Individual'!B21 -> VMORDEKAI
E7: ='NOME + Nº'!C181 -> PREÇO FINAL
J8: DATA: | K8: ='NOME + Nº'!L5 -> 45182 | P8: LEGENDA
E9: ='NOME + Nº'!D184 -> REFERÊNCIA | F9: ='NOME + Nº'!E184 -> REF. NOME + Nº - 15H x 10B x 5L (cm) | P9: Validade do Orçamento
P10: STATUS | R10: DIAS | T10: (HOJE - PRAZO)
F11: ='NOME + Nº'!E186 -> DESCONTO (%) | I11: ='NOME + Nº'!H186 -> 0 | P11: Prazo Máximo | R11: ='NOME + Nº'!K15 -> 90 | T11: =TODAY()-R11 -> 45650
P12: Fase Inicial | R12: ='NOME + Nº'!K16 -> 7 | T12: =TODAY()-R12 -> 45733
E13: ='NOME + Nº'!D188 -> QUANTIDADE | F13: ='NOME + Nº'!E188 -> 20 | H13: ='NOME + Nº'!G188 -> BASE | I13: ='NOME + Nº'!H188 -> FINAL | J13: ='NOME + Nº'!I188 -> OFERTA | P13: Desenvolvimento | R13: ='NOME + Nº'!K17 -> 30 | T13: =TODAY()-R13 -> 45710
E14: ='NOME + Nº'!D189 -> LOTE | F14: ='NOME + Nº'!E189 -> Valor Base + Acréscimos finais | H14: ='NOME + Nº'!G189 -> 8505.7544 | I14: ='NOME + Nº'!H189 -> 8505.7544 | J14: ='NOME + Nº'!I189 -> 8505.7544 | P14: Limite | R14: ='NOME + Nº'!K18 -> 60 | T14: =TODAY()-R14 -> 45680
P15: Dead Line | R15: ='NOME + Nº'!K19 -> 90 | T15: =TODAY()-R15 -> 45650
E16: ='NOME + Nº'!D191 -> UNITÁTIO | F16: ='NOME + Nº'!E191 -> Valor Base + Acréscimos finais | H16: ='NOME + Nº'!G191 -> 425.28772 | I16: ='NOME + Nº'!H191 -> 425.28772 | J16: ='NOME + Nº'!I191 -> 425.28772
E18: Data | F18: Nota | J18: Valor (R$)
E19: =IF('NOME + Nº'!D194=0,"",'NOME + Nº'!D194) | F19: =IF('NOME + Nº'!E194=0,"",'NOME + Nº'!E194) | J19: =IF('NOME + Nº'!I194=0,"",'NOME + Nº'!I194)
E20: =IF('NOME + Nº'!D195=0,"",'NOME + Nº'!D195) | F20: =IF('NOME + Nº'!E195=0,"",'NOME + Nº'!E195) | J20: =IF('NOME + Nº'!I195=0,"",'NOME + Nº'!I195)
E21: =IF('NOME + Nº'!D196=0,"",'NOME + Nº'!D196) | F21: =IF('NOME + Nº'!E196=0,"",'NOME + Nº'!E196) | J21: =IF('NOME + Nº'!I196=0,"",'NOME + Nº'!I196)
E22: =IF('NOME + Nº'!D197=0,"",'NOME + Nº'!D197) | F22: =IF('NOME + Nº'!E197=0,"",'NOME + Nº'!E197) | J22: =IF('NOME + Nº'!I197=0,"",'NOME + Nº'!I197)
E23: =IF('NOME + Nº'!D198=0,"",'NOME + Nº'!D198) | F23: =IF('NOME + Nº'!E198=0,"",'NOME + Nº'!E198) | J23: =IF('NOME + Nº'!I198=0,"",'NOME + Nº'!I198)
H24: =IF('NOME + Nº'!G199=0,"",'NOME + Nº'!G199)
D26: CÓPIA PARA EXPORTAÇÃO - CONSUMO DE MATERIAIS: Planilha de ENFESTO
D27: ='Programação Individual'!B21 -> VMORDEKAI
E28: =ENFESTO!W10 -> REF. NOME + Nº - 15H x 10B x 5L (cm)
E29: CONSUMO DE TECIDO POR MOLDE
E30: =IF('NOME + Nº'!$C$32="NÃO","!!MODELAGEM não atualizada!!","") | I30: =J8 -> DATA: | J30: =K8 -> 45182
F31: ENCOMENDA
E32: LOTE | F32: =ENFESTO!K18 -> 20
E33: LISTA DE TECIDOS | I33: Soma Total
E34: TECIDO | F34: Descrição | G34: VALOR (R$/m) | H34: Largura | I34: Metros | J34: R$
D35: 1 | E35: =ENFESTO!J21 -> Tec. Externo | F35: =ENFESTO!K21 -> Aquablock | G35: =ENFESTO!L21 -> 49.9 | H35: =ENFESTO!M21 -> 140 | I35: =ENFESTO!N21 -> 4.1447059 | J35: =ENFESTO!O21 -> 206.82082 | AR35: =ENFESTO!Y289 -> FICHA DE ENFESTO & CORTE
D36: 2 | E36: =ENFESTO!J22 | F36: =ENFESTO!K22 | G36: =ENFESTO!L22 | H36: =ENFESTO!M22 | I36: =ENFESTO!N22 -> 0 | J36: =ENFESTO!O22 -> 0
D37: 3 | E37: =ENFESTO!J23 | F37: =ENFESTO!K23 | G37: =ENFESTO!L23 | H37: =ENFESTO!M23 | I37: =ENFESTO!N23 -> 0 | J37: =ENFESTO!O23 -> 0 | AR37: =IF('NOME + Nº'!$C$33="NÃO","!!ENFESTO não atualizado!!",IF(ENFESTO!Y291=0,"",ENFESTO!Y291)) -> !!ENFESTO não atualizado!!
D38: 4 | E38: =ENFESTO!J24 | F38: =ENFESTO!K24 | G38: =ENFESTO!L24 | H38: =ENFESTO!M24 | I38: =ENFESTO!N24 -> 0 | J38: =ENFESTO!O24 -> 0
D39: 5 | E39: =ENFESTO!J25 | F39: =ENFESTO!K25 | G39: =ENFESTO!L25 | H39: =ENFESTO!M25 | I39: =ENFESTO!N25 -> 0 | J39: =ENFESTO!O25 -> 0 | AR39: MATERIAL | AT39: DESCRIÇÃO | AZ39: Valor | BA39: Obs.
D40: 6 | E40: =ENFESTO!J26 | F40: =ENFESTO!K26 | G40: =ENFESTO!L26 | H40: =ENFESTO!M26 | I40: =ENFESTO!N26 -> 0 | J40: =ENFESTO!O26 -> 0 | AQ40: 1 | AR40: =IF(ENFESTO!Y294=0,"",ENFESTO!Y294) -> Tec. Principal | AT40: =IF(ENFESTO!AA294=0,"",ENFESTO!AA294) -> EX.: No ENFESTO 1 foi posicionado moldes 1,2,6, alinhando posições de fio e maximizando aproveitamento. | AZ40: =IF(ENFESTO!AG294=0,"",ENFESTO!AG294) -> 60cm | BA40: =IF(ENFESTO!AH294=0,"",ENFESTO!AH294)
D41: 7 | E41: =ENFESTO!J27 | F41: =ENFESTO!K27 | G41: =ENFESTO!L27 | H41: =ENFESTO!M27 | I41: =ENFESTO!N27 -> 0 | J41: =ENFESTO!O27 -> 0
F43: CONSUMO TOTAL | I43: =ENFESTO!N29 -> 4.1447059 | J43: =ENFESTO!O29 -> 206.82082
AQ44: 2 | AR44: Tec. Principal
D46: ='Programação Individual'!B21 -> VMORDEKAI
E47: =ENFESTO!W10 -> REF. NOME + Nº - 15H x 10B x 5L (cm) | AQ47: 3 | AR47: Tec. Principal
E48: =ENFESTO!J34 -> CONSUMO DE TECIDO POR ENFESTO
E49: =IF('NOME + Nº'!$C$33="NÃO","!!ENFESTO não atualizado!!","") -> !!ENFESTO não atualizado!! | I49: DATA: | J49: =K8 -> 45182
F50: ENCOMENDA | AQ50: 4 | AR50: Tec. Principal
E51: LOTE | F51: =ENFESTO!K37 -> 20
E52: LISTA DE TECIDOS | I52: Soma Total
E53: TECIDO | F53: Descrição | G53: VALOR (R$/m) | H53: Largura | I53: Metros | J53: R$ | AQ53: 5 | AR53: Tec. Principal
D54: 1 | E54: =ENFESTO!J40 | F54: =ENFESTO!K40 | G54: =ENFESTO!L40 | H54: =ENFESTO!M40 | I54: =ENFESTO!N40 -> 0 | J54: =ENFESTO!O40 -> 0
D55: 2 | E55: =ENFESTO!J41 | F55: =ENFESTO!K41 | G55: =ENFESTO!L41 | H55: =ENFESTO!M41 | I55: =ENFESTO!N41 -> 0 | J55: =ENFESTO!O41 -> 0
D56: 3 | E56: =ENFESTO!J42 | F56: =ENFESTO!K42 | G56: =ENFESTO!L42 | H56: =ENFESTO!M42 | I56: =ENFESTO!N42 -> 0 | J56: =ENFESTO!O42 -> 0 | AQ56: 6 | AR56: Tec. Principal
D57: 4 | E57: =ENFESTO!J43 | F57: =ENFESTO!K43 | G57: =ENFESTO!L43 | H57: =ENFESTO!M43 | I57: =ENFESTO!N43 -> 0 | J57: =ENFESTO!O43 -> 0
D58: 5 | E58: =ENFESTO!J44 | F58: =ENFESTO!K44 | G58: =ENFESTO!L44 | H58: =ENFESTO!M44 | I58: =ENFESTO!N44 -> 0 | J58: =ENFESTO!O44 -> 0
D59: 6 | E59: =ENFESTO!J45 | F59: =ENFESTO!K45 | G59: =ENFESTO!L45 | H59: =ENFESTO!M45 | I59: =ENFESTO!N45 -> 0 | J59: =ENFESTO!O45 -> 0
D60: 7 | E60: =ENFESTO!J46 | F60: =ENFESTO!K46 | G60: =ENFESTO!L46 | H60: =ENFESTO!M46 | I60: =ENFESTO!N46 -> 0 | J60: =ENFESTO!O46 -> 0
F62: CONSUMO TOTAL | I62: =ENFESTO!N48 -> 0 | J62: =ENFESTO!O48 -> 0
D65: =D46 -> VMORDEKAI
D66: =E47 -> REF. NOME + Nº - 15H x 10B x 5L (cm)
D67: =E48 -> CONSUMO DE TECIDO POR ENFESTO
D69: Quantidade a Ser Produzida (LOTE REAL): | G69: ='NOME + Nº'!H128 -> 20
D72: ='NOME + Nº'!#REF!+1 -> #REF! | E72: AVIAMENTOS
E74: VIVO PRONTO: | G74: =IF('NOME + Nº'!E54=0,"",'NOME + Nº'!E54) -> NÃO | I74: Preços da planilha AVIAMENTOS: | L74: SIM
G76: DESCRIÇÃO | H76: Valor (R$) | I76: Valor Automático | J76: Observações | K76: Data FORNECEDOR | L76: Quant (m)* | M76: Consumo*
E77: =IF('NOME + Nº'!C58=0,"",'NOME + Nº'!C58) -> CORDÃO PARA VIVO: | G77: =IF('NOME + Nº'!E58=0,"",'NOME + Nº'!E58) -> Cordão Algodão São José 5mm 50m | H77: =IF('NOME + Nº'!F58=0,"",'NOME + Nº'!F58) | I77: =IF('NOME + Nº'!J58=0,"",'NOME + Nº'!J58) -> 2.49 | J77: =IF('NOME + Nº'!E60=0,"",'NOME + Nº'!E60) | K77: =IF('NOME + Nº'!I58=0,"",'NOME + Nº'!I58) -> 44862 | L77: =IF('NOME + Nº'!K58=0,"",'NOME + Nº'!K58*G69) -> 21.249556 | M77: =IF(L74="SIM",IF('NOME + Nº'!#REF!="SIM",L77*I77,0),L77*H77) -> #REF!
E78: =IF('NOME + Nº'!C59=0,"",'NOME + Nº'!C59) -> MATERIAL: | G78: =IF('NOME + Nº'!E59=0,"",'NOME + Nº'!E59) -> Tec. Vivo | H78: =IF('NOME + Nº'!F59=0,"",'NOME + Nº'!F59) | I78: =IF('NOME + Nº'!J59=0,"",'NOME + Nº'!J59) -> 49.9 | J78: =IF('NOME + Nº'!#REF!=0,"",'NOME + Nº'!#REF!) -> #REF! | K78: =IF('NOME + Nº'!I59=0,"",'NOME + Nº'!I59) -> ** | L78: =IF('NOME + Nº'!K59=0,"",'NOME + Nº'!K59*G69) -> 0.46106191 | M78: =IF('NOME + Nº'!L59=0,"",'NOME + Nº'!L59) -> **
L79: Consumo | M79: =SUM(M77:M78) -> #REF!
E81: ALÇA PRONTA: | G81: ='NOME + Nº'!E62 -> NÃO
E83: ALÇA Equivalente | F83: LARGURA | G83: Quant (m)* | H83: Observações | I83: FORNECEDOR | J83: Data de Orçamento do FORNECEDOR | K83: Disponível em ESTOQUE | L83: Valor Automático | M83: Consumo** | O83: Quant. LOTE
D84: Nº
D85: 1 | E85: =IF('NOME + Nº'!C66=0,"",'NOME + Nº'!C66) -> Alça ANNA B 30mm | F85: =IF('NOME + Nº'!D66=0,"",'NOME + Nº'!D66) -> #N/A | G85: =IF('NOME + Nº'!E66*O85=0,"",'NOME + Nº'!E66*O85) -> 2.48 | H85: =IF('NOME + Nº'!F66=0,"",'NOME + Nº'!F66) | I85: =IF('NOME + Nº'!G66=0,"",'NOME + Nº'!G66) -> #N/A | J85: =IF('NOME + Nº'!H66=0,"",'NOME + Nº'!H66) -> #N/A | L85: =IF('NOME + Nº'!K66=0,"",'NOME + Nº'!K66) -> ** | M85: =IF(G81="NÃO","**",IF('NOME + Nº'!L66*(O85-K85)=0,"",'NOME + Nº'!L66*O85)) -> ** | O85: =G69 -> 20
D86: 2 | E86: =IF('NOME + Nº'!C67=0,"",'NOME + Nº'!C67) | F86: =IF('NOME + Nº'!D67=0,"",'NOME + Nº'!D67) | G86: =IF('NOME + Nº'!E67*O86=0,"",'NOME + Nº'!E67*O86) | H86: =IF('NOME + Nº'!F67=0,"",'NOME + Nº'!F67) | I86: =IF('NOME + Nº'!G67=0,"",'NOME + Nº'!G67) | J86: =IF('NOME + Nº'!H67=0,"",'NOME + Nº'!H67) | L86: =IF('NOME + Nº'!K67=0,"",'NOME + Nº'!K67) -> ** | M86: =IF(G81="NÃO","**",IF('NOME + Nº'!L67*(O86-K86)=0,"",'NOME + Nº'!L67*(O86-K86))) -> ** | O86: =O85 -> 20
D87: 3 | E87: =IF('NOME + Nº'!C68=0,"",'NOME + Nº'!C68) | F87: =IF('NOME + Nº'!D68=0,"",'NOME + Nº'!D68) | G87: =IF('NOME + Nº'!E68*O87=0,"",'NOME + Nº'!E68*O87) | H87: =IF('NOME + Nº'!F68=0,"",'NOME + Nº'!F68) | I87: =IF('NOME + Nº'!G68=0,"",'NOME + Nº'!G68) | J87: =IF('NOME + Nº'!H68=0,"",'NOME + Nº'!H68) | L87: =IF('NOME + Nº'!K68=0,"",'NOME + Nº'!K68) -> ** | M87: =IF(G81="NÃO","**",IF('NOME + Nº'!L68*(O87-K87)=0,"",'NOME + Nº'!L68*(O87-K87))) -> ** | O87: =O86 -> 20
D88: 4 | E88: =IF('NOME + Nº'!C69=0,"",'NOME + Nº'!C69) | F88: =IF('NOME + Nº'!D69=0,"",'NOME + Nº'!D69) | G88: =IF('NOME + Nº'!E69*O88=0,"",'NOME + Nº'!E69*O88) | H88: =IF('NOME + Nº'!F69=0,"",'NOME + Nº'!F69) | I88: =IF('NOME + Nº'!G69=0,"",'NOME + Nº'!G69) | J88: =IF('NOME + Nº'!H69=0,"",'NOME + Nº'!H69) | L88: =IF('NOME + Nº'!K69=0,"",'NOME + Nº'!K69) -> ** | M88: =IF(G81="NÃO","**",IF('NOME + Nº'!L69*(O88-K88)=0,"",'NOME + Nº'!L69*(O88-K88))) -> ** | O88: =O87 -> 20
D89: 5 | E89: =IF('NOME + Nº'!C70=0,"",'NOME + Nº'!C70) | F89: =IF('NOME + Nº'!D70=0,"",'NOME + Nº'!D70) | G89: =IF('NOME + Nº'!E70*O89=0,"",'NOME + Nº'!E70*O89) | H89: =IF('NOME + Nº'!F70=0,"",'NOME + Nº'!F70) | I89: =IF('NOME + Nº'!G70=0,"",'NOME + Nº'!G70) | J89: =IF('NOME + Nº'!H70=0,"",'NOME + Nº'!H70) | K89: =IF('NOME + Nº'!I70=0,"",'NOME + Nº'!I70) -> SIM | L89: =IF('NOME + Nº'!K70=0,"",'NOME + Nº'!K70) -> ** | M89: =IF(G81="NÃO","**",IF('NOME + Nº'!L70*O89=0,"",'NOME + Nº'!L70*O89)) -> ** | O89: =O88 -> 20
D90: 6 | E90: =IF('NOME + Nº'!C71=0,"",'NOME + Nº'!C71) | F90: =IF('NOME + Nº'!D71=0,"",'NOME + Nº'!D71) | G90: =IF('NOME + Nº'!E71*O90=0,"",'NOME + Nº'!E71*O90) | H90: =IF('NOME + Nº'!F71=0,"",'NOME + Nº'!F71) | I90: =IF('NOME + Nº'!G71=0,"",'NOME + Nº'!G71) | J90: =IF('NOME + Nº'!H71=0,"",'NOME + Nº'!H71) | K90: =IF('NOME + Nº'!I71=0,"",'NOME + Nº'!I71) -> SIM | L90: =IF('NOME + Nº'!K71=0,"",'NOME + Nº'!K71) -> ** | M90: =IF(G81="NÃO","**",IF('NOME + Nº'!L71*O90=0,"",'NOME + Nº'!L71*O90)) -> ** | O90: =O89 -> 20
J91: =IF(SUM(J85:J90)>0,SMALL(J85:J90,1),TODAY()) -> #N/A | L91: Consumo | M91: =IF('NOME + Nº'!E62="SIM",SUM(M85:M90),MODELAGEM!EI22*G69) -> 14.621752
H92: *Valores (em azul) definidos na planilha de MODELAGEM
H93: =IF(G81="NÃO","** Valores de acordo com material específico definido na MODELAGEM","**Na planilha MODELAGEM, verificar possibilidade de moldes duplicados") -> ** Valores de acordo com material específico definido na MODELAGEM
E95: OUTROS AVIAMENTOS
E96: Nome | G96: Quant* | H96: Observações | I96: FORNECEDOR | J96: Data de Orçamento do FORNECEDOR | K96: Disponível em ESTOQUE | L96: Valor Automático | M96: TOTAL | O96: Quant. LOTE
D97: Nº
D98: 1 | E98: =IF('NOME + Nº'!C79=0,"",'NOME + Nº'!C79) -> Caneta Mágica | G98: =IF('NOME + Nº'!E79*O98=0,"",'NOME + Nº'!E79*O98) -> 1 | H98: =IF('NOME + Nº'!F79=0,"",'NOME + Nº'!F79) -> 5% de uma caneta por peça | I98: =IF('NOME + Nº'!G79=0,"",'NOME + Nº'!G79) -> NI | J98: =IF('NOME + Nº'!H79=0,"",'NOME + Nº'!H79) -> 44531 | L98: =IF('NOME + Nº'!K79=0,"",'NOME + Nº'!K79) -> 0.48 | M98: =IF('NOME + Nº'!L79*(O98-K98)=0,"",'NOME + Nº'!L79*(O98-K98)) -> 0.48 | O98: =G69 -> 20
D99: 2 | E99: =IF('NOME + Nº'!C80=0,"",'NOME + Nº'!C80) -> Rebite N.1 (5,5mm) (Níquel) (macho e fêmea) | G99: =IF('NOME + Nº'!E80*O99=0,"",'NOME + Nº'!E80*O99) -> 100 | H99: =IF('NOME + Nº'!F80=0,"",'NOME + Nº'!F80) | I99: =IF('NOME + Nº'!G80=0,"",'NOME + Nº'!G80) -> NI | J99: =IF('NOME + Nº'!H80=0,"",'NOME + Nº'!H80) -> 44862 | L99: =IF('NOME + Nº'!K80=0,"",'NOME + Nº'!K80) -> 20.8 | M99: =IF('NOME + Nº'!L80*(O99-K99)=0,"",'NOME + Nº'!L80*(O99-K99)) -> 2080 | O99: =O98 -> 20
D100: 3 | E100: =IF('NOME + Nº'!C81=0,"",'NOME + Nº'!C81) -> Ziper Nylon (pacote) 30mm | G100: =IF('NOME + Nº'!E81*O100=0,"",'NOME + Nº'!E81*O100) -> 40 | H100: =IF('NOME + Nº'!F81=0,"",'NOME + Nº'!F81) | I100: =IF('NOME + Nº'!G81=0,"",'NOME + Nº'!G81) -> NI | J100: =IF('NOME + Nº'!H81=0,"",'NOME + Nº'!H81) -> 44862 | L100: =IF('NOME + Nº'!K81=0,"",'NOME + Nº'!K81) -> 1.34 | M100: =IF('NOME + Nº'!L81*(O100-K100)=0,"",'NOME + Nº'!L81*(O100-K100)) -> 53.6 | O100: =O99 -> 20
D101: 4 | E101: =IF('NOME + Nº'!C82=0,"",'NOME + Nº'!C82) | G101: =IF('NOME + Nº'!E82*O101=0,"",'NOME + Nº'!E82*O101) | H101: =IF('NOME + Nº'!F82=0,"",'NOME + Nº'!F82) | I101: =IF('NOME + Nº'!G82=0,"",'NOME + Nº'!G82) | J101: =IF('NOME + Nº'!H82=0,"",'NOME + Nº'!H82) | L101: =IF('NOME + Nº'!K82=0,"",'NOME + Nº'!K82) | M101: =IF('NOME + Nº'!L82*(O101-K101)=0,"",'NOME + Nº'!L82*(O101-K101)) | O101: =O100 -> 20
D102: 5 | E102: =IF('NOME + Nº'!C83=0,"",'NOME + Nº'!C83) | G102: =IF('NOME + Nº'!E83*O102=0,"",'NOME + Nº'!E83*O102) | H102: =IF('NOME + Nº'!F83=0,"",'NOME + Nº'!F83) | I102: =IF('NOME + Nº'!G83=0,"",'NOME + Nº'!G83) | J102: =IF('NOME + Nº'!H83=0,"",'NOME + Nº'!H83) | L102: =IF('NOME + Nº'!K83=0,"",'NOME + Nº'!K83) | M102: =IF('NOME + Nº'!L83*(O102-K102)=0,"",'NOME + Nº'!L83*(O102-K102)) | O102: =O101 -> 20
D103: 6 | E103: =IF('NOME + Nº'!C84=0,"",'NOME + Nº'!C84) | G103: =IF('NOME + Nº'!E84*O103=0,"",'NOME + Nº'!E84*O103) | H103: =IF('NOME + Nº'!F84=0,"",'NOME + Nº'!F84) | I103: =IF('NOME + Nº'!G84=0,"",'NOME + Nº'!G84) | J103: =IF('NOME + Nº'!H84=0,"",'NOME + Nº'!H84) | L103: =IF('NOME + Nº'!K84=0,"",'NOME + Nº'!K84) | M103: =IF('NOME + Nº'!L84*(O103-K103)=0,"",'NOME + Nº'!L84*(O103-K103)) | O103: =O102 -> 20
D104: 7 | E104: =IF('NOME + Nº'!C85=0,"",'NOME + Nº'!C85) | G104: =IF('NOME + Nº'!E85*O104=0,"",'NOME + Nº'!E85*O104) | H104: =IF('NOME + Nº'!F85=0,"",'NOME + Nº'!F85) | I104: =IF('NOME + Nº'!G85=0,"",'NOME + Nº'!G85) | J104: =IF('NOME + Nº'!H85=0,"",'NOME + Nº'!H85) | L104: =IF('NOME + Nº'!K85=0,"",'NOME + Nº'!K85) | M104: =IF('NOME + Nº'!L85*(O104-K104)=0,"",'NOME + Nº'!L85*(O104-K104)) | O104: =O103 -> 20
D105: 8 | E105: =IF('NOME + Nº'!C86=0,"",'NOME + Nº'!C86) | G105: =IF('NOME + Nº'!E86*O105=0,"",'NOME + Nº'!E86*O105) | H105: =IF('NOME + Nº'!F86=0,"",'NOME + Nº'!F86) | I105: =IF('NOME + Nº'!G86=0,"",'NOME + Nº'!G86) | J105: =IF('NOME + Nº'!H86=0,"",'NOME + Nº'!H86) | L105: =IF('NOME + Nº'!K86=0,"",'NOME + Nº'!K86) | M105: =IF('NOME + Nº'!L86*(O105-K105)=0,"",'NOME + Nº'!L86*(O105-K105)) | O105: =O104 -> 20
D106: 9 | E106: =IF('NOME + Nº'!C87=0,"",'NOME + Nº'!C87) | G106: =IF('NOME + Nº'!E87*O106=0,"",'NOME + Nº'!E87*O106) | H106: =IF('NOME + Nº'!F87=0,"",'NOME + Nº'!F87) | I106: =IF('NOME + Nº'!G87=0,"",'NOME + Nº'!G87) | J106: =IF('NOME + Nº'!H87=0,"",'NOME + Nº'!H87) | L106: =IF('NOME + Nº'!K87=0,"",'NOME + Nº'!K87) | M106: =IF('NOME + Nº'!L87*(O106-K106)=0,"",'NOME + Nº'!L87*(O106-K106)) | O106: =O105 -> 20
D107: 10 | E107: =IF('NOME + Nº'!C88=0,"",'NOME + Nº'!C88) | G107: =IF('NOME + Nº'!E88*O107=0,"",'NOME + Nº'!E88*O107) | H107: =IF('NOME + Nº'!F88=0,"",'NOME + Nº'!F88) | I107: =IF('NOME + Nº'!G88=0,"",'NOME + Nº'!G88) | J107: =IF('NOME + Nº'!H88=0,"",'NOME + Nº'!H88) | L107: =IF('NOME + Nº'!K88=0,"",'NOME + Nº'!K88) | M107: =IF('NOME + Nº'!L88*(O107-K107)=0,"",'NOME + Nº'!L88*(O107-K107)) | O107: =O106 -> 20
D108: 11 | E108: =IF('NOME + Nº'!C89=0,"",'NOME + Nº'!C89) | G108: =IF('NOME + Nº'!E89*O108=0,"",'NOME + Nº'!E89*O108) | H108: =IF('NOME + Nº'!F89=0,"",'NOME + Nº'!F89) | I108: =IF('NOME + Nº'!G89=0,"",'NOME + Nº'!G89) | J108: =IF('NOME + Nº'!H89=0,"",'NOME + Nº'!H89) | L108: =IF('NOME + Nº'!K89=0,"",'NOME + Nº'!K89) | M108: =IF('NOME + Nº'!L89*(O108-K108)=0,"",'NOME + Nº'!L89*(O108-K108)) | O108: =O107 -> 20
D109: 12 | E109: =IF('NOME + Nº'!C90=0,"",'NOME + Nº'!C90) | G109: =IF('NOME + Nº'!E90*O109=0,"",'NOME + Nº'!E90*O109) | H109: =IF('NOME + Nº'!F90=0,"",'NOME + Nº'!F90) | I109: =IF('NOME + Nº'!G90=0,"",'NOME + Nº'!G90) | J109: =IF('NOME + Nº'!H90=0,"",'NOME + Nº'!H90) | L109: =IF('NOME + Nº'!K90=0,"",'NOME + Nº'!K90) | M109: =IF('NOME + Nº'!L90*(O109-K109)=0,"",'NOME + Nº'!L90*(O109-K109)) | O109: =O108 -> 20
D110: 13 | E110: =IF('NOME + Nº'!C91=0,"",'NOME + Nº'!C91) | G110: =IF('NOME + Nº'!E91*O110=0,"",'NOME + Nº'!E91*O110) | H110: =IF('NOME + Nº'!F91=0,"",'NOME + Nº'!F91) | I110: =IF('NOME + Nº'!G91=0,"",'NOME + Nº'!G91) | J110: =IF('NOME + Nº'!H91=0,"",'NOME + Nº'!H91) | L110: =IF('NOME + Nº'!K91=0,"",'NOME + Nº'!K91) | M110: =IF('NOME + Nº'!L91*(O110-K110)=0,"",'NOME + Nº'!L91*(O110-K110)) | O110: =O109 -> 20
... D122: 25 | E122: =IF('NOME + Nº'!C103=0,"",'NOME + Nº'!C103) | G122: =IF('NOME + Nº'!E103*O122=0,"",'NOME + Nº'!E103*O122) | H122: =IF('NOME + Nº'!F103=0,"",'NOME + Nº'!F103) | I122: =IF('NOME + Nº'!G103=0,"",'NOME + Nº'!G103) | J122: =IF('NOME + Nº'!H103=0,"",'NOME + Nº'!H103) | L122: =IF('NOME + Nº'!K103=0,"",'NOME + Nº'!K103) | M122: =IF('NOME + Nº'!L103*(O122-K122)=0,"",'NOME + Nº'!L103*(O122-K122)) | O122: =O121 -> 20
F123: *Medidas em metro ou em quantidade escalar de peças | J123: =IF(SUM(J98:J122)>0,SMALL(J98:J122,1),TODAY()) -> 44531 | L123: Consumo | M123: =SUM(M98:M122) -> 2134.08
D125: =D72+1 -> #REF! | E125: EMBALAGENS (DE PRODUÇÃO)
D127: QUANTIDADE DE PEÇAS NA MESMA EMBALAGEM: | G127: 1
E129: Nome | G129: Quant* | H129: Observações | I129: FORNECEDOR | J129: Data de Orçamento do FORNECEDOR | K129: Disponível em ESTOQUE | L129: Valor Automático | M129: TOTAL | O129: Quant. LOTE
D130: Nº
D131: 1 | E131: =IF('NOME + Nº'!C112=0,"",'NOME + Nº'!C112) -> Cartão Agradecimento ANNA B | G131: =IF('NOME + Nº'!E112*O131=0,"",'NOME + Nº'!E112*O131) -> 20 | H131: =IF('NOME + Nº'!F112=0,"",'NOME + Nº'!F112) | I131: =IF('NOME + Nº'!G112=0,"",'NOME + Nº'!G112) -> NI | J131: =IF('NOME + Nº'!H112=0,"",'NOME + Nº'!H112) -> 44862 | L131: =IF('NOME + Nº'!K112=0,"",'NOME + Nº'!K112) -> 2.49 | M131: =IF('NOME + Nº'!L112*(O131-K131)=0,"",'NOME + Nº'!L112*(O131-K131)) -> 49.8 | O131: =G69 -> 20
D132: 2 | E132: =IF('NOME + Nº'!C113=0,"",'NOME + Nº'!C113) -> Embalagem Plastica | G132: =IF('NOME + Nº'!E113*O132=0,"",'NOME + Nº'!E113*O132) -> 20 | H132: =IF('NOME + Nº'!F113=0,"",'NOME + Nº'!F113) | I132: =IF('NOME + Nº'!G113=0,"",'NOME + Nº'!G113) -> NI | J132: =IF('NOME + Nº'!H113=0,"",'NOME + Nº'!H113) -> 44692 | L132: =IF('NOME + Nº'!K113=0,"",'NOME + Nº'!K113) -> 0.85 | M132: =IF('NOME + Nº'!L113*(O132-K132)=0,"",'NOME + Nº'!L113*(O132-K132)) -> 17 | O132: =O131 -> 20
D133: 3 | E133: =IF('NOME + Nº'!C114=0,"",'NOME + Nº'!C114) -> Etiqueta Adesiva LAÇO | G133: =IF('NOME + Nº'!E114*O133=0,"",'NOME + Nº'!E114*O133) -> 20 | H133: =IF('NOME + Nº'!F114=0,"",'NOME + Nº'!F114) | I133: =IF('NOME + Nº'!G114=0,"",'NOME + Nº'!G114) -> NI | J133: =IF('NOME + Nº'!H114=0,"",'NOME + Nº'!H114) -> 44531 | L133: =IF('NOME + Nº'!K114=0,"",'NOME + Nº'!K114) -> 2.5 | M133: =IF('NOME + Nº'!L114*(O133-K133)=0,"",'NOME + Nº'!L114*(O133-K133)) -> 50 | O133: =O132 -> 20
...

Sheet MODELAGEM
B2: Leitura dos dados
B3: valores fixos (escritos pelo usuário) | F3: A B C
B4: valores calculados ou dependentes de outra célula | F4: A B C | J4: ='NOME + Nº'!C8 -> REF. NOME + Nº - 15H x 10B x 5L (cm)
J5: CONSUMO DE TECIDO POR MOLDE
B6: Notas e observações | F6: A B C | J6: ENCOMENDA | K6: MÍNIMO IDEAL
B7: Neutras | F7: A B C
B8: Alternativas (CLIQUE NO BOTÃO). Ex. "SIM" ou "NÃO" | F8: SIM | I8: LOTE | J8: ='NOME + Nº'!H128 -> 20 | K8: =INT(MAX((T11:T73),(W259,W266,W273,W280))) -> 35 | M8: TECIDO | P8: MOLDE | R8: ENFESTO
B9: Correto | F9: A B C | M9: Tipo | N9: VALOR (R$/m) | O9: TECIDO TOTAL | P9: Comprimento | Q9: Largura | R9: Máximo | S9: Subtotal | T9: LOTE MÍNIMO | U9: Quantidade de Moldes | X9: CÁLCULO DE CONSUMO
B10: Incorreto | F10: A B C | J10: CORTES | L10: Quantidade
B11: Controles de cálculos, números livres, encerramento de tabela ou parte | F11: A B C | G11: 1 | H11: =CONCATENATE("MOLDE ",G11) -> MOLDE 1 | J11: 1 | K11: SIM | L11: 1 | M11: Tec. Externo | N11: =IF((M11=X14),Z14,(IF((M11=X15),Z15,(IF((M11=X16),Z16,(IF((M11=X17),Z17,(IF((M11=X18),Z18,(IF((M11=X19),Z19,(IF((M11=X20),Z20))))))))))))) -> 49.9 | O11: =IF((M11=X14),AA14,(IF((M11=X15),AA15,(IF((M11=X16),AA16,(IF((M11=X17),AA17,(IF((M11=X18),AA18,(IF((M11=X19),AA19,(IF((M11=X20),AA20))))))))))))) -> 140 | P11: 34.4 | Q11: 58.3 | R11: =IF(R12<(M12*L11), INT(R12),(M12*L11)) -> 2 | S11: =IF(K11="SIM",(N11*L11*(P11/100)/R11)*L12,0) -> 8.5828 | T11: =R12*L12 -> 2.4013722 | U11: =IF(K11="SIM",1,IF(K13="SIM",1,IF(K15="SIM",1,IF(K17="SIM",1,0)))) -> 1 | AB11: Moldes Consumo
H12: CORPO | L12: =IF(K11="SIM","1","0") -> 1 | M12: =J8 -> 20 | R12: =O11/(Q11) -> 2.4013722 | X12: LISTA DE TECIDOS | AB12: =H11 -> MOLDE 1 | AF12: =H20 -> MOLDE 2 | AJ12: =H29 -> MOLDE 3 | AN12: =H38 -> MOLDE 4 | AR12: =H47 -> MOLDE 5 | AV12: =H56 -> MOLDE 6 | AZ12: =H65 -> MOLDE 7 | BD12: =H74 -> MOLDE 8 | BH12: =H83 -> MOLDE 9 | BL12: =H92 -> MOLDE 10 | BP12: =H101 -> MOLDE 11 | BT12: =H110 -> MOLDE 12 | BX12: =H119 -> MOLDE 13 | CB12: =H128 -> MOLDE 14 | CF12: =H137 -> MOLDE 15 | CJ12: =H146 -> MOLDE 16 | CN12: =H155 -> MOLDE 17 | CR12: =H164 -> MOLDE 18 | CV12: =H173 -> MOLDE 19 | CZ12: =H182 -> MOLDE 20 | DD12: =H191 -> MOLDE 21 | DH12: =H200 -> MOLDE 22 | DL12: =H209 -> MOLDE 23 | DP12: =H218 -> MOLDE 24 | DT12: =H227 -> MOLDE 25 | DX12: =H236 -> MOLDE 26 | EB12: Moldes ALÇAS | EF12: VIVO | EG12: Soma Total | EI12: ALÇAS Soma Total
B13: Destaques livres ou estéticos | F13: Cores diversas | J13: =J11+1 -> 2 | K13: SIM | L13: 1 | M13: Reforço | N13: =IF((M13=X14),Z14,(IF((M13=X15),Z15,(IF((M13=X16),Z16,(IF((M13=X17),Z17,(IF((M13=X18),Z18,(IF((M13=X19),Z19,(IF((M13=X20),Z20))))))))))))) -> 7.9 | O13: =IF((M13=X14),AA14,(IF((M13=X15),AA15,(IF((M13=X16),AA16,(IF((M13=X17),AA17,(IF((M13=X18),AA18,(IF((M13=X19),AA19,(IF((M13=X20),AA20))))))))))))) -> 140 | P13: =P11 -> 34.4 | Q13: =Q11 -> 58.3 | R13: =IF(R14<(M14*L13), INT(R14),(M14*L13)) -> 2 | S13: =IF(K13="SIM",(N13*L13*(P13/100)/R13)*L14,0) -> 1.3588 | T13: =R14*L14 -> 2.4013722 | X13: MATERIAL | Y13: Descrição | Z13: VALOR (R$/m) | AA13: Largura | AB13: 1 | AC13: =AB13+1 -> 2 | AD13: =AC13+1 -> 3 | AE13: =AD13+1 -> 4 | AF13: =AE13+1 -> 5 | AG13: =AF13+1 -> 6 | AH13: =AG13+1 -> 7 | AI13: =AH13+1 -> 8 | AJ13: =AI13+1 -> 9 | ... EF13: =EE13+1 -> 109
L14: =IF(K13="SIM","1","0") -> 1 | M14: =M12 -> 20 | R14: =O13/(Q13) -> 2.4013722 | W14: 1 | X14: ='NOME + Nº'!B35 -> Tec. Externo | Y14: ='NOME + Nº'!D35 -> Aquablock | Z14: ='NOME + Nº'!H35 -> 49.9 | AA14: ='NOME + Nº'!J35 -> 140 | AB14: =IF((M11=X14), S11, 0) -> 8.5828 | AC14: =IF((M13=X14), S13, 0) -> 0 | AD14: =IF((M15=X14), S15, 0) -> 0 | AE14: =IF((M17=X14), S17, 0) -> 0 | AF14: =IF((M20=X14), S20, 0) -> 0 | AG14: =IF((M22=X14), S22, 0) -> 0 | AH14: =IF((M24=X14), S24, 0) -> 0 | AI14: =IF((M26=X14), S26, 0) -> 0 | AJ14: =IF((M29=X14), S29, 0) -> 0 | AK14: =IF((M31=X14), S31, 0) -> 0 | AL14: =IF((M33=X14), S33, 0) -> 0 | AM14: =IF((M35=X14), S35, 0) -> 0 | AN14: =IF((M38=X14), S38, 0) -> 0 | AO14: =IF((M40=X14), S40, 0) -> 0 | AP14: =IF((M42=X14), S42, 0) -> 0 | AQ14: =IF((M44=X14), S44, 0) -> 0 | AR14: =IF((M47=X14), S47, 0) -> 0 | AS14: =IF((M49=X14), S49, 0) -> 0 | AT14: =IF((M51=X14), S51, 0) -> 0 | AU14: =IF((M53=X14), S53, 0) -> 0 | AV14: =IF((M56=X14), S56, 0) -> 0 | AW14: =IF((M58=X14), S58, 0) -> 0 | AX14: =IF((M60=X14), S60, 0) -> 0 | AY14: =IF((M62=X14), S62, 0) -> 0 | AZ14: =IF((M65=X14), S65, 0) -> 0 | BA14: =IF((M67=X14), S67, 0) -> 0 | BB14: =IF((M69=X14), S69, 0) -> 0 | BC14: =IF((M71=X14), S71, 0) -> 0 | BD14: =IF((M74=X14), S74, 0) -> 0 | BE14: =IF((M76=X14), S76, 0) -> 0 | BF14: =IF((M78=X14), S78, 0) -> 0 | BG14: =IF((M80=X14), S80, 0) -> 0 | BH14: =IF((M83=X14), S83, 0) -> 0 | BI14: =IF((M85=X14), S85, 0) -> 0 | BJ14: =IF((M87=X14), S87, 0) -> 0 | BK14: =IF((M89=X14), S89, 0) -> 0 | BL14: =IF((M92=X14), S92, 0) -> 0 | BM14: =IF((M94=X14), S94, 0) -> 0 | BN14: =IF((M96=X14), S96, 0) -> 0 | BO14: =IF((M98=X14), S98, 0) -> 0 | BP14: =IF((M101=X14), S101, 0) -> 0 | BQ14: =IF((M103=X14), S103, 0) -> 0 | BR14: =IF((M105=X14), S105, 0) -> 0 | BS14: =IF((M107=X14), S107, 0) -> 0 | BT14: =IF((M110=X14), S110, 0) -> 0 | BU14: =IF((M112=X14), S112, 0) -> 0 | BV14: =IF((M114=X14), S114, 0) -> 0 | BW14: =IF((M116=X14), S116, 0) -> 0 | BX14: =IF((M119=X14), S119, 0) -> 0 | BY14: =IF((M121=X14), S121, 0) -> 0 | BZ14: =IF((M123=X14), S123, 0) -> 0 | CA14: =IF((M125=X14), S125, 0) -> 0 | CB14: =IF((M128=X14), S128, 0) -> 0 | CC14: =IF((M130=X14), S130, 0) -> 0 | CD14: =IF((M132=X14), S132, 0) -> 0 | CE14: =IF((M134=X14), S134, 0) -> 0 | CF14: =IF((M137=X14), S137, 0) -> 0 | CG14: =IF((M139=X14), S139, 0) -> 0 | CH14: =IF((M141=X14), S141, 0) -> 0 | CI14: =IF((M143=X14),S143, 0) -> 0 | CJ14: =IF((M146=X14), S146, 0) -> 0 | CK14: =IF((M148=X14), S148, 0) -> 0 | CL14: =IF((M150=X14), S150, 0) -> 0 | CM14: =IF((M152=X14), S152, 0) -> 0 | CN14: =IF((M155=X14), S155, 0) -> 0 | CO14: =IF((M157=X14), S157, 0) -> 0 | CP14: =IF((M159=X14), S159, 0) -> 0 | CQ14: =IF((M161=X14), S161, 0) -> 0 | CR14: =IF((M164=X14), S164, 0) -> 0 | CS14: =IF((M166=X14), S166, 0) -> 0 | CT14: =IF((M168=X14), S168, 0) -> 0 | CU14: =IF((M170=X14), S170, 0) -> 0 | CV14: =IF((M173=X14), S173, 0) -> 0 | CW14: =IF((M175=X14), S175, 0) -> 0 | CX14: =IF((M177=X14), S177, 0) -> 0 | CY14: =IF((M179=X14), S179, 0) -> 0 | CZ14: =IF((M182=X14), S182, 0) -> 0 | DA14: =IF((M184=X14), S184, 0) -> 0 | DB14: =IF((M186=X14), S186, 0) -> 0 | DC14: =IF((M188=X14), S188, 0) -> 0 | DD14: =IF((M191=X14), S191, 0) -> 0 | DE14: =IF((M193=X14), S193, 0) -> 0 | DF14: =IF((M195=X14), S195, 0) -> 0 | DG14: =IF((M197=X14), S197, 0) -> 0 | DH14: =IF((M200=X14), S200, 0) -> 0 | DI14: =IF((M202=X14), S202, 0) -> 0 | DJ14: =IF((M204=X14), S204, 0) -> 0 | DK14: =IF((M206=X14), S206, 0) -> 0 | DL14: =IF((M209=X14), S209, 0) -> 0 | DM14: =IF((M211=X14), S211, 0) -> 0 | DN14: =IF((M213=X14), S213, 0) -> 0 | DO14: =IF((M215=X14), S215, 0) -> 0 | DP14: =IF((M218=X14), S218, 0) -> 0 | DQ14: =IF((M220=X14), S220, 0) -> 0 | DR14: =IF((M222=X14), S222, 0) -> 0 | DS14: =IF((M224=X14), S224, 0) -> 0 | DT14: =IF((M227=X14), S227, 0) -> 0 | DU14: =IF((M229=X14), S229, 0) -> 0 | DV14: =IF((M231=X14), S231, 0) -> 0 | DW14: =IF((M233=X14), S233, 0) -> 0 | DX14: =IF((M236=X14), S236, 0) -> 0 | DY14: =IF((M238=X14), S238, 0) -> 0 | DZ14: =IF((M240=X14), S240, 0) -> 0 | EA14: =IF((M242=X14), S242, 0) -> 0 | EB14: =IF('NOME + Nº'!E62="SIM",0,IF((M259=X14), V259+IF(H259="SIM",IF((P259=X14),SUM(V260:V263), 0)), IF(H259="SIM",IF((P259=X14),SUM(V260:V263), 0)))) -> 0.36397647 | EC14: =IF('NOME + Nº'!E62="SIM",0,IF((M266=X14), V266+IF(H259="SIM",IF((P266=X14),SUM(V267:V270), 0)), IF(H259="SIM",IF((P266=X14),SUM(V267:V270), 0)))) -> 0 | ED14: =IF('NOME + Nº'!E62="SIM",0,IF((M273=X14), V273+IF(H259="SIM",IF((P273=X14),SUM(V274:V277), 0)), IF(H259="SIM",IF((P273=X14),SUM(V274:V277), 0)))) -> 0 | EE14: =IF('NOME + Nº'!E62="SIM",0,IF((M280=X14), V280+IF(H259="SIM",IF((P280=X14),SUM(V281:V284), 0)), IF(H259="SIM",IF((P280=X14),SUM(V281:V284), 0)))) -> 0 | EF14: =IF(AE33=X14,AE49,0) -> 0 | EG14: =SUM(AB14:EF14) -> 8.9467765 | EI14: =SUM(EB14:EE14) -> 0.36397647
J15: =J13+1 -> 3 | K15: SIM | L15: 1 | M15: Reforço | N15: =IF((M15=X14),Z14,(IF((M15=X15),Z15,(IF((M15=X16),Z16,(IF((M15=X17),Z17,(IF((M15=X18),Z18,(IF((M15=X19),Z19,(IF((M15=X20),Z20))))))))))))) -> 7.9 | O15: =IF((M15=X14),AA14,(IF((M15=X15),AA15,(IF((M15=X16),AA16,(IF((M15=X17),AA17,(IF((M15=X18),AA18,(IF((M15=X19),AA19,(IF((M15=X20),AA20))))))))))))) -> 140 | P15: =P13 -> 34.4 | Q15: =Q13 -> 58.3 | R15: =IF(R16<(M16*L15), INT(R16),(M16*L15)) -> 2 | S15: =IF(K15="SIM",(N15*L15*(P15/100)/R15)*L16,0) -> 1.3588 | T15: =R16*L16 -> 2.4013722 | W15: 2 | X15: ='NOME + Nº'!B23 -> Entretela | Y15: ='NOME + Nº'!D36 -> 80 | Z15: ='NOME + Nº'!H36 -> 16 | AA15: ='NOME + Nº'!J36 -> 75 | AB15: =IF((M11=X15), S11, 0) -> 0 | AC15: =IF((M13=X15), S13, 0) -> 0 | AD15: =IF((M15=X15), S15, 0) -> 0 | AE15: =IF((M17=X15), S17, 0) -> 0 | AF15: =IF((M20=X15), S20, 0) -> 0 | AG15: =IF((M22=X15), S22, 0) -> 0 | AH15: =IF((M24=X15), S24, 0) -> 0 | AI15: =IF((M26=X15), S26, 0) -> 0 | AJ15: =IF((M29=X15), S29, 0) -> 0 | AK15: =IF((M31=X15), S31, 0) -> 0 | AL15: =IF((M33=X15), S33, 0) -> 0 | AM15: =IF((M35=X15), S35, 0) -> 0 | AN15: =IF((M38=X15), S38, 0) -> 0 | AO15: =IF((M40=X15), S40, 0) -> 0 | AP15: =IF((M42=X15), S42, 0) -> 0 | AQ15: =IF((M44=X15), S44, 0) -> 0 | AR15: =IF((M47=X15), S47, 0) -> 0 | AS15: =IF((M49=X15), S49, 0) -> 0 | AT15: =IF((M51=X15), S51, 0) -> 0 | AU15: =IF((M53=X15), S53, 0) -> 0 | AV15: =IF((M56=X15), S56, 0) -> 0 | AW15: =IF((M58=X15), S58, 0) -> 0 | AX15: =IF((M60=X15), S60, 0) -> 0 | AY15: =IF((M62=X15), S62, 0) -> 0 | AZ15: =IF((M65=X15), S65, 0) -> 0 | BA15: =IF((M67=X15), S67, 0) -> 0 | BB15: =IF((M69=X15), S69, 0) -> 0 | BC15: =IF((M71=X15), S71, 0) -> 0 | BD15: =IF((M74=X15), S74, 0) -> 0 | BE15: =IF((M76=X15), S76, 0) -> 0 | BF15: =IF((M78=X15), S78, 0) -> 0 | BG15: =IF((M80=X15), S80, 0) -> 0 | BH15: =IF((M83=X15), S83, 0) -> 0 | BI15: =IF((M85=X15), S85, 0) -> 0 | BJ15: =IF((M87=X15), S87, 0) -> 0 | BK15: =IF((M89=X15), S89, 0) -> 0 | BL15: =IF((M92=X15), S92, 0) -> 0 | BM15: =IF((M94=X15), S94, 0) -> 0 | BN15: =IF((M96=X15), S96, 0) -> 0 | BO15: =IF((M98=X15), S98, 0) -> 0 | BP15: =IF((M101=X15), S101, 0) -> 0 | BQ15: =IF((M103=X15), S103, 0) -> 0 | BR15: =IF((M105=X15), S105, 0) -> 0 | BS15: =IF((M107=X15), S107, 0) -> 0 | BT15: =IF((M110=X15), S110, 0) -> 0 | BU15: =IF((M112=X15), S112, 0) -> 0 | BV15: =IF((M114=X15), S114, 0) -> 0 | BW15: =IF((M116=X15), S116, 0) -> 0 | BX15: =IF((M119=X15), S119, 0) -> 0 | BY15: =IF((M121=X15), S121, 0) -> 0 | BZ15: =IF((M123=X15), S123, 0) -> 0 | CA15: =IF((M125=X15), S125, 0) -> 0 | CB15: =IF((M128=X15), S128, 0) -> 0 | CC15: =IF((M130=X15), S130, 0) -> 0 | CD15: =IF((M132=X15), S132, 0) -> 0 | CE15: =IF((M134=X15), S134, 0) -> 0 | CF15: =IF((M137=X15), S137, 0) -> 0 | CG15: =IF((M139=X15), S139, 0) -> 0 | CH15: =IF((M141=X15), S141, 0) -> 0 | CI15: =IF((M143=X15), S143, 0) -> 0 | CJ15: =IF((M146=X15), S146, 0) -> 0 | CK15: =IF((M148=X15), S148, 0) -> 0 | CL15: =IF((M150=X15), S150, 0) -> 0 | CM15: =IF((M152=X15), S152, 0) -> 0 | CN15: =IF((M155=X15), S155, 0) -> 0 | CO15: =IF((M157=X15), S157, 0) -> 0 | CP15: =IF((M159=X15), S159, 0) -> 0 | CQ15: =IF((M161=X15), S161, 0) -> 0 | CR15: =IF((M164=X15), S164, 0) -> 0 | CS15: =IF((M166=X15), S166, 0) -> 0 | CT15: =IF((M168=X15), S168, 0) -> 0 | CU15: =IF((M170=X15), S170, 0) -> 0 | CV15: =IF((M173=X15), S173, 0) -> 0 | CW15: =IF((M175=X15), S175, 0) -> 0 | CX15: =IF((M177=X15), S177, 0) -> 0 | CY15: =IF((M179=X15), S179, 0) -> 0 | CZ15: =IF((M182=X15), S182, 0) -> 0 | DA15: =IF((M184=X15), S184, 0) -> 0 | DB15: =IF((M186=X15), S186, 0) -> 0 | DC15: =IF((M188=X15), S188, 0) -> 0 | DD15: =IF((M191=X15), S191, 0) -> 0 | DE15: =IF((M193=X15), S193, 0) -> 0 | DF15: =IF((M195=X15), S195, 0) -> 0 | DG15: =IF((M197=X15), S197, 0) -> 0 | DH15: =IF((M200=X15), S200, 0) -> 0 | DI15: =IF((M202=X15), S202, 0) -> 0 | DJ15: =IF((M204=X15), S204, 0) -> 0 | DK15: =IF((M206=X15), S206, 0) -> 0 | DL15: =IF((M209=X15), S209, 0) -> 0 | DM15: =IF((M211=X15), S211, 0) -> 0 | DN15: =IF((M213=X15), S213, 0) -> 0 | DO15: =IF((M215=X15), S215, 0) -> 0 | DP15: =IF((M218=X15), S218, 0) -> 0 | DQ15: =IF((M220=X15), S220, 0) -> 0 | DR15: =IF((M222=X15), S222, 0) -> 0 | DS15: =IF((M224=X15), S224, 0) -> 0 | DT15: =IF((M227=X15), S227, 0) -> 0 | DU15: =IF((M229=X15), S229, 0) -> 0 | DV15: =IF((M231=X15), S231, 0) -> 0 | DW15: =IF((M233=X15), S233, 0) -> 0 | DX15: =IF((M236=X15), S236, 0) -> 0 | DY15: =IF((M238=X15), S238, 0) -> 0 | DZ15: =IF((M240=X15), S240, 0) -> 0 | EA15: =IF((M242=X15), S242, 0) -> 0 | EB15: =IF('NOME + Nº'!E62="SIM",0,IF((M259=X15),V259+IF(H259="SIM",IF((P259=X15),SUM(V260:V263), 0)), IF(H259="SIM",IF((P259=X15),SUM(V260:V263), 0)))) -> 0.22044444 | EC15: =IF('NOME + Nº'!E62="SIM",0,IF((M266=X15), V266+IF(H259="SIM",IF((P266=X15),SUM(V267:V270), 0)), IF(H259="SIM",IF((P266=X15),SUM(V267:V270), 0)))) -> 0.14666667 | ED15: =IF('NOME + Nº'!E62="SIM",0,IF((M273=X15), V273+IF(H259="SIM",IF((P273=X15),SUM(V274:V277), 0)), IF(H259="SIM",IF((P273=X15),SUM(V274:V277), 0)))) -> 0 | EE15: =IF('NOME + Nº'!E62="SIM",0,IF((M280=X15), V280+IF(H259="SIM",IF((P280=X15),SUM(V281:V284), 0)), IF(H259="SIM",IF((P280=X15),SUM(V281:V284), 0)))) -> 0 | EF15: =IF(AE33=X15,AE49,0) -> 0 | EG15: =IF('NOME + Nº'!D23="SIM",SUM(AB15:EF15),0) -> 0 | EI15: =SUM(EB15:EE15) -> 0.36711111
B16: Legendas | L16: =IF(K15="SIM","1","0") -> 1 | M16: =M14 -> 20 | R16: =O15/(Q15) -> 2.4013722 | W16: 3 | X16: ='NOME + Nº'!B24 -> Forro | Y16: ='NOME + Nº'!D37 -> Suede | Z16: ='NOME + Nº'!H37 -> 19.9 | AA16: ='NOME + Nº'!J37 -> 140 | AB16: =IF((M11=X16), S11, 0) -> 0 | AC16: =IF((M13=X16), S13, 0) -> 0 | AD16: =IF((M15=X16), S15, 0) -> 0 | AE16: =IF((M17=X16), S17, 0) -> 0 | AF16: =IF((M20=X16), S20, 0) -> 0 | AG16: =IF((M22=X16), S22, 0) -> 0 | AH16: =IF((M24=X16), S24, 0) -> 0 | AI16: =IF((M26=X16), S26, 0) -> 0 | AJ16: =IF((M29=X16), S29, 0) -> 0 | AK16: =IF((M31=X16), S31, 0) -> 0 | AL16: =IF((M33=X16), S33, 0) -> 0 | AM16: =IF((M35=X16), S35, 0) -> 0 | AN16: =IF((M38=X16), S38, 0) -> 0 | AO16: =IF((M40=X16), S40, 0) -> 0 | AP16: =IF((M42=X16), S42, 0) -> 0 | AQ16: =IF((M44=X16), S44, 0) -> 0 | AR16: =IF((M47=X16), S47, 0) -> 0 | AS16: =IF((M49=X16), S49, 0) -> 0 | AT16: =IF((M51=X16), S51, 0) -> 0 | AU16: =IF((M53=X16), S53, 0) -> 0 | AV16: =IF((M56=X16), S56, 0) -> 0 | AW16: =IF((M58=X16), S58, 0) -> 0 | AX16: =IF((M60=X16), S60, 0) -> 0 | AY16: =IF((M62=X16), S62, 0) -> 0 | AZ16: =IF((M65=X16), S65,0) -> 0 | BA16: =IF((M67=X16), S67, 0) -> 0 | BB16: =IF((M69=X16), S69, 0) -> 0 | BC16: =IF((M71=X16), S71, 0) -> 0 | BD16: =IF((M74=X16), S74, 0) -> 0 | BE16: =IF((M76=X16), S76, 0) -> 0 | BF16: =IF((M78=X16), S78, 0) -> 0 | BG16: =IF((M80=X16), S80, 0) -> 0 | BH16: =IF((M83=X16), S83, 0) -> 0 | BI16: =IF((M85=X16), S85, 0) -> 0 | BJ16: =IF((M87=X16), S87, 0) -> 0 | BK16: =IF((M89=X16), S89, 0) -> 0 | BL16: =IF((M92=X16), S92, 0) -> 0 | BM16: =IF((M94=X16), S94, 0) -> 0 | BN16: =IF((M96=X16), S96, 0) -> 0 | BO16: =IF((M98=X16), S98, 0) -> 0 | BP16: =IF((M101=X16), S101, 0) -> 0 | BQ16: =IF((M103=X16), S103, 0) -> 0 | BR16: =IF((M105=X16), S105, 0) -> 0 | BS16: =IF((M107=X16), S107, 0) -> 0 | BT16: =IF((M110=X16), S110, 0) -> 0 | BU16: =IF((M112=X16), S112, 0) -> 0 | BV16: =IF((M114=X16), S114, 0) -> 0 | BW16: =IF((M116=X16), S116, 0) -> 0 | BX16: =IF((M119=X16), S119, 0) -> 0 | BY16: =IF((M121=X16), S121, 0) -> 0 | BZ16: =IF((M123=X16), S123, 0) -> 0 | CA16: =IF((M125=X16), S125, 0) -> 0 | CB16: =IF((M128=X16), S128, 0) -> 0 | CC16: =IF((M130=X16), S130, 0) -> 0 | CD16: =IF((M132=X16), S132, 0) -> 0 | CE16: =IF((M134=X16), S134, 0) -> 0 | CF16: =IF((M137=X16), S137, 0) -> 0 | CG16: =IF((M139=X16), S139, 0) -> 0 | CH16: =IF((M141=X16), S141, 0) -> 0 | CI16: =IF((M143=X16), S143, 0) -> 0 | CJ16: =IF((M146=X16), S146, 0) -> 0 | CK16: =IF((M148=X16), S148, 0) -> 0 | CL16: =IF((M150=X16), S150, 0) -> 0 | CM16: =IF((M152=X16), S152, 0) -> 0 | CN16: =IF((M155=X16), S155, 0) -> 0 | CO16: =IF((M157=X16), S157, 0) -> 0 | CP16: =IF((M159=X16), S159, 0) -> 0 | CQ16: =IF((M161=X16), S161, 0) -> 0 | CR16: =IF((M164=X16), S164, 0) -> 0 | CS16: =IF((M166=X16), S166, 0) -> 0 | CT16: =IF((M168=X16), S168, 0) -> 0 | CU16: =IF((M170=X16), S170, 0) -> 0 | CV16: =IF((M173=X16), S173, 0) -> 0 | CW16: =IF((M175=X16), S175, 0) -> 0 | CX16: =IF((M177=X16), S177, 0) -> 0 | CY16: =IF((M179=X16), S179, 0) -> 0 | CZ16: =IF((M182=X16), S182, 0) -> 0 | DA16: =IF((M184=X16), S184, 0) -> 0 | DB16: =IF((M186=X16), S186, 0) -> 0 | DC16: =IF((M188=X16), S188, 0) -> 0 | DD16: =IF((M191=X16), S191, 0) -> 0 | DE16: =IF((M193=X16), S193, 0) -> 0 | DF16: =IF((M195=X16), S195, 0) -> 0 | DG16: =IF((M197=X16), S197, 0) -> 0 | DH16: =IF((M200=X16), S200, 0) -> 0 | DI16: =IF((M202=X16), S202, 0) -> 0 | DJ16: =IF((M204=X16), S204, 0) -> 0 | DK16: =IF((M206=X16), S206, 0) -> 0 | DL16: =IF((M209=X16), S209, 0) -> 0 | DM16: =IF((M211=X16), S211, 0) -> 0 | DN16: =IF((M213=X16), S213, 0) -> 0 | DO16: =IF((M215=X16), S215, 0) -> 0 | DP16: =IF((M218=X16), S218, 0) -> 0 | DQ16: =IF((M220=X16), S220, 0) -> 0 | DR16: =IF((M222=X16), S222, 0) -> 0 | DS16: =IF((M224=X16), S224, 0) -> 0 | DT16: =IF((M227=X16), S227, 0) -> 0 | DU16: =IF((M229=X16), S229, 0) -> 0 | DV16: =IF((M231=X16), S231, 0) -> 0 | DW16: =IF((M233=X16), S233, 0) -> 0 | DX16: =IF((M236=X16), S236, 0) -> 0 | DY16: =IF((M238=X16), S238, 0) -> 0 | DZ16: =IF((M240=X16), S240, 0) -> 0 | EA16: =IF((M242=X16), S242, 0) -> 0 | EB16: =IF('NOME + Nº'!E62="SIM",0,IF((M259=X16),V259+IF(H259="SIM",IF((P259=X16),SUM(V260:V263), 0)), IF(H259="SIM",IF((P259=X16),SUM(V260:V263), 0)))) -> 0 | EC16: =IF('NOME + Nº'!E62="SIM",0,IF((M266=X16), V266+IF(H259="SIM",IF((P266=X16),SUM(V267:V270), 0)), IF(H259="SIM",IF((P266=X16),SUM(V267:V270), 0)))) -> 0 | ED16: =IF('NOME + Nº'!E62="SIM",0,IF((M273=X16), V273+IF(H259="SIM",IF((P273=X16),SUM(V274:V277), 0)), IF(H259="SIM",IF((P273=X16),SUM(V274:V277), 0)))) -> 0 | EE16: =IF('NOME + Nº'!E62="SIM",0,IF((M280=X16), V280+IF(H259="SIM",IF((P280=X16),SUM(V281:V284), 0)), IF(H259="SIM",IF((P280=X16),SUM(V281:V284), 0)))) -> 0 | EF16: =IF(AE33=X16,AE49,0) -> 0 | EG16: =IF('NOME + Nº'!D24="SIM",SUM(AB16:EF16),0) -> 0 | EI16: =SUM(EB16:EE16) -> 0
B17: No rótulo do PROCESSO, escolha as opções para sinalizar uso do quadro | F17: SIM | J17: =J15+1 -> 4 | K17: NÃO | L17: 1 | M17: Reforço | N17: =IF((M17=X14),Z14,(IF((M17=X15),Z15,(IF((M17=X16),Z16,(IF((M17=X17),Z17,(IF((M17=X18),Z18,(IF((M17=X19),Z19,(IF((M17=X20),Z20))))))))))))) -> 7.9 | O17: =IF((M17=X14),AA14,(IF((M17=X15),AA15,(IF((M17=X16),AA16,(IF((M17=X17),AA17,(IF((M17=X18),AA18,(IF((M17=X19),AA19,(IF((M17=X20),AA20))))))))))))) -> 140 | P17: =P15 -> 34.4 | Q17: =Q15 -> 58.3 | R17: =IF(R19<(M19*L17), INT(R19),(M19*L17)) -> 2 | S17: =IF(K17="SIM",(N17*L17*(P17/100)/R17)*L19,0) -> 0 | T17: =R19*L19 -> 0 | W17: 4 | X17: ='NOME + Nº'!B25 -> Couro | Y17: ='NOME + Nº'!D38 -> Couro Legítimo Fly | Z17: ='NOME + Nº'!H38 -> 74.9 | AA17: ='NOME + Nº'!J38 -> 100 | AB17: =IF((M11=X17), S11, 0) -> 0 | AC17: =IF((M13=X17), S13, 0) -> 0 | AD17: =IF((M15=X17), S15, 0) -> 0 | AE17: =IF((M17=X17), S17, 0) -> 0 | AF17: =IF((M20=X17), S20, 0) -> 0 | AG17: =IF((M22=X17), S22, 0) -> 0 | AH17: =IF((M24=X17), S24, 0) -> 0 | AI17: =IF((M26=X17), S26, 0) -> 0 | AJ17: =IF((M29=X17), S29, 0) -> 0 | AK17: =IF((M31=X17), S31, 0) -> 0 | AL17: =IF((M33=X17), S33, 0) -> 0 | AM17: =IF((M35=X17), S35, 0) -> 0 | AN17: =IF((M38=X17), S38, 0) -> 0 | AO17: =IF((M40=X17), S40, 0) -> 0 | AP17: =IF((M42=X17), S42, 0) -> 0 | AQ17: =IF((M44=X17), S44, 0) -> 0 | AR17: =IF((M47=X17), S47, 0) -> 0 | AS17: =IF((M49=X17), S49, 0) -> 0 | AT17: =IF((M51=X17), S51, 0) -> 0 | AU17: =IF((M53=X17), S53, 0) -> 0 | AV17: =IF((M56=X17), S56, 0) -> 0 | AW17: =IF((M58=X17), S58, 0) -> 0 | AX17: =IF((M60=X17), S60, 0) -> 0 | AY17: =IF((M62=X17), S62, 0) -> 0 | AZ17: =IF((M65=X17), S65, 0) -> 0 | BA17: =IF((M67=X17), S67, 0) -> 0 | BB17: =IF((M69=X17), S69, 0) -> 0 | BC17: =IF((M71=X17), S71, 0) -> 0 | BD17: =IF((M74=X17), S74, 0) -> 0 | BE17: =IF((M76=X17), S76, 0) -> 0 | BF17: =IF((M78=X17), S78, 0) -> 0 | BG17: =IF((M80=X17), S80, 0) -> 0 | BH17: =IF((M83=X17), S83, 0) -> 0 | BI17: =IF((M85=X17), S85, 0) -> 0 | BJ17: =IF((M87=X17), S87, 0) -> 0 | BK17: =IF((M89=X17), S89, 0) -> 0 | BL17: =IF((M92=X17), S92, 0) -> 0 | BM17: =IF((M94=X17), S94, 0) -> 0 | BN17: =IF((M96=X17), S96, 0) -> 0 | BO17: =IF((M98=X17), S98, 0) -> 0 | BP17: =IF((M101=X17), S101, 0) -> 0 | BQ17: =IF((M103=X17), S103, 0) -> 0 | BR17: =IF((M105=X17), S105, 0) -> 0 | BS17: =IF((M107=X17), S107, 0) -> 0 | BT17: =IF((M110=X17), S110, 0) -> 0 | BU17: =IF((M112=X17), S112, 0) -> 0 | BV17: =IF((M114=X17), S114, 0) -> 0 | BW17: =IF((M116=X17), S116, 0) -> 0 | BX17: =IF((M119=X17), S119, 0) -> 0 | BY17: =IF((M121=X17), S121, 0) -> 0 | BZ17: =IF((M123=X17), S123, 0) -> 0 | CA17: =IF((M125=X17), S125, 0) -> 0 | CB17: =IF((M128=X17), S128, 0) -> 0 | CC17: =IF((M130=X17), S130, 0) -> 0 | CD17: =IF((M132=X17), S132, 0) -> 0 | CE17: =IF((M134=X17), S134, 0) -> 0 | CF17: =IF((M137=X17), S137, 0) -> 0 | CG17: =IF((M139=X17), S139, 0) -> 0 | CH17: =IF((M141=X17), S141, 0) -> 0 | CI17: =IF((M143=X17), S143, 0) -> 0 | CJ17: =IF((M146=X17), S146, 0) -> 0 | CK17: =IF((M148=X17), S148, 0) -> 0 | CL17: =IF((M150=X17), S150, 0) -> 0 | CM17: =IF((M152=X17), S152, 0) -> 0 | CN17: =IF((M155=X17), S155, 0) -> 0 | CO17: =IF((M157=X17), S157, 0) -> 0 | CP17: =IF((M159=X17), S159, 0) -> 0 | CQ17: =IF((M161=X17), S161, 0) -> 0 | CR17: =IF((M164=X17), S164, 0) -> 0 | CS17: =IF((M166=X17), S166, 0) -> 0 | CT17: =IF((M168=X17), S168, 0) -> 0 | CU17: =IF((M170=X17), S170, 0) -> 0 | CV17: =IF((M173=X17), S173, 0) -> 0 | CW17: =IF((M175=X17), S175, 0) -> 0 | CX17: =IF((M177=X17), S177, 0) -> 0 | CY17: =IF((M179=X17), S179, 0) -> 0 | CZ17: =IF((M182=X17), S182, 0) -> 0 | DA17: =IF((M184=X17), S184, 0) -> 0 | DB17: =IF((M186=X17), S186, 0) -> 0 | DC17: =IF((M188=X17), S188, 0) -> 0 | DD17: =IF((M191=X17), S191, 0) -> 0 | DE17: =IF((M193=X17), S193, 0) -> 0 | DF17: =IF((M195=X17), S195, 0) -> 0 | DG17: =IF((M197=X17), S197, 0) -> 0 | DH17: =IF((M200=X17), S200, 0) -> 0 | DI17: =IF((M202=X17), S202, 0) -> 0 | DJ17: =IF((M204=X17), S204, 0) -> 0 | DK17: =IF((M206=X17), S206, 0) -> 0 | DL17: =IF((M209=X17), S209, 0) -> 0 | DM17: =IF((M211=X17), S211, 0) -> 0 | DN17: =IF((M213=X17), S213, 0) -> 0 | DO17: =IF((M215=X17), S215, 0) -> 0 | DP17: =IF((M218=X17), S218, 0) -> 0 | DQ17: =IF((M220=X17), S220, 0) -> 0 | DR17: =IF((M222=X17), S222, 0) -> 0 | DS17: =IF((M224=X17), S224, 0) -> 0 | DT17: =IF((M227=X17), S227, 0) -> 0 | DU17: =IF((M229=X17), S229, 0) -> 0 | DV17: =IF((M231=X17), S231, 0) -> 0 | DW17: =IF((M233=X17), S233, 0) -> 0 | DX17: =IF((M236=X17), S236, 0) -> 0 | DY17: =IF((M238=X17), S238, 0) -> 0 | DZ17: =IF((M240=X17), S240, 0) -> 0 | EA17: =IF((M242=X17), S242, 0) -> 0 | EB17: =IF('NOME + Nº'!E62="SIM",0,IF((M259=X17),V259+IF(H259="SIM",IF((P259=X17),SUM(V260:V263), 0)), IF(H259="SIM",IF((P259=X17),SUM(V260:V263), 0)))) -> 0 | EC17: =IF('NOME + Nº'!E62="SIM",0,IF((M266=X17), V266+IF(H259="SIM",IF((P266=X17),SUM(V267:V270), 0)), IF(H259="SIM",IF((P266=X17),SUM(V267:V270), 0)))) -> 0 | ED17: =IF('NOME + Nº'!E62="SIM",0,IF((M273=X17), V273+IF(H259="SIM",IF((P273=X17),SUM(V274:V277), 0)), IF(H259="SIM",IF((P273=X17),SUM(V274:V277), 0)))) -> 0 | EE17: =IF('NOME + Nº'!E62="SIM",0,IF((M280=X17), V280+IF(H259="SIM",IF((P280=X17),SUM(V281:V284), 0)), IF(H259="SIM",IF((P280=X17),SUM(V281:V284), 0)))) -> 0 | EF17: =IF(AE33=X17,AE49,0) -> 0 | EG17: =IF('NOME + Nº'!D25="SIM",SUM(AB17:EF17),0) -> 0 | EI17: =SUM(EB17:EE17) -> 0
F18: NÃO | H18: Obs | W18: 5 | X18: ='NOME + Nº'!B26 -> Tec. Vivo | Y18: ='NOME + Nº'!D39 -> Aquablock | Z18: ='NOME + Nº'!H39 -> 49.9 | AA18: ='NOME + Nº'!J39 -> 140 | AB18: =IF((M11=X18), S11, 0) -> 0 | AC18: =IF((M13=X18), S13, 0) -> 0 | AD18: =IF((M15=X18), S15, 0) -> 0 | AE18: =IF((M17=X18), S17, 0) -> 0 | AF18: =IF((M20=X18), S20, 0) -> 0 | AG18: =IF((M22=X18), S22, 0) -> 0 | AH18: =IF((M24=X18), S24, 0) -> 0 | AI18: =IF((M26=X18), S26, 0) -> 0 | AJ18: =IF((M29=X18), S29, 0) -> 0 | AK18: =IF((M31=X18), S31, 0) -> 0 | AL18: =IF((M33=X18), S33, 0) -> 0 | AM18: =IF((M35=X18), S35, 0) -> 0 | AN18: =IF((M38=X18), S38, 0) -> 0 | AO18: =IF((M40=X18), S40, 0) -> 0 | AP18: =IF((M42=X18), S42, 0) -> 0 | AQ18: =IF((M44=X18), S44, 0) -> 0 | AR18: =IF((M47=X18), S47, 0) -> 0 | AS18: =IF((M49=X18), S49, 0) -> 0 | AT18: =IF((M51=X18), S51, 0) -> 0 | AU18: =IF((M53=X18), S53, 0) -> 0 | AV18: =IF((M56=X18), S56, 0) -> 0 | AW18: =IF((M58=X18), S58, 0) -> 0 | AX18: =IF((M60=X18), S60, 0) -> 0 | AY18: =IF((M62=X18), S62, 0) -> 0 | AZ18: =IF((M65=X18), S65, 0) -> 0 | BA18: =IF((M67=X18), S67, 0) -> 0 | BB18: =IF((M69=X18), S69, 0) -> 0 | BC18: =IF((M71=X18), S71, 0) -> 0 | BD18: =IF((M74=X18), S74, 0) -> 0 | BE18: =IF((M76=X18), S76, 0) -> 0 | BF18: =IF((M78=X18), S78, 0) -> 0 | BG18: =IF((M80=X18), S80, 0) -> 0 | BH18: =IF((M83=X18), S83, 0) -> 0 | BI18: =IF((M85=X18), S85, 0) -> 0 | BJ18: =IF((M87=X18), S87, 0) -> 0 | BK18: =IF((M89=X18), S89, 0) -> 0 | BL18: =IF((M92=X18), S92, 0) -> 0 | BM18: =IF((M94=X18), S94, 0) -> 0 | BN18: =IF((M96=X18), S96, 0) -> 0 | BO18: =IF((M98=X18), S98, 0) -> 0 | BP18: =IF((M101=X18), S101, 0) -> 0 | BQ18: =IF((M103=X18), S103, 0) -> 0 | BR18: =IF((M105=X18), S105, 0) -> 0 | BS18: =IF((M107=X18), S107, 0) -> 0 | BT18: =IF((M110=X18), S110, 0) -> 0 | BU18: =IF((M112=X18), S112, 0) -> 0 | BV18: =IF((M114=X18), S114, 0) -> 0 | BW18: =IF((M116=X18), S116, 0) -> 0 | BX18: =IF((M119=X18), S119, 0) -> 0 | BY18: =IF((M121=X18), S121, 0) -> 0 | BZ18: =IF((M123=X18), S123, 0) -> 0 | CA18: =IF((M125=X18), S125, 0) -> 0 | CB18: =IF((M128=X18), S128, 0) -> 0 | CC18: =IF((M130=X18), S130, 0) -> 0 | CD18: =IF((M132=X18), S132, 0) -> 0 | CE18: =IF((M134=X18), S134, 0) -> 0 | CF18: =IF((M137=X18), S137, 0) -> 0 | CG18: =IF((M139=X18), S139, 0) -> 0 | CH18: =IF((M141=X18), S141, 0) -> 0 | CI18: =IF((M143=X18), S143, 0) -> 0 | CJ18: =IF((M146=X18), S146, 0) -> 0 | CK18: =IF((M148=X18), S148, 0) -> 0 | CL18: =IF((M150=X18), S150, 0) -> 0 | CM18: =IF((M152=X18), S152, 0) -> 0 | CN18: =IF((M155=X18), S155, 0) -> 0 | CO18: =IF((M157=X18), S157, 0) -> 0 | CP18: =IF((M159=X18), S159, 0) -> 0 | CQ18: =IF((M161=X18), S161, 0) -> 0 | CR18: =IF((M164=X18), S164, 0) -> 0 | CS18: =IF((M166=X18), S166, 0) -> 0 | CT18: =IF((M168=X18), S168, 0) -> 0 | CU18: =IF((M170=X18), S170, 0) -> 0 | CV18: =IF((M173=X18), S173, 0) -> 0 | CW18: =IF((M175=X18), S175, 0) -> 0 | CX18: =IF((M177=X18), S177, 0) -> 0 | CY18: =IF((M179=X18), S179, 0) -> 0 | CZ18: =IF((M182=X18), S182, 0) -> 0 | DA18: =IF((M184=X18), S184, 0) -> 0 | DB18: =IF((M186=X18), S186, 0) -> 0 | DC18: =IF((M188=X18), S188, 0) -> 0 | DD18: =IF((M191=X18), S191, 0) -> 0 | DE18: =IF((M193=X18), S193, 0) -> 0 | DF18: =IF((M195=X18), S195, 0) -> 0 | DG18: =IF((M197=X18), S197, 0) -> 0 | DH18: =IF((M200=X18), S200, 0) -> 0 | DI18: =IF((M202=X18), S202, 0) -> 0 | DJ18: =IF((M204=X18), S204, 0) -> 0 | DK18: =IF((M206=X18), S206, 0) -> 0 | DL18: =IF((M209=X18), S209, 0) -> 0 | DM18: =IF((M211=X18), S211, 0) -> 0 | DN18: =IF((M213=X18), S213, 0) -> 0 | DO18: =IF((M215=X18), S215, 0) -> 0 | DP18: =IF((M218=X18), S218, 0) -> 0 | DQ18: =IF((M220=X18), S220, 0) -> 0 | DR18: =IF((M222=X18), S222, 0) -> 0 | DS18: =IF((M224=X18), S224, 0) -> 0 | DT18: =IF((M227=X18), S227, 0) -> 0 | DU18: =IF((M229=X18), S229, 0) -> 0 | DV18: =IF((M231=X18), S231, 0) -> 0 | DW18: =IF((M233=X18), S233, 0) -> 0 | DX18: =IF((M236=X18), S236, 0) -> 0 | DY18: =IF((M238=X18), S238, 0) -> 0 | DZ18: =IF((M240=X18), S240, 0) -> 0 | EA18: =IF((M242=X18), S242, 0) -> 0 | EB18: =IF('NOME + Nº'!E62="SIM",0,IF((M259=X18),V259+IF(H259="SIM",IF((P259=X18),SUM(V260:V263), 0)), IF(H259="SIM",IF((P259=X18),SUM(V260:V263), 0)))) -> 0 | EC18: =IF('NOME + Nº'!E62="SIM",0,IF((M266=X18), V266+IF(H259="SIM",IF((P266=X18),SUM(V267:V270), 0)), IF(H259="SIM",IF((P266=X18),SUM(V267:V270), 0)))) -> 0 | ED18: =IF('NOME + Nº'!E62="SIM",0,IF((M273=X18), V273+IF(H259="SIM",IF((P273=X18),SUM(V274:V277), 0)), IF(H259="SIM",IF((P273=X18),SUM(V274:V277), 0)))) -> 0 | EE18: =IF('NOME + Nº'!E62="SIM",0,IF((M280=X18), V280+IF(H259="SIM",IF((P280=X18),SUM(V281:V284), 0)), IF(H259="SIM",IF((P280=X18),SUM(V281:V284), 0)))) -> 0 | EF18: =IF(AE33=X18,AE49,0) -> 0 | EG18: =IF('NOME + Nº'!D26="SIM",SUM(AB18:EF18),0) -> 0 | EI18: =SUM(EB18:EE18) -> 0
B19: Escreva os FORNECEDORES nos quadros de Materiais com LETRAS MAIÚSCULAS. Escrever materiais iniciando com letras MAIÚSCULAS. | L19: =IF(K17="SIM","1","0") -> 0 | M19: =M16 -> 20 | R19: =O17/(Q17) -> 2.4013722 | W19: 6 | X19: ='NOME + Nº'!B27 -> Estrutura | Y19: ='NOME + Nº'!D40 -> Placa Plástica | Z19: ='NOME + Nº'!H40 -> 20.12 | AA19: ='NOME + Nº'!J40 -> 28 | AB19: =IF((M11=X19), S11, 0) -> 0 | AC19: =IF((M13=X19), S13, 0) -> 0 | AD19: =IF((M15=X19), S15, 0) -> 0 | AE19: =IF((M17=X19), S17, 0) -> 0 | AF19: =IF((M20=X19), S20, 0) -> 0 | AG19: =IF((M22=X19), S22, 0) -> 0 | AH19: =IF((M24=X19), S24, 0) -> 0 | AI19: =IF((M26=X19), S26, 0) -> 0 | AJ19: =IF((M29=X19), S29, 0) -> 0 | AK19: =IF((M31=X19), S31, 0) -> 0 | AL19: =IF((M33=X19), S33, 0) -> 0 | AM19: =IF((M35=X19), S35, 0) -> 0 | AN19: =IF((M38=X19), S38, 0) -> 0 | AO19: =IF((M40=X19), S40, 0) -> 0 | AP19: =IF((M42=X19), S42, 0) -> 0 | AQ19: =IF((M44=X19), S44, 0) -> 0 | AR19: =IF((M47=X19), S47, 0) -> 0 | AS19: =IF((M49=X19), S49, 0) -> 0 | AT19: =IF((M51=X19), S51, 0) -> 0 | AU19: =IF((M53=X19), S53, 0) -> 0 | AV19: =IF((M56=X19), S56, 0) -> 0 | AW19: =IF((M58=X19), S58, 0) -> 0 | AX19: =IF((M60=X19), S60, 0) -> 0 | AY19: =IF((M62=X19), S62, 0) -> 0 | AZ19: =IF((M65=X19), S65, 0) -> 0 | BA19: =IF((M67=X19), S67, 0) -> 0 | BB19: =IF((M69=X19), S69, 0) -> 0 | BC19: =IF((M71=X19), S71, 0) -> 0 | BD19: =IF((M74=X19), S74, 0) -> 0 | BE19: =IF((M76=X19), S76, 0) -> 0 | BF19: =IF((M78=X19), S78, 0) -> 0 | BG19: =IF((M80=X19), S80, 0) -> 0 | BH19: =IF((M83=X19), S83, 0) -> 0 | BI19: =IF((M85=X19), S85, 0) -> 0 | BJ19: =IF((M87=X19), S87, 0) -> 0 | BK19: =IF((M89=X19), S89, 0) -> 0 | BL19: =IF((M92=X19), S92, 0) -> 0 | BM19: =IF((M94=X19), S94, 0) -> 0 | BN19: =IF((M96=X19), S96, 0) -> 0 | BO19: =IF((M98=X19), S98, 0) -> 0 | BP19: =IF((M101=X19), S101, 0) -> 0 | BQ19: =IF((M103=X19), S103, 0) -> 0 | BR19: =IF((M105=X19), S105, 0) -> 0 | BS19: =IF((M107=X19), S107, 0) -> 0 | BT19: =IF((M110=X19), S110, 0) -> 0 | BU19: =IF((M112=X19), S112, 0) -> 0 | BV19: =IF((M114=X19), S114, 0) -> 0 | BW19: =IF((M116=X19), S116, 0) -> 0 | BX19: =IF((M119=X19), S119, 0) -> 0 | BY19: =IF((M121=X19), S121, 0) -> 0 | BZ19: =IF((M123=X19), S123, 0) -> 0 | CA19: =IF((M125=X19), S125, 0) -> 0 | CB19: =IF((M128=X19),S128, 0) -> 0 | CC19: =IF((M130=X19), S130, 0) -> 0 | CD19: =IF((M132=X19), S132, 0) -> 0 | CE19: =IF((M134=X19), S134, 0) -> 0 | CF19: =IF((M137=X19), S137, 0) -> 0 | CG19: =IF((M139=X19), S139, 0) -> 0 | CH19: =IF((M141=X19), S141, 0) -> 0 | CI19: =IF((M143=X19), S143, 0) -> 0 | CJ19: =IF((M146=X19), S146, 0) -> 0 | CK19: =IF((M148=X19), S148, 0) -> 0 | CL19: =IF((M150=X19), S150, 0) -> 0 | CM19: =IF((M152=X19), S152, 0) -> 0 | CN19: =IF((M155=X19), S155, 0) -> 0 | CO19: =IF((M157=X19), S157, 0) -> 0 | CP19: =IF((M159=X19), S159, 0) -> 0 | CQ19: =IF((M161=X19), S161, 0) -> 0 | CR19: =IF((M164=X19), S164, 0) -> 0 | CS19: =IF((M166=X19), S166, 0) -> 0 | CT19: =IF((M168=X19), S168, 0) -> 0 | CU19: =IF((M170=X19), S170, 0) -> 0 | CV19: =IF((M173=X19), S173, 0) -> 0 | CW19: =IF((M175=X19), S175, 0) -> 0 | CX19: =IF((M177=X19), S177, 0) -> 0 | CY19: =IF((M179=X19), S179, 0) -> 0 | CZ19: =IF((M182=X19), S182, 0) -> 0 | DA19: =IF((M184=X19), S184, 0) -> 0 | DB19: =IF((M186=X19), S186, 0) -> 0 | DC19: =IF((M188=X19), S188, 0) -> 0 | DD19: =IF((M191=X19), S191, 0) -> 0 | DE19: =IF((M193=X19), S193, 0) -> 0 | DF19: =IF((M195=X19), S195, 0) -> 0 | DG19: =IF((M197=X19), S197, 0) -> 0 | DH19: =IF((M200=X19), S200, 0) -> 0 | DI19: =IF((M202=X19), S202, 0) -> 0 | DJ19: =IF((M204=X19), S204, 0) -> 0 | DK19: =IF((M206=X19), S206, 0) -> 0 | DL19: =IF((M209=X19), S209, 0) -> 0 | DM19: =IF((M211=X19), S211, 0) -> 0 | DN19: =IF((M213=X19), S213, 0) -> 0 | DO19: =IF((M215=X19), S215, 0) -> 0 | DP19: =IF((M218=X19), S218, 0) -> 0 | DQ19: =IF((M220=X19), S220, 0) -> 0 | DR19: =IF((M222=X19), S222, 0) -> 0 | DS19: =IF((M224=X19), S224, 0) -> 0 | DT19: =IF((M227=X19), S227, 0) -> 0 | DU19: =IF((M229=X19), S229, 0) -> 0 | DV19: =IF((M231=X19), S231, 0) -> 0 | DW19: =IF((M233=X19), S233, 0) -> 0 | DX19: =IF((M236=X19), S236, 0) -> 0 | DY19: =IF((M238=X19), S238, 0) -> 0 | DZ19: =IF((M240=X19), S240, 0) -> 0 | EA19: =IF((M242=X19), S242, 0) -> 0 | EB19: =IF('NOME + Nº'!E62="SIM",0,IF((M259=X19),V259+IF(H259="SIM",IF((P259=X19),SUM(V260:V263), 0)), IF(H259="SIM",IF((P259=X19),SUM(V260:V263), 0)))) -> 0 | EC19: =IF('NOME + Nº'!E62="SIM",0,IF((M266=X19), V266+IF(H259="SIM",IF((P266=X19),SUM(V267:V270), 0)), IF(H259="SIM",IF((P266=X19),SUM(V267:V270), 0)))) -> 0 | ED19: =IF('NOME + Nº'!E62="SIM",0,IF((M273=X19), V273+IF(H259="SIM",IF((P273=X19),SUM(V274:V277), 0)), IF(H259="SIM",IF((P273=X19),SUM(V274:V277), 0)))) -> 0 | EE19: =IF('NOME + Nº'!E62="SIM",0,IF((M280=X19), V280+IF(H259="SIM",IF((P280=X19),SUM(V281:V284), 0)), IF(H259="SIM",IF((P280=X19),SUM(V281:V284), 0)))) -> 0 | EF19: =IF(AE33=X19,AE49,0) -> 0 | EG19: =IF('NOME + Nº'!D27="SIM",SUM(AB19:EF19),0) -> 0 | EI19: =SUM(EB19:EE19) -> 0
G20: =G11+1 -> 2 | H20: =CONCATENATE("MOLDE ",G20) -> MOLDE 2 | J20: =J17+1 -> 5 | K20: NÃO | L20: 1 | M20: Tec. Externo | N20: =IF((M20=X14),Z14,(IF((M20=X15),Z15,(IF((M20=X16),Z16,(IF((M20=X17),Z17,(IF((M20=X18),Z18,(IF((M20=X19),Z19,(IF((M20=X20),Z20))))))))))))) -> 49.9 | O20: =IF((M20=X14),AA14,(IF((M20=X15),AA15,(IF((M20=X16),AA16,(IF((M20=X17),AA17,(IF((M20=X18),AA18,(IF((M20=X19),AA19,(IF((M20=X20),AA20))))))))))))) -> 140 | P20: =2*Z34+Z33+2*Z38 -> 21.4 | Q20: =(Z32-1)+1.5*Z37 -> 15.5 | R20: =IF(R21<(M21*L20), INT(R21),(M21*L20)) -> 9 | S20: =IF(K20="SIM",(N20*L20*(P20/100)/R20)*L21,0) -> 0 | T20: =R21*L21 -> 0 | U20: =IF(K20="SIM",1,IF(K22="SIM",1,IF(K24="SIM",1,IF(K26="SIM",1,0)))) -> 0 | W20: 7 (NOVO) | X20: ='NOME + Nº'!B28 -> Reforço | Y20: ='NOME + Nº'!D41 -> TNT 120 | Z20: ='NOME + Nº'!H41 -> 7.9 | AA20: ='NOME + Nº'!J41 -> 140 | AB20: =IF((M11=X20), S11, 0) -> 0 | AC20: =IF((M13=X20), S13, 0) -> 1.3588 | AD20: =IF((M15=X20), S15, 0) -> 1.3588 | AE20: =IF((M17=X20), S17, 0) -> 0 | AF20: =IF((M20=X20), S20, 0) -> 0 | AG20: =IF((M22=X20), S22, 0) -> 0 | AH20: =IF((M24=X20), S24, 0) -> 0 | AI20: =IF((M26=X20), S26, 0) -> 0 | AJ20: =IF((M29=X20), S29, 0) -> 0 | AK20: =IF((M31=X20), S31, 0) -> 0 | AL20: =IF((M33=X20), S33, 0) -> 0 | AM20: =IF((M35=X20), S35, 0) -> 0 | AN20: =IF((M38=X20), S38, 0) -> 0 | AO20: =IF((M40=X20), S40, 0) -> 0 | AP20: =IF((M42=X20), S42, 0) -> 0 | AQ20: =IF((M44=X20), S44, 0) -> 0 | AR20: =IF((M47=X20), S47, 0) -> 0 | AS20: =IF((M49=X20), S49, 0) -> 0 | AT20: =IF((M51=X20), S51, 0) -> 0 | AU20: =IF((M53=X20), S53, 0) -> 0 | AV20: =IF((M56=X20), S56, 0) -> 0 | AW20: =IF((M58=X20), S58, 0) -> 0 | AX20: =IF((M60=X20), S60, 0) -> 0 | AY20: =IF((M62=X20), S62, 0) -> 0 | AZ20: =IF((M65=X20), S65, 0) -> 0 | BA20: =IF((M67=X20), S67, 0) -> 0 | BB20: =IF((M69=X20), S69, 0) -> 0 | BC20: =IF((M71=X20), S71, 0) -> 0 | BD20: =IF((M74=X20), S74, 0) -> 0 | BE20: =IF((M76=X20), S76, 0) -> 0 | BF20: =IF((M78=X20), S78, 0) -> 0 | BG20: =IF((M80=X20), S80, 0) -> 0 | BH20: =IF((M83=X20), S83, 0) -> 0 | BI20: =IF((M85=X20), S85, 0) -> 0 | BJ20: =IF((M87=X20), S87, 0) -> 0 | BK20: =IF((M89=X20), S89, 0) -> 0 | BL20: =IF((M92=X20), S92, 0) -> 0 | BM20: =IF((M94=X20), S94, 0) -> 0 | BN20: =IF((M96=X20), S96, 0) -> 0 | BO20: =IF((M98=X20), S98, 0) -> 0 | BP20: =IF((M101=X20), S101, 0) -> 0 | BQ20: =IF((M103=X20), S103, 0) -> 0 | BR20: =IF((M105=X20), S105, 0) -> 0 | BS20: =IF((M107=X20), S107, 0) -> 0 | BT20: =IF((M110=X20), S110, 0) -> 0 | BU20: =IF((M112=X20), S112, 0) -> 0 | BV20: =IF((M114=X20), S114, 0) -> 0 | BW20: =IF((M116=X20), S116, 0) -> 0 | BX20: =IF((M119=X20), S119, 0) -> 0 | BY20: =IF((M121=X20), S121, 0) -> 0 | BZ20: =IF((M123=X20), S123, 0) -> 0 | CA20: =IF((M125=X20), S125, 0) -> 0 | CB20: =IF((M128=X20),S128, 0) -> 0 | CC20: =IF((M130=X20), S130, 0) -> 0 | CD20: =IF((M132=X20), S132, 0) -> 0 | CE20: =IF((M134=X20), S134, 0) -> 0 | CF20: =IF((M137=X20), S137, 0) -> 0 | CG20: =IF((M139=X20), S139, 0) -> 0 | CH20: =IF((M141=X20), S141, 0) -> 0 | CI20: =IF((M143=X20), S143, 0) -> 0 | CJ20: =IF((M146=X20), S146, 0) -> 0 | CK20: =IF((M148=X20), S148, 0) -> 0 | CL20: =IF((M150=X20), S150, 0) -> 0 | CM20: =IF((M152=X20), S152, 0) -> 0 | CN20: =IF((M155=X20), S155, 0) -> 0 | CO20: =IF((M157=X20), S157, 0) -> 0 | CP20: =IF((M159=X20), S159, 0) -> 0 | CQ20: =IF((M161=X20), S161, 0) -> 0 | CR20: =IF((M164=X20), S164, 0) -> 0 | CS20: =IF((M166=X20), S166, 0) -> 0 | CT20: =IF((M168=X20), S168, 0) -> 0 | CU20: =IF((M170=X20), S170, 0) -> 0 | CV20: =IF((M173=X20), S173, 0) -> 0 | CW20: =IF((M175=X20), S175, 0) -> 0 | CX20: =IF((M177=X20), S177, 0) -> 0 | CY20: =IF((M179=X20), S179, 0) -> 0 | CZ20: =IF((M182=X20), S182, 0) -> 0 | DA20: =IF((M184=X20), S184, 0) -> 0 | DB20: =IF((M186=X20), S186, 0) -> 0 | DC20: =IF((M188=X20), S188, 0) -> 0 | DD20: =IF((M191=X20), S191, 0) -> 0 | DE20: =IF((M193=X20), S193, 0) -> 0 | DF20: =IF((M195=X20), S195, 0) -> 0 | DG20: =IF((M197=X20), S197, 0) -> 0 | DH20: =IF((M200=X20), S200, 0) -> 0 | DI20: =IF((M202=X20), S202, 0) -> 0 | DJ20: =IF((M204=X20), S204, 0) -> 0 | DK20: =IF((M206=X20), S206, 0) -> 0 | DL20: =IF((M209=X20), S209, 0) -> 0 | DM20: =IF((M211=X20), S211, 0) -> 0 | DN20: =IF((M213=X20), S213, 0) -> 0 | DO20: =IF((M215=X20), S215, 0) -> 0 | DP20: =IF((M218=X20), S218, 0) -> 0 | DQ20: =IF((M220=X20), S220, 0) -> 0 | DR20: =IF((M222=X20), S222, 0) -> 0 | DS20: =IF((M224=X20), S224, 0) -> 0 | DT20: =IF((M227=X20), S227, 0) -> 0 | DU20: =IF((M229=X20), S229, 0) -> 0 | DV20: =IF((M231=X20), S231, 0) -> 0 | DW20: =IF((M233=X20), S233, 0) -> 0 | DX20: =IF((M236=X20), S236, 0) -> 0 | DY20: =IF((M238=X20), S238, 0) -> 0 | DZ20: =IF((M240=X20), S240, 0) -> 0 | EA20: =IF((M242=X20), S242, 0) -> 0 | EB20: =IF('NOME + Nº'!E62="SIM",0,IF((M259=X20),V259+IF(H259="SIM",IF((P259=X20),SUM(V260:V263), 0)), IF(H259="SIM",IF((P259=X20),SUM(V260:V263), 0)))) -> 0 | EC20: =IF('NOME + Nº'!E62="SIM",0,IF((M266=X20), V266+IF(H259="SIM",IF((P266=X20),SUM(V267:V270), 0)), IF(H259="SIM",IF((P266=X20),SUM(V267:V270), 0)))) -> 0 | ED20: =IF('NOME + Nº'!E62="SIM",0,IF((M273=X14), V273+IF(H259="SIM",IF((P273=X20),SUM(V274:V277), 0)), IF(H259="SIM",IF((P273=X20),SUM(V274:V277), 0)))) -> 0 | EE20: =IF('NOME + Nº'!E62="SIM",0,IF((M280=X20), V280+IF(H259="SIM",IF((P280=X20),SUM(V281:V284), 0)), IF(H259="SIM",IF((P280=X20),SUM(V281:V284), 0)))) -> 0 | EF20: =IF(AE33=X20,AE49,0) -> 0 | EG20: =IF('NOME + Nº'!D28="SIM",SUM(AB20:EF20),0) -> 0 | EI20: =SUM(EB20:EE20) -> 0
H21: NOME | L21: =IF(K20="SIM","1","0") -> 0 | M21: =M16 -> 20 | R21: =O20/(Q20) -> 9.0322581 | W21: 8 | X21: Alça pronta | Y21: ='NOME + Nº'!C66 -> Alça ANNA B 30mm | Z21: =IF(Y21<>0,LOOKUP(Y21,ListaDeEstoque[DESCRIÇÃO],ListaDeEstoque[Preço unitário]),0) -> #N/A | AA21: =IF(Y21<>0,LOOKUP(Y21,ListaDeEstoque[DESCRIÇÃO],ListaDeEstoque[Largura e Dimensões]),0) -> #N/A | AB21: =IF((K259=Y21), V259, 0) -> 0.36397647 | AC21: - | AD21: - | AE21: - | AF21: =SUM(AB21:AE21) -> 0.36397647
B22: Todas as medidas devem estar em centímetros (cm). | J22: =J20+1 -> 6 | K22: NÃO | L22: 1 | M22: Entretela | N22: =IF((M22=X14),Z14,(IF((M22=X15),Z15,(IF((M22=X16),Z16,(IF((M22=X17),Z17,(IF((M22=X18),Z18,(IF((M22=X19),Z19,(IF((M22=X20),Z20))))))))))))) -> 16 | O22: =IF((M22=X14),AA14,(IF((M22=X15),AA15,(IF((M22=X16),AA16,(IF((M22=X17),AA17,(IF((M22=X18),AA18,(IF((M22=X19),AA19,(IF((M22=X20),AA20))))))))))))) -> 75 | P22: =P20 -> 21.4 | Q22: =Q20 -> 15.5 | R22: =IF(R23<(M23*L22), INT(R23),(M23*L22)) -> 4 | S22: =IF(K22="SIM",(N22*L22*(P22/100)/R22)*L23,0) -> 0 | T22: =R23*L23 -> 0 | W22: 9 | X22: Alça pronta | Y22: ='NOME + Nº'!C67 -> 0 | Z22: =IF(Y22<>0,LOOKUP(Y22,ListaDeEstoque[DESCRIÇÃO],ListaDeEstoque[Preço unitário]),0) -> 0 | AA22: =IF(Y22<>0,LOOKUP(Y22,ListaDeEstoque[DESCRIÇÃO],ListaDeEstoque[Largura e Dimensões]),0) -> 0 | AB22: - | AC22: =IF((K266=Y22), V266, 0) -> 0 | AD22: - | AE22: - | AF22: =SUM(AB22:AE22) -> 0 | EE22: CONSUMO TOTAL | EG22: =SUM(EG14:EG20) -> 8.9467765 | EI22: =SUM(EI14:EI20) -> 0.73108758
L23: =IF(K22="SIM","1","0") -> 0 | M23: =M21 -> 20 | R23: =O22/(Q22) -> 4.8387097 | W23: 10 | X23: Alça pronta | Y23: ='NOME + Nº'!C68 -> 0 | Z23: =IF(Y23<>0,LOOKUP(Y23,ListaDeEstoque[DESCRIÇÃO],ListaDeEstoque[Preço unitário]),0) -> 0 | AA23: =IF(Y23<>0,LOOKUP(Y23,ListaDeEstoque[DESCRIÇÃO],ListaDeEstoque[Largura e Dimensões]),0) -> 0 | AB23: - | AC23: - | AD23: =IF((K273=Y23), V273, 0) -> 0 | AE23: - | AF23: =SUM(AB23:AE23) -> 0
J24: =J22+1 -> 7 | K24: NÃO | L24: 1 | M24: Forro | N24: =IF((M24=X14),Z14,(IF((M24=X15),Z15,(IF((M24=X16),Z16,(IF((M24=X17),Z17,(IF((M24=X18),Z18,(IF((M24=X19),Z19,(IF((M24=X20),Z20))))))))))))) -> 19.9 | O24: =IF((M24=X14),AA14,(IF((M24=X15),AA15,(IF((M24=X16),AA16,(IF((M24=X17),AA17,(IF((M24=X18),AA18,(IF((M24=X19),AA19,(IF((M24=X20),AA20))))))))))))) -> 140 | P24: =P22 -> 21.4 | Q24: =Q22 -> 15.5 | R24: =IF(R25<(M25*L24), INT(R25),(M25*L24)) -> 9 | S24: =IF(K24="SIM",(N24*L24*(P24/100)/R24)*L25,0) -> 0 | T24: =R25*L25 -> 0 | W24: 11 | X24: Alça pronta | Y24: ='NOME + Nº'!C69 -> 0 | Z24: =IF(Y24<>0,LOOKUP(Y24,ListaDeEstoque[DESCRIÇÃO],ListaDeEstoque[Preço unitário]),0) -> 0 | AA24: =IF(Y24<>0,LOOKUP(Y24,ListaDeEstoque[DESCRIÇÃO],ListaDeEstoque[Largura e Dimensões]),0) -> 0 | AB24: - | AC24: - | AD24: - | AE24: =IF((K280=Y24), V280, 0) -> 0 | AF24: =SUM(AB24:AE24) -> 0
L25: =IF(K24="SIM","1","0") -> 0 | M25: =M23 -> 20 | R25: =O24/(Q24) -> 9.0322581 | W25: 12 | X25: Alça pronta | Y25: ='NOME + Nº'!C70 -> 0 | Z25: =IF(Y25<>0,LOOKUP(Y25,ListaDeEstoque[DESCRIÇÃO],ListaDeEstoque[Preço unitário]),0) -> 0 | AA25: =IF(Y25<>0,LOOKUP(Y25,ListaDeEstoque[DESCRIÇÃO],ListaDeEstoque[Largura e Dimensões]),0) -> 0 | AB25: =IF((K259=Y25), V259, 0) -> 0 | AC25: =IF((K266=Y25), V266, 0) -> 0 | AD25: =IF((K273=Y25), V273, 0) -> 0 | AE25: =IF((K280=Y25), V280, 0) -> 0 | AF25: =SUM(AB25:AE25) -> 0
B26: Book | J26: =J24+1 -> 8 | K26: NÃO | L26: 1 | M26: Forro | N26: =IF((M26=X14),Z14,(IF((M26=X15),Z15,(IF((M26=X16),Z16,(IF((M26=X17),Z17,(IF((M26=X18),Z18,(IF((M26=X19),Z19,(IF((M26=X20),Z20))))))))))))) -> 19.9 | O26: =IF((M26=X14),AA14,(IF((M26=X15),AA15,(IF((M26=X16),AA16,(IF((M26=X17),AA17,(IF((M26=X18),AA18,(IF((M26=X19),AA19,(IF((M26=X20),AA20))))))))))))) -> 140 | P26: =P24 -> 21.4 | Q26: =Q24 -> 15.5 | R26: =IF(R28<(M28*L26), INT(R28),(M28*L26)) -> 9 | S26: =IF(K26="SIM",(N26*L26*(P26/100)/R26)*L28,0) -> 0 | T26: =R28*L28 -> 0 | W26: 13 | X26: Alça pronta | Y26: ='NOME + Nº'!C71 -> 0 | Z26: =IF(Y26<>0,LOOKUP(Y26,ListaDeEstoque[DESCRIÇÃO],ListaDeEstoque[Preço unitário]),0) -> 0 | AA26: =IF(Y26<>0,LOOKUP(Y26,ListaDeEstoque[DESCRIÇÃO],ListaDeEstoque[Largura e Dimensões]),0) -> 0 | AB26: =IF((K259=Y26), V259, 0) -> 0 | AC26: =IF((K266=Y26), V266, 0) -> 0 | AD26: =IF((K273=Y26), V273, 0) -> 0 | AE26: =IF((K280=Y26), V280, 0) -> 0 | AF26: =SUM(AB26:AE26) -> 0 | CF26: =CONCATENATE("M",CF29) -> M137 | CG26: =CONCATENATE("M",CG29) -> M139 | CH26: =CONCATENATE("M",CH29) -> M141 | CI26: =CONCATENATE("M",CI29) -> M143 | CJ26: =CONCATENATE("M",CJ29) -> M146 | CK26: =CONCATENATE("M",CK29) -> M148 | CL26: =CONCATENATE("M",CL29) -> M150 | CM26: =CONCATENATE("M",CM29) -> M152 | ... EA26: =CONCATENATE("M",EA29) -> M242
B27: Data | C27: Nota | H27: Obs | CF27: =CONCATENATE("S",CF29) -> S137 | CG27: =CONCATENATE("S",CG29) -> S139 | CH27: =CONCATENATE("S",CH29) -> S141 | CI27: =CONCATENATE("S",CI29) -> S143 | CJ27: =CONCATENATE("S",CJ29) -> S146 | CK27: =CONCATENATE("S",CK29) -> S148 | CL27: =CONCATENATE("S",CL29) -> S150 | CM27: =CONCATENATE("S",CM29) -> S152 | ... EA27: =CONCATENATE("S",EA29) -> S242
L28: =IF(K26="SIM","1","0") -> 0 | M28: =M25 -> 20 | R28: =O26/(Q26) -> 9.0322581 | AD28: CONSUMO ALÇAS | AF28: =SUM(AF21:AF26) -> 0.36397647
G29: =G20+1 -> 3 | H29: =CONCATENATE("MOLDE ",G29) -> MOLDE 3 | J29: =J26+1 -> 9 | K29: NÃO | L29: 1 | M29: Tela OU Cristal | N29: =IF((M29=X14),Z14,(IF((M29=X15),Z15,(IF((M29=X16),Z16,(IF((M29=X17),Z17,(IF((M29=X18),Z18,(IF((M29=X19),Z19,(IF((M29=X20),Z20))))))))))))) -> FALSE | O29: =IF((M29=X14),AA14,(IF((M29=X15),AA15,(IF((M29=X16),AA16,(IF((M29=X17),AA17,(IF((M29=X18),AA18,(IF((M29=X19),AA19,(IF((M29=X20),AA20))))))))))))) -> FALSE | P29: =Z34+2*Z37+Z38-P38 -> 4.5 | Q29: =Z33+2*Z38 -> 11.4 | R29: =IF(R30<(M30*L29), INT(R30),(M30*L29)) -> 0 | S29: =IF(K29="SIM",(N29*L29*(P29/100)/R29)*L30,0) -> 0 | T29: =R30*L30 -> 0 | U29: =IF(K29="SIM",1,IF(K31="SIM",1,IF(K33="SIM",1,IF(K35="SIM",1,0)))) -> 0 | CF29: 137 | CG29: =CF29+2 -> 139 | CH29: =CG29+2 -> 141 | CI29: =CH29+2 -> 143 | CJ29: =CI29+3 -> 146 | CK29: =CJ29+2 -> 148 | CL29: =CK29+2 -> 150 | CM29: =CL29+2 -> 152 | CN29: =CM29+3 -> 155 | CO29: =CN29+2 -> 157 | CP29: =CO29+2 -> 159 | CQ29: =CP29+2 -> 161 | CR29: =CQ29+3 -> 164 | CS29: =CR29+2 -> 166 | CT29: =CS29+2 -> 168 | CU29: =CT29+2 -> 170 | CV29: =CU29+3 -> 173 | CW29: =CV29+2 -> 175 | CX29: =CW29+2 -> 177 | CY29: =CX29+2 -> 179 | CZ29: =CY29+3 -> 182 | DA29: =CZ29+2 -> 184 | DB29: =DA29+2 -> 186 | DC29: =DB29+2 -> 188 | DD29: =DC29+3 -> 191 | DE29: =DD29+2 -> 193 | DF29: =DE29+2 -> 195 | DG29: =DF29+2 -> 197 | DH29: =DG29+3 -> 200 | DI29: =DH29+2 -> 202 | DJ29: =DI29+2 -> 204 | DK29: =DJ29+2 -> 206 | DL29: =DK29+3 -> 209 | DM29: =DL29+2 -> 211 | DN29: =DM29+2 -> 213 | DO29: =DN29+2 -> 215 | DP29: =DO29+3 -> 218 | DQ29: =DP29+2 -> 220 | DR29: =DQ29+2 -> 222 | DS29: =DR29+2 -> 224 | DT29: =DS29+3 -> 227 | DU29: =DT29+2 -> 229 | DV29: =DU29+2 -> 231 | DW29: =DV29+2 -> 233 | DX29: =DW29+3 -> 236 | DY29: =DX29+2 -> 238 | DZ29: =DY29+2 -> 240 | EA29: =DZ29+2 -> 242
H30: NOME | L30: =IF(K29="SIM","1","0") -> 0 | M30: =M25 -> 20 | R30: =O29/(Q29) -> 0 | AB30: =N259 -> 49.9 | AC30: =N266 -> 49.9 | AD30: =N273 -> 19.9 | AE30: =N280 -> 49.9
J31: =J29+1 -> 10 | K31: NÃO | L31: 1 | M31: Material Secundário III | N31: =IF((M31=X14),Z14,(IF((M31=X15),Z15,(IF((M31=X16),Z16,(IF((M31=X17),Z17,(IF((M31=X18),Z18,(IF((M31=X19),Z19,(IF((M31=X20),Z20))))))))))))) -> FALSE | O31: =IF((M31=X14),AA14,(IF((M31=X15),AA15,(IF((M31=X16),AA16,(IF((M31=X17),AA17,(IF((M31=X18),AA18,(IF((M31=X19),AA19,(IF((M31=X20),AA20))))))))))))) -> FALSE | P31: =P29 -> 4.5 | Q31: =Q29 -> 11.4 | R31: =IF(R32<(M32*L31), INT(R32),(M32*L31)) -> 0 | S31: =IF(K31="SIM",(N31*L31*(P31/100)/R31)*L32,0) -> 0 | T31: =R32*L32 -> 0 | X31: DIMENSÕES (cm) e Parâmetros
L32: =IF(K31="SIM","1","0") -> 0 | M32: =M30 -> 20 | R32: =O31/(Q31) -> 0 | X32: ='NOME + Nº'!B13 -> Altura (H - Altura máxima) | Z32: ='NOME + Nº'!D13 -> 15 | AC32: Determinando tecido para o VIVO
J33: =J31+1 -> 11 | K33: NÃO | L33: 1 | M33: Forro | N33: =IF((M33=X14),Z14,(IF((M33=X15),Z15,(IF((M33=X16),Z16,(IF((M33=X17),Z17,(IF((M33=X18),Z18,(IF((M33=X19),Z19,(IF((M33=X20),Z20))))))))))))) -> 19.9 | O33: =IF((M33=X14),AA14,(IF((M33=X15),AA15,(IF((M33=X16),AA16,(IF((M33=X17),AA17,(IF((M33=X18),AA18,(IF((M33=X19),AA19,(IF((M33=X20),AA20))))))))))))) -> 140 | P33: =P31 -> 4.5 | Q33: =Q31 -> 11.4 | R33: =IF(R34<(M34*L33), INT(R34),(M34*L33)) -> 12 | S33: =IF(K33="SIM",(N33*L33*(P33/100)/R33)*L34,0) -> 0 | T33: =R34*L34 -> 0 | X33: ='NOME + Nº'!B14 -> Base (B - Vista Frontal) | Z33: ='NOME + Nº'!D14 -> 10 | AC33: MATERIAL: | AE33: Tec. Vivo | AG33: =IF((AE33=X14),Z14,(IF((AE33=X15),Z15,(IF((AE33=X16),Z16,(IF((AE33=X17),Z17,(IF((AE33=X18),Z18,(IF((AE33=X19),Z19))))))))))) -> 49.9
L34: =IF(K33="SIM","1","0") -> 0 | M34: =M32 -> 20 | R34: =O33/(Q33) -> 12.280702 | X34: ='NOME + Nº'!B15 -> Largura (L - Vista Lateral) | Z34: ='NOME + Nº'!D15 -> 5
J35: =J33+1 -> 12 | K35: NÃO | L35: 2 | M35: Forro | N35: =IF((M35=X14),Z14,(IF((M35=X15),Z15,(IF((M35=X16),Z16,(IF((M35=X17),Z17,(IF((M35=X18),Z18,(IF((M35=X19),Z19,(IF((M35=X20),Z20))))))))))))) -> 19.9 | O35: =IF((M35=X14),AA14,(IF((M35=X15),AA15,(IF((M35=X16),AA16,(IF((M35=X17),AA17,(IF((M35=X18),AA18,(IF((M35=X19),AA19,(IF((M35=X20),AA20))))))))))))) -> 140 | P35: =P33 -> 4.5 | Q35: =Q33 -> 11.4 | R35: =IF(R37<(M37*L35), INT(R37),(M37*L35)) -> 12 | S35: =IF(K35="SIM",(N35*L35*(P35/100)/R35)*L37,0) -> 0 | T35: =R37*L37 -> 0 | X35: ='NOME + Nº'!B16 -> (Outro parâmetro) | Z35: ='NOME + Nº'!D16 -> 0 | AC35: Descrição | AG35: Quant
H36: Obs | X36: ='NOME + Nº'!B17 -> (Outro parâmetro) | Z36: ='NOME + Nº'!D17 -> 0 | AC36: VIVO POR MOLDE DA BASE (cm): | AG36: =(PI()*Z32)+5*Z37 -> 52.12389
L37: =IF(K35="SIM","1","0") -> 0 | M37: =M34 -> 20 | R37: =O35/(Q35) -> 12.280702 | X37: ='NOME + Nº'!B18 -> Margem | Z37: ='NOME + Nº'!D18 -> 1 | AC37: QUANTIDADE DE MOLDES POR PEÇA | AG37: 2
G38: =G29+1 -> 4 | H38: =CONCATENATE("MOLDE ",G38) -> MOLDE 4 | J38: =J35+1 -> 13 | K38: NÃO | L38: 2 | M38: Forro | N38: =IF((M38=X14),Z14,(IF((M38=X15),Z15,(IF((M38=X16),Z16,(IF((M38=X17),Z17,(IF((M38=X18),Z18,(IF((M38=X19),Z19,(IF((M38=X20),Z20))))))))))))) -> 19.9 | O38: =IF((M38=X14),AA14,(IF((M38=X15),AA15,(IF((M38=X16),AA16,(IF((M38=X17),AA17,(IF((M38=X18),AA18,(IF((M38=X19),AA19,(IF((M38=X20),AA20))))))))))))) -> 140 | P38: =3.2 -> 3.2 | Q38: =Z33+2*Z38 -> 11.4 | R38: =IF(R39<(M39*L38), INT(R39),(M39*L38)) -> 12 | S38: =IF(K38="SIM",(N38*L38*(P38/100)/R38)*L39,0) -> 0 | T38: =R39*L39 -> 0 | U38: =IF(K38="SIM",1,IF(K40="SIM",1,IF(K42="SIM",1,IF(K44="SIM",1,0)))) -> 0 | X38: Margem_2 | Z38: 0.7 | AC38: LOTE (ENCOMENDA) | AG38: =J8 -> 20
H39: NOME | L39: =IF(K38="SIM","1","0") -> 0 | M39: =M34 -> 20 | R39: =O38/(Q38) -> 12.280702 | X39: Margem_3 | Z39: - | AC39: COMPRIMENTO TOTAL DE VIVO (cm)* | AG39: =(AG36*AG37*AG38)+(AG38*'NOME + Nº'!D18) -> 2104.9556
J40: =J38+1 -> 14 | K40: NÃO | L40: 1 | M40: Tela OU Cristal | N40: =IF((M40=X14),Z14,(IF((M40=X15),Z15,(IF((M40=X16),Z16,(IF((M40=X17),Z17,(IF((M40=X18),Z18,(IF((M40=X19),Z19,(IF((M40=X20),Z20))))))))))))) -> FALSE | O40: =IF((M40=X14),AA14,(IF((M40=X15),AA15,(IF((M40=X16),AA16,(IF((M40=X17),AA17,(IF((M40=X18),AA18,(IF((M40=X19),AA19,(IF((M40=X20),AA20))))))))))))) -> FALSE | P40: =P38 -> 3.2 | Q40: =Q38 -> 11.4 | R40: =IF(R41<(M41*L40), INT(R41),(M41*L40)) -> 0 | S40: =IF(K40="SIM",(N40*L40*(P40/100)/R40)*L41,0) -> 0 | T40: =R41*L41 -> 0 | X40: ='NOME + Nº'!B19 -> Alça | Z40: ='NOME + Nº'!D19 -> SIM | AA40: ='NOME + Nº'!E19 -> 1 | AC40: LARGURA DO VIVO (cm) | AG40: 3
L41: =IF(K40="SIM","1","0") -> 0 | M41: =M39 -> 20 | R41: =O40/(Q40) -> 0 | X41: ='NOME + Nº'!B20 -> Alça Dupla | Z41: ='NOME + Nº'!D20 -> NÃO | AA41: ='NOME + Nº'!E20 -> 1 | AC41: LARGURA DO TECIDO (cm) | AG41: =IF((AE33=X14),AA14,(IF((AE33=X15),AA15,(IF((AE33=X16),AA16,(IF((AE33=X17),AA17,(IF((AE33=X18),AA18,(IF((AE33=X19),AA19))))))))))) -> 140
J42: =J40+1 -> 15 | K42: NÃO | L42: 2 | M42: Forro | N42: =IF((M42=X14),Z14,(IF((M42=X15),Z15,(IF((M42=X16),Z16,(IF((M42=X17),Z17,(IF((M42=X18),Z18,(IF((M42=X19),Z19,(IF((M42=X20),Z20))))))))))))) -> 19.9 | O42: =IF((M42=X14),AA14,(IF((M42=X15),AA15,(IF((M42=X16),AA16,(IF((M42=X17),AA17,(IF((M42=X18),AA18,(IF((M42=X19),AA19,(IF((M42=X20),AA20))))))))))))) -> 140 | P42: =P40 -> 3.2 | Q42: =Q40 -> 11.4 | R42: =IF(R43<(M43*L42), INT(R43),(M43*L42)) -> 12 | S42: =IF(K42="SIM",(N42*L42*(P42/100)/R42)*L43,0) -> 0 | T42: =R43*L43 -> 0 | X42: ='NOME + Nº'!B21 -> Alça Largura | Z42: ='NOME + Nº'!D21 -> 3 | AC42: LOGO, RENDE EM FITAS | AG42: =(AG41/AG40) -> 46.666667
L43: =IF(K42="SIM","1","0") -> 0 | M43: =M41 -> 20 | R43: =O42/(Q42) -> 12.280702 | X43: ='NOME + Nº'!B22 -> Vivo | Z43: ='NOME + Nº'!D22 -> NÃO | AC43: COMPR. TECIDO NECESSÁRIO (m) | AG43: =((AG39/AG42)+Z37)/100 -> 0.46106191
J44: =J42+1 -> 16 | K44: NÃO | L44: 2 | M44: Forro | N44: =IF((M44=X14),Z14,(IF((M44=X15),Z15,(IF((M44=X16),Z16,(IF((M44=X17),Z17,(IF((M44=X18),Z18,(IF((M44=X19),Z19,(IF((M44=X20),Z20))))))))))))) -> 19.9 | O44: =IF((M44=X14),AA14,(IF((M44=X15),AA15,(IF((M44=X16),AA16,(IF((M44=X17),AA17,(IF((M44=X18),AA18,(IF((M44=X19),AA19,(IF((M44=X20),AA20))))))))))))) -> 140 | P44: =P42 -> 3.2 | Q44: =Q42 -> 11.4 | R44: =IF(R46<(M46*L44), INT(R46),(M46*L44)) -> 12 | S44: =IF(K44="SIM",(N44*L44*(P44/100)/R44)*L46,0) -> 0 | T44: =R46*L46 -> 0 | AC44: *Adicionado +1cm de MARGEM por PEÇA
H45: Obs
L46: =IF(K44="SIM","1","0") -> 0 | M46: =M43 -> 20 | R46: =O44/(Q44) -> 12.280702 | AC46: ADICIONAR TECIDO AO ORÇAMENTO? | AG46: =IF('NOME + Nº'!E54="NÃO","SIM","NÃO") -> SIM
G47: =G38+1 -> 5 | H47: =CONCATENATE("MOLDE ",G47) -> MOLDE 5 | J47: =J44+1 -> 17 | K47: NÃO | L47: 1 | M47: Forro | N47: =IF((M47=X14),Z14,(IF((M47=X15),Z15,(IF((M47=X16),Z16,(IF((M47=X17),Z17,(IF((M47=X18),Z18,(IF((M47=X19),Z19,(IF((M47=X20),Z20))))))))))))) -> 19.9 | O47: =IF((M47=X14),AA14,(IF((M47=X15),AA15,(IF((M47=X16),AA16,(IF((M47=X17),AA17,(IF((M47=X18),AA18,(IF((M47=X19),AA19,(IF((M47=X20),AA20))))))))))))) -> 140 | P47: =Z34+Z37+Z38 -> 6.7 | Q47: =Z33+2*Z38 -> 11.4 | R47: =IF(R48<(M48*L47), INT(R48),(M48*L47)) -> 12 | S47: =IF(K47="SIM",(N47*L47*(P47/100)/R47)*L48,0) -> 0 | T47: =R48*L48 -> 0 | U47: =IF(K47="SIM",1,IF(K49="SIM",1,IF(K51="SIM",1,IF(K53="SIM",1,0)))) -> 0 | AE47: INDIVIDUAL | AG47: =AG48/AG38 -> 1.1503495
H48: NOME | L48: =IF(K47="SIM","1","0") -> 0 | M48: =M43 -> 20 | R48: =O47/(Q47) -> 12.280702 | AE48: CONSUMO TOTAL | AG48: =AG43*AG33 -> 23.006989
J49: =J47+1 -> 18 | K49: NÃO | L49: 1 | M49: Forro | N49: =IF((M49=X14),Z14,(IF((M49=X15),Z15,(IF((M49=X16),Z16,(IF((M49=X17),Z17,(IF((M49=X18),Z18,(IF((M49=X19),Z19,(IF((M49=X20),Z20))))))))))))) -> 19.9 | O49: =IF((M49=X14),AA14,(IF((M49=X15),AA15,(IF((M49=X16),AA16,(IF((M49=X17),AA17,(IF((M49=X18),AA18,(IF((M49=X19),AA19,(IF((M49=X20),AA20))))))))))))) -> 140 | P49: =P47 -> 6.7 | Q49: =Q47 -> 11.4 | R49: =IF(R50<(M50*L49), INT(R50),(M50*L49)) -> 12 | S49: =IF(K49="SIM",(N49*L49*(P49/100)/R49)*L50,0) -> 0 | T49: =R50*L50 -> 0 | AE49: =IF(AND(Z43="SIM",AG46="SIM"),AG47,0) -> 0 | AF49: =IF(AND(Z43="SIM",AG46="SIM"),AG48,0) -> 0
L50: =IF(K49="SIM","1","0") -> 0 | M50: =M48 -> 20 | R50: =O49/(Q49) -> 12.280702
J51: =J49+1 -> 19 | K51: NÃO | L51: 2 | M51: Tec. Externo | N51: =IF((M51=X14),Z14,(IF((M51=X15),Z15,(IF((M51=X16),Z16,(IF((M51=X17),Z17,(IF((M51=X18),Z18,(IF((M51=X19),Z19,(IF((M51=X20),Z20))))))))))))) -> 49.9 | O51: =IF((M51=X14),AA14,(IF((M51=X15),AA15,(IF((M51=X16),AA16,(IF((M51=X17),AA17,(IF((M51=X18),AA18,(IF((M51=X19),AA19,(IF((M51=X20),AA20))))))))))))) -> 140 | P51: =P49 -> 6.7 | Q51: =Q49 -> 11.4 | R51: =IF(R52<(M52*L51), INT(R52),(M52*L51)) -> 12 | S51: =IF(K51="SIM",(N51*L51*(P51/100)/R51)*L52,0) -> 0 | T51: =R52*L52 -> 0
L52: =IF(K51="SIM","1","0") -> 0 | M52: =M50 -> 20 | R52: =O51/(Q51) -> 12.280702
J53: =J51+1 -> 20 | K53: NÃO | L53: 2 | M53: Forro | N53: =IF((M53=X14),Z14,(IF((M53=X15),Z15,(IF((M53=X16),Z16,(IF((M53=X17),Z17,(IF((M53=X18),Z18,(IF((M53=X19),Z19,(IF((M53=X20),Z20))))))))))))) -> 19.9 | O53: =IF((M53=X14),AA14,(IF((M53=X15),AA15,(IF((M53=X16),AA16,(IF((M53=X17),AA17,(IF((M53=X18),AA18,(IF((M53=X19),AA19,(IF((M53=X20),AA20))))))))))))) -> 140 | P53: =P51 -> 6.7 | Q53: =Q51 -> 11.4 | R53: =IF(R55<(M55*L53), INT(R55),(M55*L53)) -> 12 | S53: =IF(K53="SIM",(N53*L53*(P53/100)/R53)*L55,0) -> 0 | T53: =R55*L55 -> 0
H54: Obs
L55: =IF(K53="SIM","1","0") -> 0 | M55: =M52 -> 20 | R55: =O53/(Q53) -> 12.280702
G56: =G47+1 -> 6 | H56: =CONCATENATE("MOLDE ",G56) -> MOLDE 6 | J56: =J53+1 -> 21 | K56: NÃO | L56: 1 | M56: Forro | N56: =IF((M56=X14),Z14,(IF((M56=X15),Z15,(IF((M56=X16),Z16,(IF((M56=X17),Z17,(IF((M56=X18),Z18,(IF((M56=X19),Z19,(IF((M56=X20),Z20))))))))))))) -> 19.9 | O56: =IF((M56=X14),AA14,(IF((M56=X15),AA15,(IF((M56=X16),AA16,(IF((M56=X17),AA17,(IF((M56=X18),AA18,(IF((M56=X19),AA19,(IF((M56=X20),AA20))))))))))))) -> 140 | P56: =Z34+Z32+Z37+Z38 -> 21.7 | Q56: =Z33+2*Z38 -> 11.4 | R56: =IF(R57<(M57*L56), INT(R57),(M57*L56)) -> 12 | S56: =IF(K56="SIM",(N56*L56*(P56/100)/R56)*L57,0) -> 0 | T56: =R57*L57 -> 0 | U56: =IF(K56="SIM",1,IF(K58="SIM",1,IF(K60="SIM",1,IF(K62="SIM",1,0)))) -> 0
H57: NOME | L57: =IF(K56="SIM","1","0") -> 0 | M57: =M52 -> 20 | R57: =O56/(Q56) -> 12.280702
J58: =J56+1 -> 22 | K58: NÃO | L58: 1 | M58: Entretela | N58: =IF((M58=X14),Z14,(IF((M58=X15),Z15,(IF((M58=X16),Z16,(IF((M58=X17),Z17,(IF((M58=X18),Z18,(IF((M58=X19),Z19,(IF((M58=X20),Z20))))))))))))) -> 16 | O58: =IF((M58=X14),AA14,(IF((M58=X15),AA15,(IF((M58=X16),AA16,(IF((M58=X17),AA17,(IF((M58=X18),AA18,(IF((M58=X19),AA19,(IF((M58=X20),AA20))))))))))))) -> 75 | P58: =P56 -> 21.7 | Q58: =Q56 -> 11.4 | R58: =IF(R59<(M59*L58), INT(R59),(M59*L58)) -> 6 | S58: =IF(K58="SIM",(N58*L58*(P58/100)/R58)*L59,0) -> 0 | T58: =R59*L59 -> 0
L59: =IF(K58="SIM","1","0") -> 0 | M59: =M57 -> 20 | R59: =O58/(Q58) -> 6.5789474
J60: =J58+1 -> 23 | K60: NÃO | L60: 1 | M60: Forro | N60: =IF((M60=X14),Z14,(IF((M60=X15),Z15,(IF((M60=X16),Z16,(IF((M60=X17),Z17,(IF((M60=X18),Z18,(IF((M60=X19),Z19,(IF((M60=X20),Z20))))))))))))) -> 19.9 | O60: =IF((M60=X14),AA14,(IF((M60=X15),AA15,(IF((M60=X16),AA16,(IF((M60=X17),AA17,(IF((M60=X18),AA18,(IF((M60=X19),AA19,(IF((M60=X20),AA20))))))))))))) -> 140 | P60: =P58 -> 21.7 | Q60: =Q58 -> 11.4 | R60: =IF(R61<(M61*L60), INT(R61),(M61*L60)) -> 12 | S60: =IF(K60="SIM",(N60*L60*(P60/100)/R60)*L61,0) -> 0 | T60: =R61*L61 -> 0
L61: =IF(K60="SIM","1","0") -> 0 | M61: =M59 -> 20 | R61: =O60/(Q60) -> 12.280702
J62: =J60+1 -> 24 | K62: NÃO | L62: 2 | M62: Forro | N62: =IF((M62=X14),Z14,(IF((M62=X15),Z15,(IF((M62=X16),Z16,(IF((M62=X17),Z17,(IF((M62=X18),Z18,(IF((M62=X19),Z19,(IF((M62=X20),Z20))))))))))))) -> 19.9 | O62: =IF((M62=X14),AA14,(IF((M62=X15),AA15,(IF((M62=X16),AA16,(IF((M62=X17),AA17,(IF((M62=X18),AA18,(IF((M62=X19),AA19,(IF((M62=X20),AA20))))))))))))) -> 140 | P62: =P60 -> 21.7 | Q62: =Q60 -> 11.4 | R62: =IF(R64<(M64*L62), INT(R64),(M64*L62)) -> 12 | S62: =IF(K62="SIM",(N62*L62*(P62/100)/R62)*L64,0) -> 0 | T62: =R64*L64 -> 0
H63: Obs
L64: =IF(K62="SIM","1","0") -> 0 | M64: =M61 -> 20 | R64: =O62/(Q62) -> 12.280702
G65: =G56+1 -> 7 | H65: =CONCATENATE("MOLDE ",G65) -> MOLDE 7 | J65: =J62+1 -> 25 | K65: NÃO | L65: 2 | M65: Forro | N65: =IF((M65=X14),Z14,(IF((M65=X15),Z15,(IF((M65=X16),Z16,(IF((M65=X17),Z17,(IF((M65=X18),Z18,(IF((M65=X19),Z19,(IF((M65=X20),Z20))))))))))))) -> 19.9 | O65: =IF((M65=X14),AA14,(IF((M65=X15),AA15,(IF((M65=X16),AA16,(IF((M65=X17),AA17,(IF((M65=X18),AA18,(IF((M65=X19),AA19,(IF((M65=X20),AA20))))))))))))) -> 140 | P65: 20 | Q65: =Q29-(Z37/2) -> 10.9 | R65: =IF(R66<(M66*L65), INT(R66),(M66*L65)) -> 12 | S65: =IF(K65="SIM",(N65*L65*(P65/100)/R65)*L66,0) -> 0 | T65: =R66*L66 -> 0 | U65: =IF(K65="SIM",1,IF(K67="SIM",1,IF(K69="SIM",1,IF(K71="SIM",1,0)))) -> 0
H66: NOME | L66: =IF(K65="SIM","1","0") -> 0 | M66: =M61 -> 20 | R66: =O65/(Q65) -> 12.844037
J67: =J65+1 -> 26 | K67: NÃO | L67: 1 | M67: Tec. Externo | N67: =IF((M67=X14),Z14,(IF((M67=X15),Z15,(IF((M67=X16),Z16,(IF((M67=X17),Z17,(IF((M67=X18),Z18,(IF((M67=X19),Z19,(IF((M67=X20),Z20))))))))))))) -> 49.9 | O67: =IF((M67=X14),AA14,(IF((M67=X15),AA15,(IF((M67=X16),AA16,(IF((M67=X17),AA17,(IF((M67=X18),AA18,(IF((M67=X19),AA19,(IF((M67=X20),AA20))))))))))))) -> 140 | P67: =P65 -> 20 | Q67: =Q65 -> 10.9 | R67: =IF(R68<(M68*L67), INT(R68),(M68*L67)) -> 12 | S67: =IF(K67="SIM",(N67*L67*(P67/100)/R67)*L68,0) -> 0 | T67: =R68*L68 -> 0
L68: =IF(K67="SIM","1","0") -> 0 | M68: =M66 -> 20 | R68: =O67/(Q67) -> 12.844037
J69: =J67+1 -> 27 | K69: NÃO | L69: 1 | M69: Entretela | N69: =IF((M69=X14),Z14,(IF((M69=X15),Z15,(IF((M69=X16),Z16,(IF((M69=X17),Z17,(IF((M69=X18),Z18,(IF((M69=X19),Z19,(IF((M69=X20),Z20))))))))))))) -> 16 | O69: =IF((M69=X14),AA14,(IF((M69=X15),AA15,(IF((M69=X16),AA16,(IF((M69=X17),AA17,(IF((M69=X18),AA18,(IF((M69=X19),AA19,(IF((M69=X20),AA20))))))))))))) -> 75 | P69: =P67 -> 20 | Q69: =Q67 -> 10.9 | R69: =IF(R70<(M70*L69), INT(R70),(M70*L69)) -> 6 | S69: =IF(K69="SIM",(N69*L69*(P69/100)/R69)*L70,0) -> 0 | T69: =R70*L70 -> 0
L70: =IF(K69="SIM","1","0") -> 0 | M70: =M68 -> 20 | R70: =O69/(Q69) -> 6.8807339
J71: =J69+1 -> 28 | K71: NÃO | L71: 2 | M71: Forro | N71: =IF((M71=X14),Z14,(IF((M71=X15),Z15,(IF((M71=X16),Z16,(IF((M71=X17),Z17,(IF((M71=X18),Z18,(IF((M71=X19),Z19,(IF((M71=X20),Z20))))))))))))) -> 19.9 | O71: =IF((M71=X14),AA14,(IF((M71=X15),AA15,(IF((M71=X16),AA16,(IF((M71=X17),AA17,(IF((M71=X18),AA18,(IF((M71=X19),AA19,(IF((M71=X20),AA20))))))))))))) -> 140 | P71: =P69 -> 20 | Q71: =Q69 -> 10.9 | R71: =IF(R73<(M73*L71), INT(R73),(M73*L71)) -> 12 | S71: =IF(K71="SIM",(N71*L71*(P71/100)/R71)*L73,0) -> 0 | T71: =R73*L73 -> 0
H72: Obs
L73: =IF(K71="SIM","1","0") -> 0 | M73: =M70 -> 20 | R73: =O71/(Q71) -> 12.844037
G74: =G65+1 -> 8 | H74: =CONCATENATE("MOLDE ",G74) -> MOLDE 8 | J74: =J71+1 -> 29 | K74: NÃO | L74: 2 | M74: Tec. Externo | N74: =IF((M74=X14),Z14,(IF((M74=X15),Z15,(IF((M74=X16),Z16,(IF((M74=X17),Z17,(IF((M74=X18),Z18,(IF((M74=X19),Z19,(IF((M74=X20),Z20))))))))))))) -> 49.9 | O74: =IF((M74=X14),AA14,(IF((M74=X15),AA15,(IF((M74=X16),AA16,(IF((M74=X17),AA17,(IF((M74=X18),AA18,(IF((M74=X19),AA19,(IF((M74=X20),AA20))))))))))))) -> 140 | P74: =P47 -> 6.7 | Q74: =Q65 -> 10.9 | R74: =IF(R75<(M75*L74), INT(R75),(M75*L74)) -> 12 | S74: =IF(K74="SIM",(N74*L74*(P74/100)/R74)*L75,0) -> 0 | T74: =R75*L75 -> 0 | U74: =IF(K74="SIM",1,IF(K76="SIM",1,IF(K78="SIM",1,IF(K80="SIM",1,0)))) -> 0
H75: NOME | L75: =IF(K74="SIM","1","0") -> 0 | M75: =M70 -> 20 | R75: =O74/(Q74) -> 12.844037
J76: =J74+1 -> 30 | K76: NÃO | L76: 2 | M76: Entretela | N76: =IF((M76=X14),Z14,(IF((M76=X15),Z15,(IF((M76=X16),Z16,(IF((M76=X17),Z17,(IF((M76=X18),Z18,(IF((M76=X19),Z19,(IF((M76=X20),Z20))))))))))))) -> 16 | O76: =IF((M76=X14),AA14,(IF((M76=X15),AA15,(IF((M76=X16),AA16,(IF((M76=X17),AA17,(IF((M76=X18),AA18,(IF((M76=X19),AA19,(IF((M76=X20),AA20))))))))))))) -> 75 | P76: =P74 -> 6.7 | Q76: =Q74 -> 10.9 | R76: =IF(R77<(M77*L76), INT(R77),(M77*L76)) -> 6 | S76: =IF(K76="SIM",(N76*L76*(P76/100)/R76)*L77,0) -> 0 | T76: =R77*L77 -> 0
L77: =IF(K76="SIM","1","0") -> 0 | M77: =M75 -> 20 | R77: =O76/(Q76) -> 6.8807339
J78: =J76+1 -> 31 | K78: NÃO | L78: 2 | M78: Tec. Externo | N78: =IF((M78=X14),Z14,(IF((M78=X15),Z15,(IF((M78=X16),Z16,(IF((M78=X17),Z17,(IF((M78=X18),Z18,(IF((M78=X19),Z19,(IF((M78=X20),Z20))))))))))))) -> 49.9 | O78: =IF((M78=X14),AA14,(IF((M78=X15),AA15,(IF((M78=X16),AA16,(IF((M78=X17),AA17,(IF((M78=X18),AA18,(IF((M78=X19),AA19,(IF((M78=X20),AA20))))))))))))) -> 140 | P78: =P76 -> 6.7 | Q78: =Q76 -> 10.9 | R78: =IF(R79<(M79*L78), INT(R79),(M79*L78)) -> 12 | S78: =IF(K78="SIM",(N78*L78*(P78/100)/R78)*L79,0) -> 0 | T78: =R79*L79 -> 0
L79: =IF(K78="SIM","1","0") -> 0 | M79: =M77 -> 20 | R79: =O78/(Q78) -> 12.844037
J80: =J78+1 -> 32 | K80: NÃO | L80: 2 | M80: Forro | N80: =IF((M80=X14),Z14,(IF((M80=X15),Z15,(IF((M80=X16),Z16,(IF((M80=X17),Z17,(IF((M80=X18),Z18,(IF((M80=X19),Z19,(IF((M80=X20),Z20))))))))))))) -> 19.9 | O80: =IF((M80=X14),AA14,(IF((M80=X15),AA15,(IF((M80=X16),AA16,(IF((M80=X17),AA17,(IF((M80=X18),AA18,(IF((M80=X19),AA19,(IF((M80=X20),AA20))))))))))))) -> 140 | P80: =P78 -> 6.7 | Q80: =Q78 -> 10.9 | R80: =IF(R82<(M82*L80), INT(R82),(M82*L80)) -> 12 | S80: =IF(K80="SIM",(N80*L80*(P80/100)/R80)*L82,0) -> 0 | T80: =R82*L82 -> 0
H81: Obs
L82: =IF(K80="SIM","1","0") -> 0 | M82: =M79 -> 20 | R82: =O80/(Q80) -> 12.844037
G83: =G74+1 -> 9 | H83: =CONCATENATE("MOLDE ",G83) -> MOLDE 9 | J83: =J80+1 -> 33 | K83: NÃO | L83: 2 | M83: Forro | N83: =IF((M83=X14),Z14,(IF((M83=X15),Z15,(IF((M83=X16),Z16,(IF((M83=X17),Z17,(IF((M83=X18),Z18,(IF((M83=X19),Z19,(IF((M83=X20),Z20))))))))))))) -> 19.9 | O83: =IF((M83=X14),AA14,(IF((M83=X15),AA15,(IF((M83=X16),AA16,(IF((M83=X17),AA17,(IF((M83=X18),AA18,(IF((M83=X19),AA19,(IF((M83=X20),AA20))))))))))))) -> 140 | P83: =IF((2*P65/3)<16,16,2*P65/3)+(2*Z37) -> 18 | Q83: =Q65 -> 10.9 | R83: =IF(R84<(M84*L83), INT(R84),(M84*L83)) -> 12 | S83: =IF(K83="SIM",(N83*L83*(P83/100)/R83)*L84,0) -> 0 | T83: =R84*L84 -> 0 | U83: =IF(K83="SIM",1,IF(K85="SIM",1,IF(K87="SIM",1,IF(K89="SIM",1,0)))) -> 0
H84: NOME | L84: =IF(K83="SIM","1","0") -> 0 | M84: =M79 -> 20 | R84: =O83/(Q83) -> 12.844037
J85: =J83+1 -> 34 | K85: NÃO | L85: 1 | M85: Entretela | N85: =IF((M85=X14),Z14,(IF((M85=X15),Z15,(IF((M85=X16),Z16,(IF((M85=X17),Z17,(IF((M85=X18),Z18,(IF((M85=X19),Z19,(IF((M85=X20),Z20))))))))))))) -> 16 | O85: =IF((M85=X14),AA14,(IF((M85=X15),AA15,(IF((M85=X16),AA16,(IF((M85=X17),AA17,(IF((M85=X18),AA18,(IF((M85=X19),AA19,(IF((M85=X20),AA20))))))))))))) -> 75 | P85: =P83 -> 18 | Q85: =Q83 -> 10.9 | R85: =IF(R86<(M86*L85), INT(R86),(M86*L85)) -> 6 | S85: =IF(K85="SIM",(N85*L85*(P85/100)/R85)*L86,0) -> 0 | T85: =R86*L86 -> 0
L86: =IF(K85="SIM","1","0") -> 0 | M86: =M84 -> 20 | R86: =O85/(Q85) -> 6.8807339
J87: =J85+1 -> 35 | K87: NÃO | L87: 1 | M87: Tec. Externo | N87: =IF((M87=X14),Z14,(IF((M87=X15),Z15,(IF((M87=X16),Z16,(IF((M87=X17),Z17,(IF((M87=X18),Z18,(IF((M87=X19),Z19,(IF((M87=X20),Z20))))))))))))) -> 49.9 | O87: =IF((M87=X14),AA14,(IF((M87=X15),AA15,(IF((M87=X16),AA16,(IF((M87=X17),AA17,(IF((M87=X18),AA18,(IF((M87=X19),AA19,(IF((M87=X20),AA20))))))))))))) -> 140 | P87: =P85 -> 18 | Q87: =Q85 -> 10.9 | R87: =IF(R88<(M88*L87), INT(R88),(M88*L87)) -> 12 | S87: =IF(K87="SIM",(N87*L87*(P87/100)/R87)*L88,0) -> 0 | T87: =R88*L88 -> 0
L88: =IF(K87="SIM","1","0") -> 0 | M88: =M86 -> 20 | R88: =O87/(Q87) -> 12.844037
J89: =J87+1 -> 36 | K89: NÃO | L89: 2 | M89: Forro | N89: =IF((M89=X14),Z14,(IF((M89=X15),Z15,(IF((M89=X16),Z16,(IF((M89=X17),Z17,(IF((M89=X18),Z18,(IF((M89=X19),Z19,(IF((M89=X20),Z20))))))))))))) -> 19.9 | O89: =IF((M89=X14),AA14,(IF((M89=X15),AA15,(IF((M89=X16),AA16,(IF((M89=X17),AA17,(IF((M89=X18),AA18,(IF((M89=X19),AA19,(IF((M89=X20),AA20))))))))))))) -> 140 | P89: =P87 -> 18 | Q89: =Q87 -> 10.9 | R89: =IF(R91<(M91*L89), INT(R91),(M91*L89)) -> 12 | S89: =IF(K89="SIM",(N89*L89*(P89/100)/R89)*L91,0) -> 0 | T89: =R91*L91 -> 0
H90: Obs
L91: =IF(K89="SIM","1","0") -> 0 | M91: =M88 -> 20 | R91: =O89/(Q89) -> 12.844037
G92: =G83+1 -> 10 | H92: =CONCATENATE("MOLDE ",G92) -> MOLDE 10 | J92: =J89+1 -> 37 | K92: NÃO | L92: 1 | M92: Forro | N92: =IF((M92=X14),Z14,(IF((M92=X15),Z15,(IF((M92=X16),Z16,(IF((M92=X17),Z17,(IF((M92=X18),Z18,(IF((M92=X19),Z19,(IF((M92=X20),Z20))))))))))))) -> 19.9 | O92: =IF((M92=X14),AA14,(IF((M92=X15),AA15,(IF((M92=X16),AA16,(IF((M92=X17),AA17,(IF((M92=X18),AA18,(IF((M92=X19),AA19,(IF((M92=X20),AA20))))))))))))) -> 140 | P92: =P83 -> 18 | Q92: =Q38 -> 11.4 | R92: =IF(R93<(M93*L92), INT(R93),(M93*L92)) -> 12 | S92: =IF(K92="SIM",(N92*L92*(P92/100)/R92)*L93,0) -> 0 | T92: =R93*L93 -> 0 | U92: =IF(K92="SIM",1,IF(K94="SIM",1,IF(K96="SIM",1,IF(K98="SIM",1,0)))) -> 0
H93: NOME | L93: =IF(K92="SIM","1","0") -> 0 | M93: =M88 -> 20 | R93: =O92/(Q92) -> 12.280702
J94: =J92+1 -> 38 | K94: NÃO | L94: 4 | M94: Tec. Externo | N94: =IF((M94=X14),Z14,(IF((M94=X15),Z15,(IF((M94=X16),Z16,(IF((M94=X17),Z17,(IF((M94=X18),Z18,(IF((M94=X19),Z19,(IF((M94=X20),Z20))))))))))))) -> 49.9 | O94: =IF((M94=X14),AA14,(IF((M94=X15),AA15,(IF((M94=X16),AA16,(IF((M94=X17),AA17,(IF((M94=X18),AA18,(IF((M94=X19),AA19,(IF((M94=X20),AA20))))))))))))) -> 140 | P94: =P92 -> 18 | Q94: =Q92 -> 11.4 | R94: =IF(R95<(M95*L94), INT(R95),(M95*L94)) -> 12 | S94: =IF(K94="SIM",(N94*L94*(P94/100)/R94)*L95,0) -> 0 | T94: =R95*L95 -> 0
L95: =IF(K94="SIM","1","0") -> 0 | M95: =M93 -> 20 | R95: =O94/(Q94) -> 12.280702
J96: =J94+1 -> 39 | K96: NÃO | L96: 4 | M96: Tec. Externo | N96: =IF((M96=X14),Z14,(IF((M96=X15),Z15,(IF((M96=X16),Z16,(IF((M96=X17),Z17,(IF((M96=X18),Z18,(IF((M96=X19),Z19,(IF((M96=X20),Z20))))))))))))) -> 49.9 | O96: =IF((M96=X14),AA14,(IF((M96=X15),AA15,(IF((M96=X16),AA16,(IF((M96=X17),AA17,(IF((M96=X18),AA18,(IF((M96=X19),AA19,(IF((M96=X20),AA20))))))))))))) -> 140 | P96: =P94 -> 18 | Q96: =Q94 -> 11.4 | R96: =IF(R97<(M97*L96), INT(R97),(M97*L96)) -> 12 | S96: =IF(K96="SIM",(N96*L96*(P96/100)/R96)*L97,0) -> 0 | T96: =R97*L97 -> 0
L97: =IF(K96="SIM","1","0") -> 0 | M97: =M95 -> 20 | R97: =O96/(Q96) -> 12.280702
J98: =J96+1 -> 40 | K98: NÃO | L98: 2 | M98: Forro | N98: =IF((M98=X14),Z14,(IF((M98=X15),Z15,(IF((M98=X16),Z16,(IF((M98=X17),Z17,(IF((M98=X18),Z18,(IF((M98=X19),Z19,(IF((M98=X20),Z20))))))))))))) -> 19.9 | O98: =IF((M98=X14),AA14,(IF((M98=X15),AA15,(IF((M98=X16),AA16,(IF((M98=X17),AA17,(IF((M98=X18),AA18,(IF((M98=X19),AA19,(IF((M98=X20),AA20))))))))))))) -> 140 | P98: =P96 -> 18 | Q98: =Q96 -> 11.4 | R98: =IF(R100<(M100*L98), INT(R100),(M100*L98)) -> 12 | S98: =IF(K98="SIM",(N98*L98*(P98/100)/R98)*L100,0) -> 0 | T98: =R100*L100 -> 0
H99: Obs
L100: =IF(K98="SIM","1","0") -> 0 | M100: =M97 -> 20 | R100: =O98/(Q98) -> 12.280702
G101: =G92+1 -> 11 | H101: =CONCATENATE("MOLDE ",G101) -> MOLDE 11 | J101: =J98+1 -> 41 | K101: NÃO | L101: 1 | M101: Forro | N101: =IF((M101=X14),Z14,(IF((M101=X15),Z15,(IF((M101=X16),Z16,(IF((M101=X17),Z17,(IF((M101=X18),Z18,(IF((M101=X19),Z19,(IF((M101=X20),Z20))))))))))))) -> 19.9 | O101: =IF((M101=X14),AA14,(IF((M101=X15),AA15,(IF((M101=X16),AA16,(IF((M101=X17),AA17,(IF((M101=X18),AA18,(IF((M101=X19),AA19,(IF((M101=X20),AA20))))))))))))) -> 140 | P101: 36 | Q101: 24 | R101: =IF(R102<(M102*L101), INT(R102),(M102*L101)) -> 5 | S101: =IF(K101="SIM",(N101*L101*(P101/100)/R101)*L102,0) -> 0 | T101: =R102*L102 -> 0 | U101: =IF(K101="SIM",1,IF(K103="SIM",1,IF(K105="SIM",1,IF(K107="SIM",1,0)))) -> 0
...

Sheet ENFESTO
B2: Leitura dos dados
B3: valores fixos (escritos pelo usuário) | F3: A B C | H3: Descrição
B4: valores calculados ou dependentes de outra célula | F4: A B C | H4: TIPO DE ORÇAMENTO DE TECIDOS | R4: TOTAL
H5: Tipos | J5: Recomendação | L5: Características | R5: m | S5: R$
B6: Notas e observações | F6: A B C | H6: MOLDES | J6: INDIVIDUAL | L6: Máximo de aproveitamento | O6: Considera moldes individualmente | R6: =AN28 -> 4.1447059 | S6: =AO28 -> 206.82082
B7: Neutras | F7: A B C | H7: ENFESTO | J7: LOTE OU EXCLUSIVO | L7: Aproveitamento limitado | O7: Considera consumo total do material | R7: =AL288 -> #DIV/0! | S7: =AM288 -> #DIV/0!
B8: Alternativas (CLIQUE NO BOTÃO). Ex. "SIM" ou "NÃO" | F8: NÃO | H8: MISTO | J8: CONDICIONAL | L8: Varia por material empregado | O8: Características mistas | R8: - | S8: -
B9: Correto | F9: A B C
B10: Incorreto | F10: A B C | W10: =MODELAGEM!J4 -> REF. NOME + Nº - 15H x 10B x 5L (cm)
B11: Controles de cálculos, números livres, encerramento de tabela ou parte | F11: A B C | I11: RESUMO | U11: CONSUMO DE TECIDO POR MOLDE
U12: ENCOMENDA | V12: MÍNIMO IDEAL
B13: Destaques livres ou estéticos | F13: Cores diversas
I14: 1 | J14: =ENFESTO!W10 -> REF. NOME + Nº - 15H x 10B x 5L (cm) | T14: LOTE | U14: ='NOME + Nº'!H128 -> 20 | V14: =INT(MAX(MODELAGEM!T11:T68)) -> 2
J15: CONSUMO DE TECIDO POR MOLDES | AB15: METRO NECESSÁRIO | AC15: MARGEM ENFESTO | AE15: TOTAL | AG15: Quantidade de Moldes | AO15: CONSUMO DE MATERIAL POR MOLDE
B16: Legendas | J16: =IF('NOME + Nº'!$C$32="NÃO","!!MODELAGEM não atualizada!!","") | V16: Molde | Y16: MATERIAL | AA16: VALOR (R$/m) | AE16: (m) | AF16: (R$)
B17: No rótulo do PROCESSO, escolha as opções para sinalizar uso do quadro | F17: SIM | K17: ENCOMENDA | T17: =MODELAGEM!H11 -> MOLDE 1 | U17: 1 | V17: =MODELAGEM!K11 -> SIM | W17: =MODELAGEM!H12 -> CORPO | Y17: =MODELAGEM!M11 -> Tec. Externo | AA17: =MODELAGEM!N11 -> 49.9 | AB17: =IF(V17="NÃO",0,((Z18*MODELAGEM!P11/(MODELAGEM!R11/MODELAGEM!L11))/100)) -> 3.44 | AC17: 2.5 | AE17: =IF(V17="NÃO",0,((Z18/(MODELAGEM!R11))*(AC17*2/100)+AB17)*W18) -> 3.94 | AF17: =AE17*AA17 -> 196.606 | AG17: =IF(V17="SIM",1,IF(V19="SIM",1,IF(V21="SIM",1,0))) -> 1 | AO17: Moldes Consumo
F18: NÃO | J18: LOTE | K18: =ENFESTO!U14 -> 20 | W18: =IF(V17="SIM","1","0") -> 1 | Z18: =U14 -> 20 | AJ18: LISTA DE TECIDOS | AN18: Soma Total | AP18: =T17 -> MOLDE 1 | AT18: =T26 -> MOLDE 2 | AX18: =T35 -> MOLDE 3 | BB18: =T44 -> MOLDE 4 | BF18: =T53 -> MOLDE 5 | BJ18: =T62 -> MOLDE 6 | BN18: =T71 -> MOLDE 7 | BR18: =T80 -> MOLDE 8 | BV18: =T89 -> MOLDE 9 | BZ18: =T98 -> MOLDE 10 | CD18: =T107 -> MOLDE 11 | CH18: =T116 -> MOLDE 12 | CL18: =T125 -> MOLDE 13 | CP18: =T134 -> MOLDE 14 | CT18: =T143 -> MOLDE 15 | CX18: =T152 -> MOLDE 16 | DB18: =T161 -> MOLDE 17 | DF18: =T170 -> MOLDE 18 | DJ18: =T179 -> MOLDE 19 | DN18: =T188 -> MOLDE 20 | DR18: =T197 -> MOLDE 21 | DV18: =T206 -> MOLDE 22 | DZ18: =T215 -> MOLDE 23 | ED18: =T224 -> MOLDE 24 | EH18: =T233 -> MOLDE 25 | EL18: =T242 -> MOLDE 26 | EP18: ALÇA | ET18: VIVO | EU18: Soma Total | EW18: ALÇAS Soma Total
B19: Escreva os FORNECEDORES nos quadros de Materiais com LETRAS MAIÚSCULAS. Escrever materiais iniciando com letras MAIÚSCULAS. | J19: LISTA DE TECIDOS | N19: Soma Total | U19: =U17+1 -> 2 | V19: =MODELAGEM!K13 -> SIM | W19: ' ' | Y19: =MODELAGEM!M13 -> Reforço | AA19: =MODELAGEM!N13 -> 7.9 | AB19: =IF(V19="NÃO",0,((Z20*MODELAGEM!P13/(MODELAGEM!R13/MODELAGEM!L13))/100)) -> 3.44 | AC19: =AC17 -> 2.5 | AE19: =IF(V19="NÃO",0,((Z20/(MODELAGEM!R13))*(AC19*2/100)+AB19)*W20) -> 3.94 | AF19: =AE19*AA19 -> 31.126 | AJ19: TECIDO | AK19: Descrição | AL19: VALOR (R$/m) | AM19: Largura | AN19: Metros | AO19: R$ | AP19: 1 | AQ19: =AP19+1 -> 2 | AR19: =AQ19+1 -> 3 | AS19: =AR19+1 -> 4 | AT19: =AS19+1 -> 5 | AU19: =AT19+1 -> 6 | AV19: =AU19+1 -> 7 | AW19: =AV19+1 -> 8 | AX19: =AW19+1 -> 9 | ... ET19: =ES19+1 -> 109
J20: TECIDO | K20: Descrição | L20: VALOR (R$/m) | M20: Largura | N20: Metros | O20: R$ | W20: =IF(V19="SIM","1","0") -> 1 | Z20: =Z18 -> 20 | AI20: 1 | AJ20: ='NOME + Nº'!B35 -> Tec. Externo | AK20: =IF('NOME + Nº'!D35=0," ",'NOME + Nº'!D35) -> Aquablock | AL20: ='NOME + Nº'!H35 -> 49.9 | AM20: ='NOME + Nº'!J35 -> 140 | AN20: =IF(AL20<>0,AO20/AL20,0) -> 4.1447059 | AO20: =SUM(AP20:ET20) -> 206.82082 | AP20: =IF((Y17=AJ20), AF17, 0) -> 196.606 | AQ20: =IF((Y19=AJ20), AF19, 0) -> 0 | AR20: =IF((Y21=AJ20), AF21, 0) -> 0 | AS20: =IF((Y23=AJ20), AF23, 0) -> 0 | AT20: =IF((Y26=AJ20), AF26, 0) -> 0 | AU20: =IF((Y28=AJ20), AF28, 0) -> 0 | AV20: =IF((Y30=AJ20), AF30, 0) -> 0 | AW20: =IF((Y32=AJ20), AF32, 0) -> 0 | AX20: =IF((Y35=AJ20), AF35, 0) -> 0 | AY20: =IF((Y37=AJ20), AF37, 0) -> 0 | AZ20: =IF((Y39=AJ20), AF39, 0) -> 0 | BA20: =IF((Y41=AJ20), AF41, 0) -> 0 | BB20: =IF((Y44=AJ20), AF44, 0) -> 0 | BC20: =IF((Y46=AJ20), AF46, 0) -> 0 | BD20: =IF((Y48=AJ20), AF48, 0) -> 0 | BE20: =IF((Y50=AJ20), AF50, 0) -> 0 | BF20: =IF((Y53=AJ20), AF53, 0) -> 0 | BG20: =IF((Y55=AJ20), AF55, 0) -> 0 | BH20: =IF((Y57=AJ20), AF57, 0) -> 0 | BI20: =IF((Y59=AJ20), AF59, 0) -> 0 | BJ20: =IF((Y62=AJ20), AF62, 0) -> 0 | BK20: =IF((Y64=AJ20), AF64, 0) -> 0 | BL20: =IF((Y66=AJ20), AF66, 0) -> 0 | BM20: =IF((Y68=AJ20), AF68, 0) -> 0 | BN20: =IF((Y71=AJ20), AF71, 0) -> 0 | BO20: =IF((Y73=AJ20), AF73, 0) -> 0 | BP20: =IF((Y75=AJ20), AF75, 0) -> 0 | BQ20: =IF((Y77=AJ20), AF77, 0) -> 0 | BR20: =IF((Y80=AJ20), AF80, 0) -> 0 | BS20: =IF((Y82=AJ20), AF82, 0) -> 0 | BT20: =IF((Y84=AJ20), AF84, 0) -> 0 | BU20: =IF((Y86=AJ20), AF86, 0) -> 0 | BV20: =IF((Y89=AJ20), AF89, 0) -> 0 | BW20: =IF((Y91=AJ20), AF91, 0) -> 0 | BX20: =IF((Y93=AJ20), AF93, 0) -> 0 | BY20: =IF((Y95=AJ20), AF95, 0) -> 0 | BZ20: =IF((Y98=AJ20), AF98, 0) -> 0 | CA20: =IF((Y100=AJ20), AF100, 0) -> 0 | CB20: =IF((Y102=AJ20), AF102, 0) -> 0 | CC20: =IF((Y104=AJ20), AF104, 0) -> 0 | CD20: =IF((Y107=AJ20), AF107, 0) -> 0 | CE20: =IF((Y109=AJ20), AF109, 0) -> 0 | CF20: =IF((Y111=AJ20), AF111, 0) -> 0 | CG20: =IF((Y113=AJ20), AF113, 0) -> 0 | CH20: =IF((Y116=AJ20), AF116, 0) -> 0 | CI20: =IF((Y118=AJ20), AF118, 0) -> 0 | CJ20: =IF((Y120=AJ20), AF120, 0) -> 0 | CK20: =IF((Y122=AJ20), AF122, 0) -> 0 | CL20: =IF((Y125=AJ20), AF125, 0) -> 0 | CM20: =IF((Y127=AJ20), AF127, 0) -> 0 | CN20: =IF((Y129=AJ20), AF129, 0) -> 0 | CO20: =IF((Y131=AJ20), AF131, 0) -> 0 | CP20: =IF((Y134=AJ20), AF134, 0) -> 0 | CQ20: =IF((Y136=AJ20), AF136, 0) -> 0 | CR20: =IF((Y138=AJ20), AF138, 0) -> 0 | CS20: =IF((Y140=AJ20), AF140, 0) -> 0 | CT20: =IF((Y143=AJ20), AF143, 0) -> 0 | CU20: =IF((Y145=AJ20), AF145, 0) -> 0 | CV20: =IF((Y147=AJ20), AF147, 0) -> 0 | CW20: =IF((Y149=AJ20),AF149, 0) -> 0 | CX20: =IF((Y152=AJ20), AF152, 0) -> 0 | CY20: =IF((Y154=AJ20), AF154, 0) -> 0 | CZ20: =IF((Y156=AJ20), AF156, 0) -> 0 | DA20: =IF((Y158=AJ20), AF158, 0) -> 0 | DB20: =IF((Y161=AJ20), AF161, 0) -> 0 | DC20: =IF((Y163=AJ20), AF163, 0) -> 0 | DD20: =IF((Y165=AJ20), AF165, 0) -> 0 | DE20: =IF((Y167=AJ20), AF167, 0) -> 0 | DF20: =IF((Y170=AJ20), AF170, 0) -> 0 | DG20: =IF((Y172=AJ20), AF172, 0) -> 0 | DH20: =IF((Y174=AJ20), AF174, 0) -> 0 | DI20: =IF((Y176=AJ20), AF176, 0) -> 0 | DJ20: =IF((Y179=AJ20), AF179, 0) -> 0 | DK20: =IF((Y181=AJ20), AF181, 0) -> 0 | DL20: =IF((Y183=AJ20), AF183, 0) -> 0 | DM20: =IF((Y185=AJ20), AF185, 0) -> 0 | DN20: =IF((Y188=AJ20), AF188, 0) -> 0 | DO20: =IF((Y190=AJ20), AF190, 0) -> 0 | DP20: =IF((Y192=AJ20), AF192, 0) -> 0 | DQ20: =IF((Y194=AJ20), AF194, 0) -> 0 | DR20: =IF((Y197=AJ20), AF197, 0) -> 0 | DS20: =IF((Y199=AJ20), AF199, 0) -> 0 | DT20: =IF((Y201=AJ20), AF201, 0) -> 0 | DU20: =IF((Y203=AJ20), AF203, 0) -> 0 | DV20: =IF((Y206=AJ20), AF206, 0) -> 0 | DW20: =IF((Y208=AJ20), AF208, 0) -> 0 | DX20: =IF((Y210=AJ20), AF210, 0) -> 0 | DY20: =IF((Y212=AJ20), AF212, 0) -> 0 | DZ20: =IF((Y215=AJ20), AF215, 0) -> 0 | EA20: =IF((Y217=AJ20), AF217, 0) -> 0 | EB20: =IF((Y219=AJ20), AF219, 0) -> 0 | EC20: =IF((Y221=AJ20), AF221, 0) -> 0 | ED20: =IF((Y224=AJ20), AF224, 0) -> 0 | EE20: =IF((Y226=AJ20), AF226, 0) -> 0 | EF20: =IF((Y228=AJ20), AF228, 0) -> 0 | EG20: =IF((Y230=AJ20), AF230, 0) -> 0 | EH20: =IF((Y233=AJ20), AF233, 0) -> 0 | EI20: =IF((Y235=AJ20), AF235, 0) -> 0 | EJ20: =IF((Y237=AJ20), AF237, 0) -> 0 | EK20: =IF((Y239=AJ20), AF239, 0) -> 0 | EL20: =IF((Y242=AJ20), AF242, 0) -> 0 | EM20: =IF((Y244=AJ20), AF244, 0) -> 0 | EN20: =IF((Y246=AJ20), AF246, 0) -> 0 | EO20: =IF((Y248=AJ20), AF248, 0) -> 0 | EP20: =IF('NOME + Nº'!E62="SIM",0,IF((Y251=AJ20),AF251,0)+IF((Y252=AJ20),AF252,0)) -> 10.214824 | EQ20: =IF('NOME + Nº'!E62="SIM",0,IF((Y254=AJ20),AF254,0)+IF((Y255=AJ20),AF255,0)) -> 0 | ER20: =IF('NOME + Nº'!E62="SIM",0,IF((Y257=AJ20), AF257,0)+IF((Y258=AJ20), AF258,0)) -> 0 | ES20: =IF('NOME + Nº'!E62="SIM",0,IF((Y260=AJ20), AF260,0)+IF((Y261=AJ20), AF261,0)) -> 0 | ET20: =IF(Y263=AJ20,AF263,0) -> 0 | EU20: =SUM(AP20:ET20) -> 206.82082 | EW20: =SUM(EP20:ES20) -> 10.214824
I21: 1 | J21: =IF(N21=0," ",ENFESTO!AJ20) -> Tec. Externo | K21: =IF(N21=0," ",ENFESTO!AK20) -> Aquablock | L21: =IF(N21=0," ",ENFESTO!AL20) -> 49.9 | M21: =IF(N21=0," ",ENFESTO!AM20) -> 140 | N21: =IF(ENFESTO!AN20=0,0,ENFESTO!AN20) -> 4.1447059 | O21: =IF(ENFESTO!AO20=0,0,ENFESTO!AO20) -> 206.82082 | U21: =U19+1 -> 3 | V21: =MODELAGEM!K15 -> SIM | W21: ' ' | Y21: =MODELAGEM!M15 -> Reforço | AA21: =MODELAGEM!N15 -> 7.9 | AB21: =IF(V21="NÃO",0,((Z22*MODELAGEM!P15/(MODELAGEM!R15/MODELAGEM!L15))/100)) -> 3.44 | AC21: =AC19 -> 2.5 | AE21: =IF(V21="NÃO",0,((Z22/(MODELAGEM!R15))*(AC21*2/100)+AB21)*W22) -> 3.94 | AF21: =AE21*AA21 -> 31.126 | AI21: 2 | AJ21: ='NOME + Nº'!B36 -> Entretela | AK21: =IF('NOME + Nº'!D36=0," ",'NOME + Nº'!D36) -> 80 | AL21: ='NOME + Nº'!H36 -> 16 | AM21: ='NOME + Nº'!J36 -> 75 | AN21: =IF('NOME + Nº'!D23="NÃO",0,IF(AL21<>0,AO21/AL21,0)) -> 0 | AO21: =IF('NOME + Nº'!D23="NÃO",0,SUM(AP21:ET21)) -> 0 | AP21: =IF((Y17=AJ21), AF17, 0) -> 0 | AQ21: =IF((Y19=AJ21), AF19, 0) -> 0 | AR21: =IF((Y21=AJ21), AF21, 0) -> 0 | AS21: =IF((Y23=AJ21), AF23, 0) -> 0 | AT21: =IF((Y26=AJ21), AF26, 0) -> 0 | AU21: =IF((Y28=AJ21), AF28, 0) -> 0 | AV21: =IF((Y30=AJ21), AF30, 0) -> 0 | AW21: =IF((Y32=AJ21), AF32, 0) -> 0 | AX21: =IF((Y35=AJ21), AF35, 0) -> 0 | AY21: =IF((Y37=AJ21), AF37, 0) -> 0 | AZ21: =IF((Y39=AJ21), AF39, 0) -> 0 | BA21: =IF((Y41=AJ21), AF41, 0) -> 0 | BB21: =IF((Y44=AJ21), AF44, 0) -> 0 | BC21: =IF((Y46=AJ21), AF46, 0) -> 0 | BD21: =IF((Y48=AJ21), AF48, 0) -> 0 | BE21: =IF((Y50=AJ21), AF50, 0) -> 0 | BF21: =IF((Y53=AJ21), AF53, 0) -> 0 | BG21: =IF((Y55=AJ21), AF55, 0) -> 0 | BH21: =IF((Y57=AJ21), AF57, 0) -> 0 | BI21: =IF((Y59=AJ21), AF59, 0) -> 0 | BJ21: =IF((Y62=AJ21), AF62, 0) -> 0 | BK21: =IF((Y64=AJ21), AF64, 0) -> 0 | BL21: =IF((Y66=AJ21), AF66, 0) -> 0 | BM21: =IF((Y68=AJ21), AF68, 0) -> 0 | BN21: =IF((Y71=AJ21), AF71, 0) -> 0 | BO21: =IF((Y73=AJ21), AF73, 0) -> 0 | BP21: =IF((Y75=AJ21), AF75, 0) -> 0 | BQ21: =IF((Y77=AJ21), AF77, 0) -> 0 | BR21: =IF((Y80=AJ21), AF80, 0) -> 0 | BS21: =IF((Y82=AJ21), AF82, 0) -> 0 | BT21: =IF((Y84=AJ21), AF84, 0) -> 0 | BU21: =IF((Y86=AJ21), AF86, 0) -> 0 | BV21: =IF((Y89=AJ21), AF89, 0) -> 0 | BW21: =IF((Y91=AJ21), AF91, 0) -> 0 | BX21: =IF((Y93=AJ21), AF93, 0) -> 0 | BY21: =IF((Y95=AJ21), AF95, 0) -> 0 | BZ21: =IF((Y98=AJ21), AF98, 0) -> 0 | CA21: =IF((Y100=AJ21), AF100, 0) -> 0 | CB21: =IF((Y102=AJ21), AF102, 0) -> 0 | CC21: =IF((Y104=AJ21), AF104, 0) -> 0 | CD21: =IF((Y107=AJ21), AF107, 0) -> 0 | CE21: =IF((Y109=AJ21), AF109, 0) -> 0 | CF21: =IF((Y111=AJ21), AF111, 0) -> 0 | CG21: =IF((Y113=AJ21), AF113, 0) -> 0 | CH21: =IF((Y116=AJ21), AF116, 0) -> 0 | CI21: =IF((Y118=AJ21), AF118, 0) -> 0 | CJ21: =IF((Y120=AJ21), AF120, 0) -> 0 | CK21: =IF((Y122=AJ21), AF122, 0) -> 0 | CL21: =IF((Y125=AJ21), AF125, 0) -> 0 | CM21: =IF((Y127=AJ21), AF127, 0) -> 0 | CN21: =IF((Y129=AJ21), AF129, 0) -> 0 | CO21: =IF((Y131=AJ21), AF131, 0) -> 0 | CP21: =IF((Y134=AJ21), AF134, 0) -> 0 | CQ21: =IF((Y136=AJ21), AF136, 0) -> 0 | CR21: =IF((Y138=AJ21), AF138, 0) -> 0 | CS21: =IF((Y140=AJ21), AF140, 0) -> 0 | CT21: =IF((Y143=AJ21), AF143, 0) -> 0 | CU21: =IF((Y145=AJ21), AF145, 0) -> 0 | CV21: =IF((Y147=AJ21), AF147, 0) -> 0 | CW21: =IF((Y149=AJ21), AF149, 0) -> 0 | CX21: =IF((Y152=AJ21), AF152, 0) -> 0 | CY21: =IF((Y154=AJ21), AF154, 0) -> 0 | CZ21: =IF((Y156=AJ21), AF156, 0) -> 0 | DA21: =IF((Y158=AJ21), AF158, 0) -> 0 | DB21: =IF((Y161=AJ21), AF161, 0) -> 0 | DC21: =IF((Y163=AJ21), AF163, 0) -> 0 | DD21: =IF((Y165=AJ21), AF165, 0) -> 0 | DE21: =IF((Y167=AJ21), AF167, 0) -> 0 | DF21: =IF((Y170=AJ21), AF170, 0) -> 0 | DG21: =IF((Y172=AJ21), AF172, 0) -> 0 | DH21: =IF((Y174=AJ21), AF174, 0) -> 0 | DI21: =IF((Y176=AJ21), AF176, 0) -> 0 | DJ21: =IF((Y179=AJ21), AF179, 0) -> 0 | DK21: =IF((Y181=AJ21), AF181, 0) -> 0 | DL21: =IF((Y183=AJ21), AF183, 0) -> 0 | DM21: =IF((Y185=AJ21), AF185, 0) -> 0 | DN21: =IF((Y188=AJ21), AF188, 0) -> 0 | DO21: =IF((Y190=AJ21), AF190, 0) -> 0 | DP21: =IF((Y192=AJ21), AF192, 0) -> 0 | DQ21: =IF((Y194=AJ21), AF194, 0) -> 0 | DR21: =IF((Y197=AJ21), AF197, 0) -> 0 | DS21: =IF((Y199=AJ21), AF199, 0) -> 0 | DT21: =IF((Y201=AJ21), AF201, 0) -> 0 | DU21: =IF((Y203=AJ21), AF203, 0) -> 0 | DV21: =IF((Y206=AJ21), AF206, 0) -> 0 | DW21: =IF((Y208=AJ21), AF208, 0) -> 0 | DX21: =IF((Y210=AJ21), AF210, 0) -> 0 | DY21: =IF((Y212=AJ21), AF212, 0) -> 0 | DZ21: =IF((Y215=AJ21), AF215, 0) -> 0 | EA21: =IF((Y217=AJ21), AF217, 0) -> 0 | EB21: =IF((Y219=AJ21), AF219, 0) -> 0 | EC21: =IF((Y221=AJ21), AF221, 0) -> 0 | ED21: =IF((Y224=AJ21), AF224, 0) -> 0 | EE21: =IF((Y226=AJ21), AF226, 0) -> 0 | EF21: =IF((Y228=AJ21), AF228, 0) -> 0 | EG21: =IF((Y230=AJ21), AF230, 0) -> 0 | EH21: =IF((Y233=AJ21), AF233, 0) -> 0 | EI21: =IF((Y235=AJ21), AF235, 0) -> 0 | EJ21: =IF((Y237=AJ21), AF237, 0) -> 0 | EK21: =IF((Y239=AJ21), AF239, 0) -> 0 | EL21: =IF((Y242=AJ21), AF242, 0) -> 0 | EM21: =IF((Y244=AJ21), AF244, 0) -> 0 | EN21: =IF((Y246=AJ21), AF246, 0) -> 0 | EO21: =IF((Y248=AJ21), AF248, 0) -> 0 | EP21: =IF('NOME + Nº'!E62="SIM",0,IF((Y251=AJ21),AF251,0)+IF((Y252=AJ21),AF252,0)) -> 6.1866667 | EQ21: =IF('NOME + Nº'!E62="SIM",0,IF((Y254=AJ21),AF254,0)+IF((Y255=AJ21),AF255,0)) -> 3.8222222 | ER21: =IF('NOME + Nº'!E62="SIM",0,IF((Y257=AJ21), AF257,0)+IF((Y258=AJ21), AF258,0)) -> 0 | ES21: =IF('NOME + Nº'!E62="SIM",0,IF((Y260=AJ21), AF260,0)+IF((Y261=AJ21), AF261,0)) -> 0 | ET21: =IF(Y263=AJ21,AF263,0) -> 0 | EU21: =IF('NOME + Nº'!D23="SIM",SUM(AP21:ET21),0) -> 0 | EW21: =SUM(EP21:ES21) -> 10.008889
B22: Todas as medidas devem estar em centímetros (cm). | I22: 2 | J22: =IF(N22=0," ",ENFESTO!AJ21) | K22: =IF(N22=0," ",ENFESTO!AK21) | L22: =IF(N22=0," ",ENFESTO!AL21) | M22: =IF(N22=0," ",ENFESTO!AM21) | N22: =IF(ENFESTO!AN21=0,0,ENFESTO!AN21) -> 0 | O22: =IF(ENFESTO!AO21=0,0,ENFESTO!AO21) -> 0 | W22: =IF(V21="SIM","1","0") -> 1 | Z22: =Z20 -> 20 | AI22: 3 | AJ22: ='NOME + Nº'!B37 -> Forro | AK22: =IF('NOME + Nº'!D37=0," ",'NOME + Nº'!D37) -> Suede | AL22: ='NOME + Nº'!H37 -> 19.9 | AM22: ='NOME + Nº'!J37 -> 140 | AN22: =IF('NOME + Nº'!D24="NÃO",0,IF(AL22<>0,AO22/AL22,0)) -> 0 | AO22: =IF('NOME + Nº'!D24="NÃO",0,SUM(AP22:ET22)) -> 0 | AP22: =IF((Y17=AJ22), AF17, 0) -> 0 | AQ22: =IF((Y19=AJ22), AF19, 0) -> 0 | AR22: =IF((Y21=AJ22), AF21, 0) -> 0 | AS22: =IF((Y23=AJ22), AF23, 0) -> 0 | AT22: =IF((Y26=AJ22), AF26, 0) -> 0 | AU22: =IF((Y28=AJ22), AF28, 0) -> 0 | AV22: =IF((Y30=AJ22), AF30, 0) -> 0 | AW22: =IF((Y32=AJ22), AF32, 0) -> 0 | AX22: =IF((Y35=AJ22), AF35, 0) -> 0 | AY22: =IF((Y37=AJ22), AF37, 0) -> 0 | AZ22: =IF((Y39=AJ22), AF39, 0) -> 0 | BA22: =IF((Y41=AJ22), AF41, 0) -> 0 | BB22: =IF((Y44=AJ22), AF44, 0) -> 0 | BC22: =IF((Y46=AJ22), AF46, 0) -> 0 | BD22: =IF((Y48=AJ22), AF48, 0) -> 0 | BE22: =IF((Y50=AJ22), AF50, 0) -> 0 | BF22: =IF((Y53=AJ22), AF53, 0) -> 0 | BG22: =IF((Y55=AJ22), AF55, 0) -> 0 | BH22: =IF((Y57=AJ22), AF57, 0) -> 0 | BI22: =IF((Y59=AJ22), AF59, 0) -> 0 | BJ22: =IF((Y62=AJ22), AF62, 0) -> 0 | BK22: =IF((Y64=AJ22), AF64, 0) -> 0 | BL22: =IF((Y66=AJ22), AF66, 0) -> 0 | BM22: =IF((Y68=AJ22), AF68, 0) -> 0 | BN22: =IF((Y71=AJ22), AF71,0) -> 0 | BO22: =IF((Y73=AJ22), AF73, 0) -> 0 | BP22: =IF((Y75=AJ22), AF75, 0) -> 0 | BQ22: =IF((Y77=AJ22), AF77, 0) -> 0 | BR22: =IF((Y80=AJ22), AF80, 0) -> 0 | BS22: =IF((Y82=AJ22), AF82, 0) -> 0 | BT22: =IF((Y84=AJ22), AF84, 0) -> 0 | BU22: =IF((Y86=AJ22), AF86, 0) -> 0 | BV22: =IF((Y89=AJ22), AF89, 0) -> 0 | BW22: =IF((Y91=AJ22), AF91, 0) -> 0 | BX22: =IF((Y93=AJ22), AF93, 0) -> 0 | BY22: =IF((Y95=AJ22), AF95, 0) -> 0 | BZ22: =IF((Y98=AJ22), AF98, 0) -> 0 | CA22: =IF((Y100=AJ22), AF100, 0) -> 0 | CB22: =IF((Y102=AJ22), AF102, 0) -> 0 | CC22: =IF((Y104=AJ22), AF104, 0) -> 0 | CD22: =IF((Y107=AJ22), AF107, 0) -> 0 | CE22: =IF((Y109=AJ22), AF109, 0) -> 0 | CF22: =IF((Y111=AJ22), AF111, 0) -> 0 | CG22: =IF((Y113=AJ22), AF113, 0) -> 0 | CH22: =IF((Y116=AJ22), AF116, 0) -> 0 | CI22: =IF((Y118=AJ22), AF118, 0) -> 0 | CJ22: =IF((Y120=AJ22), AF120, 0) -> 0 | CK22: =IF((Y122=AJ22), AF122, 0) -> 0 | CL22: =IF((Y125=AJ22), AF125, 0) -> 0 | CM22: =IF((Y127=AJ22), AF127, 0) -> 0 | CN22: =IF((Y129=AJ22), AF129, 0) -> 0 | CO22: =IF((Y131=AJ22), AF131, 0) -> 0 | CP22: =IF((Y134=AJ22), AF134, 0) -> 0 | CQ22: =IF((Y136=AJ22), AF136, 0) -> 0 | CR22: =IF((Y138=AJ22), AF138, 0) -> 0 | CS22: =IF((Y140=AJ22), AF140, 0) -> 0 | CT22: =IF((Y143=AJ22), AF143, 0) -> 0 | CU22: =IF((Y145=AJ22), AF145, 0) -> 0 | CV22: =IF((Y147=AJ22), AF147, 0) -> 0 | CW22: =IF((Y149=AJ22), AF149, 0) -> 0 | CX22: =IF((Y152=AJ22), AF152, 0) -> 0 | CY22: =IF((Y154=AJ22), AF154, 0) -> 0 | CZ22: =IF((Y156=AJ22), AF156, 0) -> 0 | DA22: =IF((Y158=AJ22), AF158, 0) -> 0 | DB22: =IF((Y161=AJ22), AF161, 0) -> 0 | DC22: =IF((Y163=AJ22), AF163, 0) -> 0 | DD22: =IF((Y165=AJ22), AF165, 0) -> 0 | DE22: =IF((Y167=AJ22), AF167, 0) -> 0 | DF22: =IF((Y170=AJ22), AF170, 0) -> 0 | DG22: =IF((Y172=AJ22), AF172, 0) -> 0 | DH22: =IF((Y174=AJ22), AF174, 0) -> 0 | DI22: =IF((Y176=AJ22), AF176, 0) -> 0 | DJ22: =IF((Y179=AJ22), AF179, 0) -> 0 | DK22: =IF((Y181=AJ22), AF181, 0) -> 0 | DL22: =IF((Y183=AJ22), AF183, 0) -> 0 | DM22: =IF((Y185=AJ22), AF185, 0) -> 0 | DN22: =IF((Y188=AJ22), AF188, 0) -> 0 | DO22: =IF((Y190=AJ22), AF190, 0) -> 0 | DP22: =IF((Y192=AJ22), AF192, 0) -> 0 | DQ22: =IF((Y194=AJ22), AF194, 0) -> 0 | DR22: =IF((Y197=AJ22), AF197, 0) -> 0 | DS22: =IF((Y199=AJ22), AF199, 0) -> 0 | DT22: =IF((Y201=AJ22), AF201, 0) -> 0 | DU22: =IF((Y203=AJ22), AF203, 0) -> 0 | DV22: =IF((Y206=AJ22), AF206, 0) -> 0 | DW22: =IF((Y208=AJ22), AF208, 0) -> 0 | DX22: =IF((Y210=AJ22), AF210, 0) -> 0 | DY22: =IF((Y212=AJ22), AF212, 0) -> 0 | DZ22: =IF((Y215=AJ22), AF215, 0) -> 0 | EA22: =IF((Y217=AJ22), AF217, 0) -> 0 | EB22: =IF((Y219=AJ22), AF219, 0) -> 0 | EC22: =IF((Y221=AJ22), AF221, 0) -> 0 | ED22: =IF((Y224=AJ22), AF224, 0) -> 0 | EE22: =IF((Y226=AJ22), AF226, 0) -> 0 | EF22: =IF((Y228=AJ22), AF228, 0) -> 0 | EG22: =IF((Y230=AJ22), AF230, 0) -> 0 | EH22: =IF((Y233=AJ22), AF233, 0) -> 0 | EI22: =IF((Y235=AJ22), AF235, 0) -> 0 | EJ22: =IF((Y237=AJ22), AF237, 0) -> 0 | EK22: =IF((Y239=AJ22), AF239, 0) -> 0 | EL22: =IF((Y242=AJ22), AF242, 0) -> 0 | EM22: =IF((Y244=AJ22), AF244, 0) -> 0 | EN22: =IF((Y246=AJ22), AF246, 0) -> 0 | EO22: =IF((Y248=AJ22), AF248, 0) -> 0 | EP22: =IF('NOME + Nº'!E62="SIM",0,IF((Y251=AJ22),AF251,0)+IF((Y252=AJ22),AF252,0)) -> 0 | EQ22: =IF('NOME + Nº'!E62="SIM",0,IF((Y254=AJ22),AF254,0)+IF((Y255=AJ22),AF255,0)) -> 0 | ER22: =IF('NOME + Nº'!E62="SIM",0,IF((Y257=AJ22), AF257,0)+IF((Y258=AJ22), AF258,0)) -> 0 | ES22: =IF('NOME + Nº'!E62="SIM",0,IF((Y260=AJ22), AF260,0)+IF((Y261=AJ22), AF261,0)) -> 0 | ET22: =IF(Y263=AJ22,AF263,0) -> 0 | EU22: =IF('NOME + Nº'!D24="SIM",SUM(AP22:ET22),0) -> 0 | EW22: =SUM(EP22:ES22) -> 0
I23: 3 | J23: =IF(N23=0," ",ENFESTO!AJ22) | K23: =IF(N23=0," ",ENFESTO!AK22) | L23: =IF(N23=0," ",ENFESTO!AL22) | M23: =IF(N23=0," ",ENFESTO!AM22) | N23: =IF(ENFESTO!AN22=0,0,ENFESTO!AN22) -> 0 | O23: =IF(ENFESTO!AO22=0,0,ENFESTO!AO22) -> 0 | U23: =U21+1 -> 4 | V23: =MODELAGEM!K17 -> NÃO | W23: ' ' | Y23: =MODELAGEM!M17 -> Reforço | AA23: =MODELAGEM!N17 -> 7.9 | AB23: =IF(V23="NÃO",0,((Z24*MODELAGEM!P17/(MODELAGEM!R17/MODELAGEM!L17))/100)) -> 0 | AC23: =AC21 -> 2.5 | AE23: =IF(V23="NÃO",0,((Z24/(MODELAGEM!R17))*(AC23*2/100)+AB23)*W24) -> 0 | AF23: =AE23*AA23 -> 0 | AI23: 4 | AJ23: ='NOME + Nº'!B38 -> Couro | AK23: =IF('NOME + Nº'!D38=0," ",'NOME + Nº'!D38) -> Couro Legítimo Fly | AL23: ='NOME + Nº'!H38 -> 74.9 | AM23: ='NOME + Nº'!J38 -> 100 | AN23: =IF('NOME + Nº'!D25="NÃO",0,IF(AL23<>0,AO23/AL23,0)) -> 0 | AO23: =IF('NOME + Nº'!D25="NÃO",0,SUM(AP23:ET23)) -> 0 | AP23: =IF((Y17=AJ23), AF17, 0) -> 0 | AQ23: =IF((Y19=AJ23), AF19, 0) -> 0 | AR23: =IF((Y21=AJ23), AF21, 0) -> 0 | AS23: =IF((Y23=AJ23), AF23, 0) -> 0 | AT23: =IF((Y26=AJ23), AF26, 0) -> 0 | AU23: =IF((Y28=AJ23), AF28, 0) -> 0 | AV23: =IF((Y30=AJ23), AF30, 0) -> 0 | AW23: =IF((Y32=AJ23), AF32, 0) -> 0 | AX23: =IF((Y35=AJ23), AF35, 0) -> 0 | AY23: =IF((Y37=AJ23), AF37, 0) -> 0 | AZ23: =IF((Y39=AJ23), AF39, 0) -> 0 | BA23: =IF((Y41=AJ23), AF41, 0) -> 0 | BB23: =IF((Y44=AJ23), AF44, 0) -> 0 | BC23: =IF((Y46=AJ23), AF46, 0) -> 0 | BD23: =IF((Y48=AJ23), AF48, 0) -> 0 | BE23: =IF((Y50=AJ23), AF50, 0) -> 0 | BF23: =IF((Y53=AJ23), AF53, 0) -> 0 | BG23: =IF((Y55=AJ23), AF55, 0) -> 0 | BH23: =IF((Y57=AJ23), AF57, 0) -> 0 | BI23: =IF((Y59=AJ23), AF59, 0) -> 0 | BJ23: =IF((Y62=AJ23), AF62, 0) -> 0 | BK23: =IF((Y64=AJ23), AF64, 0) -> 0 | BL23: =IF((Y66=AJ23), AF66, 0) -> 0 | BM23: =IF((Y68=AJ23), AF68, 0) -> 0 | BN23: =IF((Y71=AJ23), AF71, 0) -> 0 | BO23: =IF((Y73=AJ23), AF73, 0) -> 0 | BP23: =IF((Y75=AJ23), AF75, 0) -> 0 | BQ23: =IF((Y77=AJ23), AF77, 0) -> 0 | BR23: =IF((Y80=AJ23), AF80, 0) -> 0 | BS23: =IF((Y82=AJ23), AF82, 0) -> 0 | BT23: =IF((Y84=AJ23), AF84, 0) -> 0 | BU23: =IF((Y86=AJ23), AF86, 0) -> 0 | BV23: =IF((Y89=AJ23), AF89, 0) -> 0 | BW23: =IF((Y91=AJ23), AF91, 0) -> 0 | BX23: =IF((Y93=AJ23), AF93, 0) -> 0 | BY23: =IF((Y95=AJ23), AF95, 0) -> 0 | BZ23: =IF((Y98=AJ23), AF98, 0) -> 0 | CA23: =IF((Y100=AJ23), AF100, 0) -> 0 | CB23: =IF((Y102=AJ23), AF102, 0) -> 0 | CC23: =IF((Y104=AJ23), AF104, 0) -> 0 | CD23: =IF((Y107=AJ23), AF107, 0) -> 0 | CE23: =IF((Y109=AJ23), AF109, 0) -> 0 | CF23: =IF((Y111=AJ23), AF111, 0) -> 0 | CG23: =IF((Y113=AJ23), AF113, 0) -> 0 | CH23: =IF((Y116=AJ23), AF116, 0) -> 0 | CI23: =IF((Y118=AJ23), AF118, 0) -> 0 | CJ23: =IF((Y120=AJ23), AF120, 0) -> 0 | CK23: =IF((Y122=AJ23), AF122, 0) -> 0 | CL23: =IF((Y125=AJ23), AF125, 0) -> 0 | CM23: =IF((Y127=AJ23), AF127, 0) -> 0 | CN23: =IF((Y129=AJ23), AF129, 0) -> 0 | CO23: =IF((Y131=AJ23), AF131, 0) -> 0 | CP23: =IF((Y134=AJ23), AF134, 0) -> 0 | CQ23: =IF((Y136=AJ23), AF136, 0) -> 0 | CR23: =IF((Y138=AJ23), AF138, 0) -> 0 | CS23: =IF((Y140=AJ23), AF140, 0) -> 0 | CT23: =IF((Y143=AJ23), AF143, 0) -> 0 | CU23: =IF((Y145=AJ23), AF145, 0) -> 0 | CV23: =IF((Y147=AJ23), AF147, 0) -> 0 | CW23: =IF((Y149=AJ23), AF149, 0) -> 0 | CX23: =IF((Y152=AJ23), AF152, 0) -> 0 | CY23: =IF((Y154=AJ23), AF154, 0) -> 0 | CZ23: =IF((Y156=AJ23), AF156, 0) -> 0 | DA23: =IF((Y158=AJ23), AF158, 0) -> 0 | DB23: =IF((Y161=AJ23), AF161, 0) -> 0 | DC23: =IF((Y163=AJ23), AF163, 0) -> 0 | DD23: =IF((Y165=AJ23), AF165, 0) -> 0 | DE23: =IF((Y167=AJ23), AF167, 0) -> 0 | DF23: =IF((Y170=AJ23), AF170, 0) -> 0 | DG23: =IF((Y172=AJ23), AF172, 0) -> 0 | DH23: =IF((Y174=AJ23), AF174, 0) -> 0 | DI23: =IF((Y176=AJ23), AF176, 0) -> 0 | DJ23: =IF((Y179=AJ23), AF179, 0) -> 0 | DK23: =IF((Y181=AJ23), AF181, 0) -> 0 | DL23: =IF((Y183=AJ23), AF183, 0) -> 0 | DM23: =IF((Y185=AJ23), AF185, 0) -> 0 | DN23: =IF((Y188=AJ23), AF188, 0) -> 0 | DO23: =IF((Y190=AJ23), AF190, 0) -> 0 | DP23: =IF((Y192=AJ23), AF192, 0) -> 0 | DQ23: =IF((Y194=AJ23), AF194, 0) -> 0 | DR23: =IF((Y197=AJ23), AF197, 0) -> 0 | DS23: =IF((Y199=AJ23), AF199, 0) -> 0 | DT23: =IF((Y201=AJ23), AF201, 0) -> 0 | DU23: =IF((Y203=AJ23), AF203, 0) -> 0 | DV23: =IF((Y206=AJ23), AF206, 0) -> 0 | DW23: =IF((Y208=AJ23), AF208, 0) -> 0 | DX23: =IF((Y210=AJ23), AF210, 0) -> 0 | DY23: =IF((Y212=AJ23), AF212, 0) -> 0 | DZ23: =IF((Y215=AJ23), AF215, 0) -> 0 | EA23: =IF((Y217=AJ23), AF217, 0) -> 0 | EB23: =IF((Y219=AJ23), AF219, 0) -> 0 | EC23: =IF((Y221=AJ23), AF221, 0) -> 0 | ED23: =IF((Y224=AJ23), AF224, 0) -> 0 | EE23: =IF((Y226=AJ23), AF226, 0) -> 0 | EF23: =IF((Y228=AJ23), AF228, 0) -> 0 | EG23: =IF((Y230=AJ23), AF230, 0) -> 0 | EH23: =IF((Y233=AJ23), AF233, 0) -> 0 | EI23: =IF((Y235=AJ23), AF235, 0) -> 0 | EJ23: =IF((Y237=AJ23), AF237, 0) -> 0 | EK23: =IF((Y239=AJ23), AF239, 0) -> 0 | EL23: =IF((Y242=AJ23), AF242, 0) -> 0 | EM23: =IF((Y244=AJ23), AF244, 0) -> 0 | EN23: =IF((Y246=AJ23), AF246, 0) -> 0 | EO23: =IF((Y248=AJ23), AF248, 0) -> 0 | EP23: =IF('NOME + Nº'!E62="SIM",0,IF((Y251=AJ23),AF251,0)+IF((Y252=AJ23),AF252,0)) -> 0 | EQ23: =IF('NOME + Nº'!E62="SIM",0,IF((Y254=AJ23),AF254,0)+IF((Y255=AJ23),AF255,0)) -> 0 | ER23: =IF('NOME + Nº'!E62="SIM",0,IF((Y257=AJ23), AF257,0)+IF((Y258=AJ23), AF258,0)) -> 0 | ES23: =IF('NOME + Nº'!E62="SIM",0,IF((Y260=AJ23), AF263,0)+IF((Y261=AJ23), AF261,0)) -> 0 | ET23: =IF(Y263=AJ23,AF263,0) -> 0 | EU23: =IF('NOME + Nº'!D25="SIM",SUM(AP23:ET23),0) -> 0 | EW23: =SUM(EP23:ES23) -> 0
I24: 4 | J24: =IF(N24=0," ",ENFESTO!AJ23) | K24: =IF(N24=0," ",ENFESTO!AK23) | L24: =IF(N24=0," ",ENFESTO!AL23) | M24: =IF(N24=0," ",ENFESTO!AM23) | N24: =IF(ENFESTO!AN23=0,0,ENFESTO!AN23) -> 0 | O24: =IF(ENFESTO!AO23=0,0,ENFESTO!AO23) -> 0 | W24: =IF(V23="SIM","1","0") -> 0 | Z24: =Z22 -> 20 | AI24: 5 | AJ24: ='NOME + Nº'!B39 -> Tec. Vivo | AK24: =IF('NOME + Nº'!D39=0," ",'NOME + Nº'!D39) -> Aquablock | AL24: ='NOME + Nº'!H39 -> 49.9 | AM24: ='NOME + Nº'!J39 -> 140 | AN24: =IF('NOME + Nº'!D26="NÃO",0,IF(AL24<>0,AO24/AL24,0)) -> 0 | AO24: =IF('NOME + Nº'!D26="NÃO",0,SUM(AP24:ET24)) -> 0 | AP24: =IF((Y17=AJ24), AF17, 0) -> 0 | AQ24: =IF((Y19=AJ24), AF19, 0) -> 0 | AR24: =IF((Y21=AJ24), AF21, 0) -> 0 | AS24: =IF((Y23=AJ24), AF23, 0) -> 0 | AT24: =IF((Y26=AJ24), AF26, 0) -> 0 | AU24: =IF((Y28=AJ24), AF28, 0) -> 0 | AV24: =IF((Y30=AJ24), AF30, 0) -> 0 | AW24: =IF((Y32=AJ24), AF32, 0) -> 0 | AX24: =IF((Y35=AJ24), AF35, 0) -> 0 | AY24: =IF((Y37=AJ24), AF37, 0) -> 0 | AZ24: =IF((Y39=AJ24), AF39, 0) -> 0 | BA24: =IF((Y41=AJ24), AF41, 0) -> 0 | BB24: =IF((Y44=AJ24), AF44, 0) -> 0 | BC24: =IF((Y46=AJ24), AF46, 0) -> 0 | BD24: =IF((Y48=AJ24), AF48, 0) -> 0 | BE24: =IF((Y50=AJ24), AF50, 0) -> 0 | BF24: =IF((Y53=AJ24), AF53, 0) -> 0 | BG24: =IF((Y55=AJ24), AF55, 0) -> 0 | BH24: =IF((Y57=AJ24), AF57, 0) -> 0 | BI24: =IF((Y59=AJ24), AF59, 0) -> 0 | BJ24: =IF((Y62=AJ24), AF62, 0) -> 0 | BK24: =IF((Y64=AJ24), AF64, 0) -> 0 | BL24: =IF((Y66=AJ24), AF66, 0) -> 0 | BM24: =IF((Y68=AJ24), AF68, 0) -> 0 | BN24: =IF((Y71=AJ24), AF71, 0) -> 0 | BO24: =IF((Y73=AJ24), AF73, 0) -> 0 | BP24: =IF((Y75=AJ24), AF75, 0) -> 0 | BQ24: =IF((Y77=AJ24), AF77, 0) -> 0 | BR24: =IF((Y80=AJ24), AF80, 0) -> 0 | BS24: =IF((Y82=AJ24), AF82, 0) -> 0 | BT24: =IF((Y84=AJ24), AF84, 0) -> 0 | BU24: =IF((Y86=AJ24), AF86, 0) -> 0 | BV24: =IF((Y89=AJ24), AF89, 0) -> 0 | BW24: =IF((Y91=AJ24), AF91, 0) -> 0 | BX24: =IF((Y93=AJ24), AF93, 0) -> 0 | BY24: =IF((Y95=AJ24), AF95, 0) -> 0 | BZ24: =IF((Y98=AJ24), AF98, 0) -> 0 | CA24: =IF((Y100=AJ24), AF100, 0) -> 0 | CB24: =IF((Y102=AJ24), AF102, 0) -> 0 | CC24: =IF((Y104=AJ24), AF104, 0) -> 0 | CD24: =IF((Y107=AJ24), AF107, 0) -> 0 | CE24: =IF((Y109=AJ24), AF109, 0) -> 0 | CF24: =IF((Y111=AJ24), AF111, 0) -> 0 | CG24: =IF((Y113=AJ24), AF113, 0) -> 0 | CH24: =IF((Y116=AJ24), AF116, 0) -> 0 | CI24: =IF((Y118=AJ24), AF118, 0) -> 0 | CJ24: =IF((Y120=AJ24), AF120, 0) -> 0 | CK24: =IF((Y122=AJ24), AF122, 0) -> 0 | CL24: =IF((Y125=AJ24), AF125, 0) -> 0 | CM24: =IF((Y127=AJ24), AF127, 0) -> 0 | CN24: =IF((Y129=AJ24), AF129, 0) -> 0 | CO24: =IF((Y131=AJ24), AF131, 0) -> 0 | CP24: =IF((Y134=AJ24), AF134, 0) -> 0 | CQ24: =IF((Y136=AJ24), AF136, 0) -> 0 | CR24: =IF((Y138=AJ24), AF138, 0) -> 0 | CS24: =IF((Y140=AJ24), AF140, 0) -> 0 | CT24: =IF((Y143=AJ24), AF143, 0) -> 0 | CU24: =IF((Y145=AJ24), AF145, 0) -> 0 | CV24: =IF((Y147=AJ24), AF147, 0) -> 0 | CW24: =IF((Y149=AJ24), AF149, 0) -> 0 | CX24: =IF((Y152=AJ24), AF152, 0) -> 0 | CY24: =IF((Y154=AJ24), AF154, 0) -> 0 | CZ24: =IF((Y156=AJ24), AF156, 0) -> 0 | DA24: =IF((Y158=AJ24), AF158, 0) -> 0 | DB24: =IF((Y161=AJ24), AF161, 0) -> 0 | DC24: =IF((Y163=AJ24), AF163, 0) -> 0 | DD24: =IF((Y165=AJ24), AF165, 0) -> 0 | DE24: =IF((Y167=AJ24), AF167, 0) -> 0 | DF24: =IF((Y170=AJ24), AF170, 0) -> 0 | DG24: =IF((Y172=AJ24), AF172, 0) -> 0 | DH24: =IF((Y174=AJ24), AF174, 0) -> 0 | DI24: =IF((Y176=AJ24), AF176, 0) -> 0 | DJ24: =IF((Y179=AJ24), AF179, 0) -> 0 | DK24: =IF((Y181=AJ24), AF181, 0) -> 0 | DL24: =IF((Y183=AJ24), AF183, 0) -> 0 | DM24: =IF((Y185=AJ24), AF185, 0) -> 0 | DN24: =IF((Y188=AJ24), AF188, 0) -> 0 | DO24: =IF((Y190=AJ24), AF190, 0) -> 0 | DP24: =IF((Y192=AJ24), AF192, 0) -> 0 | DQ24: =IF((Y194=AJ24), AF194, 0) -> 0 | DR24: =IF((Y197=AJ24), AF197, 0) -> 0 | DS24: =IF((Y199=AJ24), AF199, 0) -> 0 | DT24: =IF((Y201=AJ24), AF201, 0) -> 0 | DU24: =IF((Y203=AJ24), AF203, 0) -> 0 | DV24: =IF((Y206=AJ24), AF206, 0) -> 0 | DW24: =IF((Y208=AJ24), AF208, 0) -> 0 | DX24: =IF((Y210=AJ24), AF210, 0) -> 0 | DY24: =IF((Y212=AJ24), AF212, 0) -> 0 | DZ24: =IF((Y215=AJ24), AF215, 0) -> 0 | EA24: =IF((Y217=AJ24), AF217, 0) -> 0 | EB24: =IF((Y219=AJ24), AF219, 0) -> 0 | EC24: =IF((Y221=AJ24), AF221, 0) -> 0 | ED24: =IF((Y224=AJ24), AF224, 0) -> 0 | EE24: =IF((Y226=AJ24), AF226, 0) -> 0 | EF24: =IF((Y228=AJ24), AF228, 0) -> 0 | EG24: =IF((Y230=AJ24), AF230, 0) -> 0 | EH24: =IF((Y233=AJ24), AF233, 0) -> 0 | EI24: =IF((Y235=AJ24), AF235, 0) -> 0 | EJ24: =IF((Y237=AJ24), AF237, 0) -> 0 | EK24: =IF((Y239=AJ24), AF239, 0) -> 0 | EL24: =IF((Y242=AJ24), AF242, 0) -> 0 | EM24: =IF((Y244=AJ24), AF244, 0) -> 0 | EN24: =IF((Y246=AJ24), AF246, 0) -> 0 | EO24: =IF((Y248=AJ24), AF248, 0) -> 0 | EP24: =IF('NOME + Nº'!E62="SIM",0,IF((Y251=AJ24),AF251,0)+IF((Y252=AJ24),AF252,0)) -> 0 | EQ24: =IF('NOME + Nº'!E62="SIM",0,IF((Y254=AJ24),AF254,0)+IF((Y255=AJ24),AF255,0)) -> 0 | ER24: =IF('NOME + Nº'!E62="SIM",0,IF((Y257=AJ24), AF257,0)+IF((Y258=AJ24), AF258,0)) -> 0 | ES24: =IF('NOME + Nº'!E62="SIM",0,IF((Y260=AJ24), AF260,0)+IF((Y261=AJ24), AF261,0)) -> 0 | ET24: =IF(Y263=AJ24,AF263,0) -> 0 | EU24: =IF('NOME + Nº'!D26="SIM",SUM(AP24:ET24),0) -> 0 | EW24: =SUM(EP24:ES24) -> 0
I25: 5 | J25: =IF(N25=0," ",ENFESTO!AJ24) | K25: =IF(N25=0," ",ENFESTO!AK24) | L25: =IF(N25=0," ",ENFESTO!AL24) | M25: =IF(N25=0," ",ENFESTO!AM24) | N25: =IF(ENFESTO!AN24=0,0,ENFESTO!AN24) -> 0 | O25: =IF(ENFESTO!AO24=0,0,ENFESTO!AO24) -> 0 | AI25: 6 | AJ25: ='NOME + Nº'!B40 -> Estrutura | AK25: =IF('NOME + Nº'!D40=0," ",'NOME + Nº'!D40) -> Placa Plástica | AL25: ='NOME + Nº'!H40 -> 20.12 | AM25: ='NOME + Nº'!J40 -> 28 | AN25: =IF('NOME + Nº'!D27="NÃO",0,IF(AL25<>0,AO25/AL25,0)) -> 0 | AO25: =IF('NOME + Nº'!D27="NÃO",0,SUM(AP25:ET25)) -> 0 | AP25: =IF((Y17=AJ25), AF17, 0) -> 0 | AQ25: =IF((Y19=AJ25), AF19, 0) -> 0 | AR25: =IF((Y21=AJ25), AF21, 0) -> 0 | AS25: =IF((Y23=AJ25), AF23, 0) -> 0 | AT25: =IF((Y26=AJ25), AF26, 0) -> 0 | AU25: =IF((Y28=AJ25), AF28, 0) -> 0 | AV25: =IF((Y30=AJ25), AF30, 0) -> 0 | AW25: =IF((Y32=AJ25), AF32, 0) -> 0 | AX25: =IF((Y35=AJ25), AF35, 0) -> 0 | AY25: =IF((Y37=AJ25), AF37, 0) -> 0 | AZ25: =IF((Y39=AJ25), AF39, 0) -> 0 | BA25: =IF((Y41=AJ25), AF41, 0) -> 0 | BB25: =IF((Y44=AJ25), AF44, 0) -> 0 | BC25: =IF((Y46=AJ25), AF46, 0) -> 0 | BD25: =IF((Y48=AJ25), AF48, 0) -> 0 | BE25: =IF((Y50=AJ25), AF50, 0) -> 0 | BF25: =IF((Y53=AJ25), AF53, 0) -> 0 | BG25: =IF((Y55=AJ25), AF55, 0) -> 0 | BH25: =IF((Y57=AJ25), AF57, 0) -> 0 | BI25: =IF((Y59=AJ25), AF59, 0) -> 0 | BJ25: =IF((Y62=AJ25), AF62, 0) -> 0 | BK25: =IF((Y64=AJ25), AF64, 0) -> 0 | BL25: =IF((Y66=AJ25), AF66, 0) -> 0 | BM25: =IF((Y68=AJ25), AF68, 0) -> 0 | BN25: =IF((Y71=AJ25), AF71, 0) -> 0 | BO25: =IF((Y73=AJ25), AF73, 0) -> 0 | BP25: =IF((Y75=AJ25), AF75, 0) -> 0 | BQ25: =IF((Y77=AJ25), AF77, 0) -> 0 | BR25: =IF((Y80=AJ25), AF80, 0) -> 0 | BS25: =IF((Y82=AJ25), AF82, 0) -> 0 | BT25: =IF((Y84=AJ25), AF84, 0) -> 0 | BU25: =IF((Y86=AJ25), AF86, 0) -> 0 | BV25: =IF((Y89=AJ25), AF89, 0) -> 0 | BW25: =IF((Y91=AJ25), AF91, 0) -> 0 | BX25: =IF((Y93=AJ25), AF93, 0) -> 0 | BY25: =IF((Y95=AJ25), AF95, 0) -> 0 | BZ25: =IF((Y98=AJ25), AF98, 0) -> 0 | CA25: =IF((Y100=AJ25), AF100, 0) -> 0 | CB25: =IF((Y102=AJ25), AF102, 0) -> 0 | CC25: =IF((Y104=AJ25), AF104, 0) -> 0 | CD25: =IF((Y107=AJ25), AF107, 0) -> 0 | CE25: =IF((Y109=AJ25), AF109, 0) -> 0 | CF25: =IF((Y111=AJ25), AF111, 0) -> 0 | CG25: =IF((Y113=AJ25), AF113, 0) -> 0 | CH25: =IF((Y116=AJ25), AF116, 0) -> 0 | CI25: =IF((Y118=AJ25), AF118, 0) -> 0 | CJ25: =IF((Y120=AJ25), AF120, 0) -> 0 | CK25: =IF((Y122=AJ25), AF122, 0) -> 0 | CL25: =IF((Y125=AJ25), AF125, 0) -> 0 | CM25: =IF((Y127=AJ25), AF127, 0) -> 0 | CN25: =IF((Y129=AJ25), AF129, 0) -> 0 | CO25: =IF((Y131=AJ25), AF131, 0) -> 0 | CP25: =IF((Y134=AJ25),AF134, 0) -> 0 | CQ25: =IF((Y136=AJ25), AF136, 0) -> 0 | CR25: =IF((Y138=AJ25), AF138, 0) -> 0 | CS25: =IF((Y140=AJ25), AF140, 0) -> 0 | CT25: =IF((Y143=AJ25), AF143, 0) -> 0 | CU25: =IF((Y145=AJ25), AF145, 0) -> 0 | CV25: =IF((Y147=AJ25), AF147, 0) -> 0 | CW25: =IF((Y149=AJ25), AF149, 0) -> 0 | CX25: =IF((Y152=AJ25), AF152, 0) -> 0 | CY25: =IF((Y154=AJ25), AF154, 0) -> 0 | CZ25: =IF((Y156=AJ25), AF156, 0) -> 0 | DA25: =IF((Y158=AJ25), AF158, 0) -> 0 | DB25: =IF((Y161=AJ25), AF161, 0) -> 0 | DC25: =IF((Y163=AJ25), AF163, 0) -> 0 | DD25: =IF((Y165=AJ25), AF165, 0) -> 0 | DE25: =IF((Y167=AJ25), AF167, 0) -> 0 | DF25: =IF((Y170=AJ25), AF170, 0) -> 0 | DG25: =IF((Y172=AJ25), AF172, 0) -> 0 | DH25: =IF((Y174=AJ25), AF174, 0) -> 0 | DI25: =IF((Y176=AJ25), AF176, 0) -> 0 | DJ25: =IF((Y179=AJ25), AF179, 0) -> 0 | DK25: =IF((Y181=AJ25), AF181, 0) -> 0 | DL25: =IF((Y183=AJ25), AF183, 0) -> 0 | DM25: =IF((Y185=AJ25), AF185, 0) -> 0 | DN25: =IF((Y188=AJ25), AF188, 0) -> 0 | DO25: =IF((Y190=AJ25), AF190, 0) -> 0 | DP25: =IF((Y192=AJ25), AF192, 0) -> 0 | DQ25: =IF((Y194=AJ25), AF194, 0) -> 0 | DR25: =IF((Y197=AJ25), AF197, 0) -> 0 | DS25: =IF((Y199=AJ25), AF199, 0) -> 0 | DT25: =IF((Y201=AJ25), AF201, 0) -> 0 | DU25: =IF((Y203=AJ25), AF203, 0) -> 0 | DV25: =IF((Y206=AJ25), AF206, 0) -> 0 | DW25: =IF((Y208=AJ25), AF208, 0) -> 0 | DX25: =IF((Y210=AJ25), AF210, 0) -> 0 | DY25: =IF((Y212=AJ25), AF212, 0) -> 0 | DZ25: =IF((Y215=AJ25), AF215, 0) -> 0 | EA25: =IF((Y217=AJ25), AF217, 0) -> 0 | EB25: =IF((Y219=AJ25), AF219, 0) -> 0 | EC25: =IF((Y221=AJ25), AF221, 0) -> 0 | ED25: =IF((Y224=AJ25), AF224, 0) -> 0 | EE25: =IF((Y226=AJ25), AF226, 0) -> 0 | EF25: =IF((Y228=AJ25), AF228, 0) -> 0 | EG25: =IF((Y230=AJ25), AF230, 0) -> 0 | EH25: =IF((Y233=AJ25), AF233, 0) -> 0 | EI25: =IF((Y235=AJ25), AF235, 0) -> 0 | EJ25: =IF((Y237=AJ25), AF237, 0) -> 0 | EK25: =IF((Y239=AJ25), AF239, 0) -> 0 | EL25: =IF((Y242=AJ25), AF242, 0) -> 0 | EM25: =IF((Y244=AJ25), AF244, 0) -> 0 | EN25: =IF((Y246=AJ25), AF246, 0) -> 0 | EO25: =IF((Y248=AJ25), AF248, 0) -> 0 | EP25: =IF('NOME + Nº'!E62="SIM",0,IF((Y251=AJ25),AF251,0)+IF((Y252=AJ25),AF252,0)) -> 0 | EQ25: =IF('NOME + Nº'!E62="SIM",0,IF((Y254=AJ25),AF254,0)+IF((Y255=AJ25),AF255,0)) -> 0 | ER25: =IF('NOME + Nº'!E62="SIM",0,IF((Y257=AJ25), AF257,0)+IF((Y258=AJ25), AF258,0)) -> 0 | ES25: =IF('NOME + Nº'!E62="SIM",0,IF((Y260=AJ25), AF260,0)+IF((Y261=AJ25), AF261,0)) -> 0 | ET25: =IF(Y263=AJ25,AF263,0) -> 0 | EU25: =IF('NOME + Nº'!D27="SIM",SUM(AP25:ET25),0) -> 0 | EW25: =SUM(EP25:ES25) -> 0
I26: 6 | J26: =IF(N26=0," ",ENFESTO!AJ25) | K26: =IF(N26=0," ",ENFESTO!AK25) | L26: =IF(N26=0," ",ENFESTO!AL25) | M26: =IF(N26=0," ",ENFESTO!AM25) | N26: =IF(ENFESTO!AN25=0,0,ENFESTO!AN25) -> 0 | O26: =IF(ENFESTO!AO25=0,0,ENFESTO!AO25) -> 0 | T26: =MODELAGEM!H20 -> MOLDE 2 | U26: =U23+1 -> 5 | V26: =MODELAGEM!K20 -> NÃO | W26: =MODELAGEM!H21 -> NOME | Y26: =MODELAGEM!M20 -> Tec. Externo | AA26: =MODELAGEM!N20 -> 49.9 | AB26: =IF(V26="NÃO",0,((Z27*MODELAGEM!P20/(MODELAGEM!R20/MODELAGEM!L20))/100)) -> 0 | AC26: =AC23 -> 2.5 | AE26: =IF(V26="NÃO",0,((Z27/(MODELAGEM!R20))*(AC26*2/100)+AB26)*W27) -> 0 | AF26: =AE26*AA26 -> 0 | AG26: =IF(V26="SIM",1,IF(V28="SIM",1,IF(V30="SIM",1,0))) -> 0 | AI26: 7 (NOVO) | AJ26: ='NOME + Nº'!B41 -> Reforço | AK26: =IF('NOME + Nº'!D41=0," ",'NOME + Nº'!D41) -> TNT 120 | AL26: ='NOME + Nº'!H41 -> 7.9 | AM26: ='NOME + Nº'!J41 -> 140 | AN26: =IF('NOME + Nº'!D28="NÃO",0,IF(AL26<>0,AO26/AL26,0)) -> 0 | AO26: =IF('NOME + Nº'!D28="NÃO",0,SUM(AP26:ET26)) -> 0 | AP26: =IF((Y17=AJ26), AF17, 0) -> 0 | AQ26: =IF((Y19=AJ26), AF19, 0) -> 31.126 | AR26: =IF((Y21=AJ26), AF21, 0) -> 31.126 | AS26: =IF((Y23=AJ26), AF23, 0) -> 0 | AT26: =IF((Y26=AJ26), AF26, 0) -> 0 | AU26: =IF((Y28=AJ26), AF28, 0) -> 0 | AV26: =IF((Y30=AJ26), AF30, 0) -> 0 | AW26: =IF((Y32=AJ26), AF32, 0) -> 0 | AX26: =IF((Y35=AJ26), AF35, 0) -> 0 | AY26: =IF((Y37=AJ26), AF37, 0) -> 0 | AZ26: =IF((Y39=AJ26), AF39, 0) -> 0 | BA26: =IF((Y41=AJ26), AF41, 0) -> 0 | BB26: =IF((Y44=AJ26), AF44, 0) -> 0 | BC26: =IF((Y46=AJ26), AF46, 0) -> 0 | BD26: =IF((Y48=AJ26), AF48, 0) -> 0 | BE26: =IF((Y50=AJ26), AF50, 0) -> 0 | BF26: =IF((Y53=AJ26), AF53, 0) -> 0 | BG26: =IF((Y55=AJ26), AF55, 0) -> 0 | BH26: =IF((Y57=AJ26), AF57, 0) -> 0 | BI26: =IF((Y59=AJ26), AF59, 0) -> 0 | BJ26: =IF((Y62=AJ26), AF62, 0) -> 0 | BK26: =IF((Y64=AJ26), AF64, 0) -> 0 | BL26: =IF((Y66=AJ26), AF66, 0) -> 0 | BM26: =IF((Y68=AJ26), AF68, 0) -> 0 | BN26: =IF((Y71=AJ26), AF71, 0) -> 0 | BO26: =IF((Y73=AJ26), AF73, 0) -> 0 | BP26: =IF((Y75=AJ26), AF75, 0) -> 0 | BQ26: =IF((Y77=AJ26), AF77, 0) -> 0 | BR26: =IF((Y80=AJ26), AF80, 0) -> 0 | BS26: =IF((Y82=AJ26), AF82, 0) -> 0 | BT26: =IF((Y84=AJ26), AF84, 0) -> 0 | BU26: =IF((Y86=AJ26), AF86, 0) -> 0 | BV26: =IF((Y89=AJ26), AF89, 0) -> 0 | BW26: =IF((Y91=AJ26), AF91, 0) -> 0 | BX26: =IF((Y93=AJ26), AF93, 0) -> 0 | BY26: =IF((Y95=AJ26), AF95, 0) -> 0 | BZ26: =IF((Y98=AJ26), AF98, 0) -> 0 | CA26: =IF((Y100=AJ26), AF100, 0) -> 0 | CB26: =IF((Y102=AJ26), AF102, 0) -> 0 | CC26: =IF((Y104=AJ26), AF104, 0) -> 0 | CD26: =IF((Y107=AJ26), AF107, 0) -> 0 | CE26: =IF((Y109=AJ26), AF109, 0) -> 0 | CF26: =IF((Y111=AJ26), AF111, 0) -> 0 | CG26: =IF((Y113=AJ26), AF113, 0) -> 0 | CH26: =IF((Y116=AJ26), AF116, 0) -> 0 | CI26: =IF((Y118=AJ26), AF118, 0) -> 0 | CJ26: =IF((Y120=AJ26), AF120, 0) -> 0 | CK26: =IF((Y122=AJ26), AF122, 0) -> 0 | CL26: =IF((Y125=AJ26), AF125, 0) -> 0 | CM26: =IF((Y127=AJ26), AF127, 0) -> 0 | CN26: =IF((Y129=AJ26), AF129, 0) -> 0 | CO26: =IF((Y131=AJ26), AF131, 0) -> 0 | CP26: =IF((Y134=AJ26),AF134, 0) -> 0 | CQ26: =IF((Y136=AJ26), AF136, 0) -> 0 | CR26: =IF((Y138=AJ26), AF138, 0) -> 0 | CS26: =IF((Y140=AJ26), AF140, 0) -> 0 | CT26: =IF((Y143=AJ26), AF143, 0) -> 0 | CU26: =IF((Y145=AJ26), AF145, 0) -> 0 | CV26: =IF((Y147=AJ26), AF147, 0) -> 0 | CW26: =IF((Y149=AJ26), AF149, 0) -> 0 | CX26: =IF((Y152=AJ26), AF152, 0) -> 0 | CY26: =IF((Y154=AJ26), AF154, 0) -> 0 | CZ26: =IF((Y156=AJ26), AF156, 0) -> 0 | DA26: =IF((Y158=AJ26), AF158, 0) -> 0 | DB26: =IF((Y161=AJ26), AF161, 0) -> 0 | DC26: =IF((Y163=AJ26), AF163, 0) -> 0 | DD26: =IF((Y165=AJ26), AF165, 0) -> 0 | DE26: =IF((Y167=AJ26), AF167, 0) -> 0 | DF26: =IF((Y170=AJ26), AF170, 0) -> 0 | DG26: =IF((Y172=AJ26), AF172, 0) -> 0 | DH26: =IF((Y174=AJ26), AF174, 0) -> 0 | DI26: =IF((Y176=AJ26), AF176, 0) -> 0 | DJ26: =IF((Y179=AJ26), AF179, 0) -> 0 | DK26: =IF((Y181=AJ26), AF181, 0) -> 0 | DL26: =IF((Y183=AJ26), AF183, 0) -> 0 | DM26: =IF((Y185=AJ26), AF185, 0) -> 0 | DN26: =IF((Y188=AJ26), AF188, 0) -> 0 | DO26: =IF((Y190=AJ26), AF190, 0) -> 0 | DP26: =IF((Y192=AJ26), AF192, 0) -> 0 | DQ26: =IF((Y194=AJ26), AF194, 0) -> 0 | DR26: =IF((Y197=AJ26), AF197, 0) -> 0 | DS26: =IF((Y199=AJ26), AF199, 0) -> 0 | DT26: =IF((Y201=AJ26), AF201, 0) -> 0 | DU26: =IF((Y203=AJ26), AF203, 0) -> 0 | DV26: =IF((Y206=AJ26), AF206, 0) -> 0 | DW26: =IF((Y208=AJ26), AF208, 0) -> 0 | DX26: =IF((Y210=AJ26), AF210, 0) -> 0 | DY26: =IF((Y212=AJ26), AF212, 0) -> 0 | DZ26: =IF((Y215=AJ26), AF215, 0) -> 0 | EA26: =IF((Y217=AJ26), AF217, 0) -> 0 | EB26: =IF((Y219=AJ26), AF219, 0) -> 0 | EC26: =IF((Y221=AJ26), AF221, 0) -> 0 | ED26: =IF((Y224=AJ26), AF224, 0) -> 0 | EE26: =IF((Y226=AJ26), AF226, 0) -> 0 | EF26: =IF((Y228=AJ26), AF228, 0) -> 0 | EG26: =IF((Y230=AJ26), AF230, 0) -> 0 | EH26: =IF((Y233=AJ26), AF233, 0) -> 0 | EI26: =IF((Y235=AJ26), AF235, 0) -> 0 | EJ26: =IF((Y237=AJ26), AF237, 0) -> 0 | EK26: =IF((Y239=AJ26), AF239, 0) -> 0 | EL26: =IF((Y242=AJ26), AF242, 0) -> 0 | EM26: =IF((Y244=AJ26), AF244, 0) -> 0 | EN26: =IF((Y246=AJ26), AF246, 0) -> 0 | EO26: =IF((Y248=AJ26), AF248, 0) -> 0 | EP26: =IF('NOME + Nº'!E62="SIM",0,IF((Y251=AJ26),AF251,0)+IF((Y252=AJ26),AF252,0)) -> 0 | EQ26: =IF('NOME + Nº'!E62="SIM",0,IF((Y254=AJ26),AF254,0)+IF((Y255=AJ26),AF255,0)) -> 0 | ER26: =IF('NOME + Nº'!E62="SIM",0,IF((Y257=AJ26), AF257,0)+IF((Y258=AJ26), AF258,0)) -> 0 | ES26: =IF('NOME + Nº'!E62="SIM",0,IF((Y260=AJ26), AF260,0)+IF((Y261=AJ26), AF261,0)) -> 0 | ET26: =IF(Y264=AJ26,AF264,0) -> 0 | EU26: =IF('NOME + Nº'!D28="SIM",SUM(AP26:ET26),0) -> 0 | EW26: =SUM(EP26:ES26) -> 0
I27: 7 | J27: =IF(N27=0," ",ENFESTO!AJ26) | K27: =IF(N27=0," ",ENFESTO!AK26) | L27: =IF(N27=0," ",ENFESTO!AL26) | M27: =IF(N27=0," ",ENFESTO!AM26) | N27: =IF(ENFESTO!AN26=0,0,ENFESTO!AN26) -> 0 | O27: =IF(ENFESTO!AO26=0,0,ENFESTO!AO26) -> 0 | W27: =IF(V26="SIM","1","0") -> 0 | Z27: =Z22 -> 20
U28: =U26+1 -> 6 | V28: =MODELAGEM!K22 -> NÃO | W28: ' ' | Y28: =MODELAGEM!M22 -> Entretela | AA28: =MODELAGEM!N22 -> 16 | AB28: =IF(V28="NÃO",0,((Z29*MODELAGEM!P22/(MODELAGEM!R22/MODELAGEM!L22))/100)) -> 0 | AC28: =AC26 -> 2.5 | AE28: =IF(V28="NÃO",0,((Z29/(MODELAGEM!R22))*(AC28*2/100)+AB28)*W29) -> 0 | AF28: =AE28*AA28 -> 0 | AK28: CONSUMO TOTAL | AN28: =SUM(AN20:AN26) -> 4.1447059 | AO28: =SUM(AO20:AO26) -> 206.82082 | ES28: CONSUMO TOTAL | EU28: =SUM(EU20:EU26) -> 206.82082 | EW28: =SUM(EW20:EW26) -> 20.223712
B29: Book | K29: CONSUMO TOTAL | N29: =ENFESTO!AN28 -> 4.1447059 | O29: =ENFESTO!AO28 -> 206.82082 | W29: =IF(V28="SIM","1","0") -> 0 | Z29: =Z27 -> 20
B30: Data | C30: Nota | U30: =U28+1 -> 7 | V30: =MODELAGEM!K24 -> NÃO | W30: ' ' | Y30: =MODELAGEM!M24 -> Forro | AA30: =MODELAGEM!N24 -> 19.9 | AB30: =IF(V30="NÃO",0,((Z31*MODELAGEM!P24/(MODELAGEM!R24/MODELAGEM!L24))/100)) -> 0 | AC30: =AC28 -> 2.5 | AE30: =IF(V30="NÃO",0,((Z31/(MODELAGEM!R24))*(AC30*2/100)+AB30)*W31) -> 0 | AF30: =AE30*AA30 -> 0
W31: =IF(V30="SIM","1","0") -> 0 | Z31: =Z29 -> 20
U32: =U30+1 -> 8 | V32: =MODELAGEM!K26 -> NÃO | W32: ' ' | Y32: =MODELAGEM!M26 -> Forro | AA32: =MODELAGEM!N26 -> 19.9 | AB32: =IF(V32="NÃO",0,((Z33*MODELAGEM!P26/(MODELAGEM!R26/MODELAGEM!L26))/100)) -> 0 | AC32: =AC30 -> 2.5 | AE32: =IF(V32="NÃO",0,((Z33/(MODELAGEM!R25))*(AC32*2/100)+AB32)*W33) -> 0 | AF32: =AE32*AA32 -> 0
I33: 2 | J33: =ENFESTO!W10 -> REF. NOME + Nº - 15H x 10B x 5L (cm) | W33: =IF(V32="SIM","1","0") -> 0 | Z33: =Z31 -> 20 | ER33: =SE('REF. NOME + N'!E62="SIM";0;SE((M259=X14); V259+SE(H259="SIM";SE((P259=X14);SOMA(V260:V263); 0)); SE(H259="SIM";SE((P259=X14);SOMA(V260:V263); 0))))
J34: CONSUMO DE TECIDO POR ENFESTO
J35: =IF('NOME + Nº'!$C$33="NÃO","!!ENFESTO não atualizado!!","") -> !!ENFESTO não atualizado!! | T35: =MODELAGEM!H29 -> MOLDE 3 | U35: =U32+1 -> 9 | V35: =MODELAGEM!K29 -> NÃO | W35: =MODELAGEM!H30 -> NOME | Y35: =MODELAGEM!M29 -> Tela OU Cristal | AA35: =MODELAGEM!N29 -> FALSE | AB35: =IF(V35="NÃO",0,((Z36*MODELAGEM!P29/(MODELAGEM!R29/MODELAGEM!L29))/100)) -> 0 | AC35: =AC32 -> 2.5 | AE35: =IF(V35="NÃO",0,((Z36/(MODELAGEM!R29))*(AC35*2/100)+AB35)*W36) -> 0 | AF35: =AE35*AA35 -> 0 | AG35: =IF(V35="SIM",1,IF(V37="SIM",1,IF(V39="SIM",1,0))) -> 0
K36: ENCOMENDA | W36: =IF(V35="SIM","1","0") -> 0 | Z36: =Z31 -> 20
J37: LOTE | K37: =ENFESTO!U14 -> 20 | U37: =U35+1 -> 10 | V37: =MODELAGEM!K31 -> NÃO | W37: ' ' | Y37: =MODELAGEM!M31 -> Material Secundário III | AA37: =MODELAGEM!N31 -> FALSE | AB37: =IF(V37="NÃO",0,((Z38*MODELAGEM!P31/(MODELAGEM!R31/MODELAGEM!L31))/100)) -> 0 | AC37: =AC35 -> 2.5 | AE37: =IF(V37="NÃO",0,((Z38/(MODELAGEM!R31))*(AC37*2/100)+AB37)*W38) -> 0 | AF37: =AE37*AA37 -> 0
J38: LISTA DE TECIDOS | N38: Soma Total | W38: =IF(V37="SIM","1","0") -> 0 | Z38: =Z36 -> 20
J39: TECIDO | K39: Descrição | L39: VALOR (R$/m) | M39: Largura | N39: Metros | O39: R$ | U39: =U37+1 -> 11 | V39: =MODELAGEM!K33 -> NÃO | W39: ' ' | Y39: =MODELAGEM!M33 -> Forro | AA39: =MODELAGEM!N33 -> 19.9 | AB39: =IF(V39="NÃO",0,((Z40*MODELAGEM!P33/(MODELAGEM!R33/MODELAGEM!L33))/100)) -> 0 | AC39: =AC37 -> 2.5 | AE39: =IF(V39="NÃO",0,((Z40/(MODELAGEM!R33))*(AC39*2/100)+AB39)*W40) -> 0 | AF39: =AE39*AA39 -> 0
I40: 1 | J40: =IF(N40=0," ",AQ274) | K40: =IF(N40=0," ",AR274) | L40: =IF(N40=0," ",AS274) | M40: =IF(N40=0," ",AT274) | N40: =IF(AU274=0,0,AU274) -> 0 | O40: =IF(AU274=0,0,AV274) -> 0 | W40: =IF(V39="SIM","1","0") -> 0 | Z40: =Z38 -> 20
I41: 2 | J41: =IF(N41=0," ",AQ275) | K41: =IF(N41=0," ",AR275) | L41: =IF(N41=0," ",AS275) | M41: =IF(N41=0," ",AT275) | N41: =IF(AU275=0,0,AU275) -> 0 | O41: =IF(AU275=0,0,AV275) -> 0 | U41: =U39+1 -> 12 | V41: =MODELAGEM!K35 -> NÃO | W41: ' ' | Y41: =MODELAGEM!M35 -> Forro | AA41: =MODELAGEM!N35 -> 19.9 | AB41: =IF(V41="NÃO",0,((Z42*MODELAGEM!P35/(MODELAGEM!R35/MODELAGEM!L35))/100)) -> 0 | AC41: =AC39 -> 2.5 | AE41: =IF(V41="NÃO",0,((Z42/(MODELAGEM!R33))*(AC41*2/100)+AB41)*W42) -> 0 | AF41: =AE41*AA41 -> 0
I42: 3 | J42: =IF(N42=0," ",AQ276) | K42: =IF(N42=0," ",AR276) | L42: =IF(N42=0," ",AS276) | M42: =IF(N42=0," ",AT276) | N42: =IF(AU276=0,0,AU276) -> 0 | O42: =IF(AU276=0,0,AV276) -> 0 | W42: =IF(V41="SIM","1","0") -> 0 | Z42: =Z40 -> 20
I43: 4 | J43: =IF(N43=0," ",AQ277) | K43: =IF(N43=0," ",AR277) | L43: =IF(N43=0," ",AS277) | M43: =IF(N43=0," ",AT277) | N43: =IF(AU277=0,0,AU277) -> 0 | O43: =IF(AU277=0,0,AV277) -> 0
I44: 5 | J44: =IF(N44=0," ",AQ278) | K44: =IF(N44=0," ",AR278) | L44: =IF(N44=0," ",AS278) | M44: =IF(N44=0," ",AT278) | N44: =IF(AU278=0,0,AU278) -> 0 | O44: =IF(AU278=0,0,AV278) -> 0 | T44: =MODELAGEM!H38 -> MOLDE 4 | U44: =U41+1 -> 13 | V44: =MODELAGEM!K38 -> NÃO | W44: =MODELAGEM!H39 -> NOME | Y44: =MODELAGEM!M38 -> Forro | AA44: =MODELAGEM!N38 -> 19.9 | AB44: =IF(V44="NÃO",0,((Z45*MODELAGEM!P38/(MODELAGEM!R38/MODELAGEM!L38))/100)) -> 0 | AC44: =AC41 -> 2.5 | AE44: =IF(V44="NÃO",0,((Z45/(MODELAGEM!R38))*(AC44*2/100)+AB44)*W45) -> 0 | AF44: =AE44*AA44 -> 0 | AG44: =IF(V44="SIM",1,IF(V46="SIM",1,IF(V48="SIM",1,0))) -> 0
I45: 6 | J45: =IF(N45=0," ",AQ279) | K45: =IF(N45=0," ",AR279) | L45: =IF(N45=0," ",AS279) | M45: =IF(N45=0," ",AT279) | N45: =IF(AU279=0,0,AU279) -> 0 | O45: =IF(AU279=0,0,AV279) -> 0 | W45: =IF(V44="SIM","1","0") -> 0 | Z45: =Z40 -> 20
I46: 7 | J46: =IF(N46=0," ",AQ280) | K46: =IF(N46=0," ",AR280) | L46: =IF(N46=0," ",AS280) | M46: =IF(N46=0," ",AT280) | N46: =IF(AU280=0,0,AU280) -> 0 | O46: =IF(AU280=0,0,AV280) -> 0 | U46: =U44+1 -> 14 | V46: =MODELAGEM!K40 -> NÃO | W46: ' ' | Y46: =MODELAGEM!M40 -> Tela OU Cristal | AA46: =MODELAGEM!N40 -> FALSE | AB46: =IF(V46="NÃO",0,((Z47*MODELAGEM!P40/(MODELAGEM!R40/MODELAGEM!L40))/100)) -> 0 | AC46: =AC44 -> 2.5 | AE46: =IF(V46="NÃO",0,((Z47/(MODELAGEM!R40))*(AC46*2/100)+AB46)*W47) -> 0 | AF46: =AE46*AA46 -> 0
W47: =IF(V46="SIM","1","0") -> 0 | Z47: =Z45 -> 20
K48: CONSUMO TOTAL | N48: =IF(ENFESTO!AU282=0,0,ENFESTO!AU282) -> 0 | O48: =IF(ENFESTO!AV282=0,0,ENFESTO!AV282) -> 0 | U48: =U46+1 -> 15 | V48: =MODELAGEM!K42 -> NÃO | W48: ' ' | Y48: =MODELAGEM!M42 -> Forro | AA48: =MODELAGEM!N42 -> 19.9 | AB48: =IF(V48="NÃO",0,((Z49*MODELAGEM!P42/(MODELAGEM!R42/MODELAGEM!L42))/100)) -> 0 | AC48: =AC46 -> 2.5 | AE48: =IF(V48="NÃO",0,((Z49/(MODELAGEM!R42))*(AC48*2/100)+AB48)*W49) -> 0 | AF48: =AE48*AA48 -> 0
W49: =IF(V48="SIM","1","0") -> 0 | Z49: =Z47 -> 20
U50: =U48+1 -> 16 | V50: =MODELAGEM!K44 -> NÃO | W50: ' ' | Y50: =MODELAGEM!M44 -> Forro | AA50: =MODELAGEM!N44 -> 19.9 | AB50: =IF(V50="NÃO",0,((Z51*MODELAGEM!P44/(MODELAGEM!R44/MODELAGEM!L44))/100)) -> 0 | AC50: =AC48 -> 2.5 | AE50: =IF(V50="NÃO",0,((Z51/(MODELAGEM!R41))*(AC50*2/100)+AB50)*W51) -> 0 | AF50: =AE50*AA50 -> 0
W51: =IF(V50="SIM","1","0") -> 0 | Z51: =Z49 -> 20
T53: =MODELAGEM!H47 -> MOLDE 5 | U53: =U50+1 -> 17 | V53: =MODELAGEM!K47 -> NÃO | W53: =MODELAGEM!H48 -> NOME | Y53: =MODELAGEM!M47 -> Forro | AA53: =MODELAGEM!N47 -> 19.9 | AB53: =IF(V53="NÃO",0,((Z54*MODELAGEM!P47/(MODELAGEM!R47/MODELAGEM!L47))/100)) -> 0 | AC53: =AC50 -> 2.5 | AE53: =IF(V53="NÃO",0,((Z54/(MODELAGEM!R47))*(AC53*2/100)+AB53)*W54) -> 0 | AF53: =AE53*AA53 -> 0 | AG53: =IF(V53="SIM",1,IF(V55="SIM",1,IF(V57="SIM",1,0))) -> 0
W54: =IF(V53="SIM","1","0") -> 0 | Z54: =Z49 -> 20
U55: =U53+1 -> 18 | V55: =MODELAGEM!K49 -> NÃO | W55: ' ' | Y55: =MODELAGEM!M49 -> Forro | AA55: =MODELAGEM!N49 -> 19.9 | AB55: =IF(V55="NÃO",0,((Z56*MODELAGEM!P49/(MODELAGEM!R49/MODELAGEM!L49))/100)) -> 0 | AC55: =AC53 -> 2.5 | AE55: =IF(V55="NÃO",0,((Z56/(MODELAGEM!R49))*(AC55*2/100)+AB55)*W56) -> 0 | AF55: =AE55*AA55 -> 0
W56: =IF(V55="SIM","1","0") -> 0 | Z56: =Z54 -> 20
U57: =U55+1 -> 19 | V57: =MODELAGEM!K51 -> NÃO | W57: ' ' | Y57: =MODELAGEM!M51 -> Tec. Externo | AA57: =MODELAGEM!N51 -> 49.9 | AB57: =IF(V57="NÃO",0,((Z58*MODELAGEM!P51/(MODELAGEM!R51/MODELAGEM!L51))/100)) -> 0 | AC57: =AC55 -> 2.5 | AE57: =IF(V57="NÃO",0,((Z58/(MODELAGEM!R51))*(AC57*2/100)+AB57)*W58) -> 0 | AF57: =AE57*AA57 -> 0
W58: =IF(V57="SIM","1","0") -> 0 | Z58: =Z56 -> 20
U59: =U57+1 -> 20 | V59: =MODELAGEM!K53 -> NÃO | W59: ' ' | Y59: =MODELAGEM!M53 -> Forro | AA59: =MODELAGEM!N53 -> 19.9 | AB59: =IF(V59="NÃO",0,((Z60*MODELAGEM!P53/(MODELAGEM!R53/MODELAGEM!L53))/100)) -> 0 | AC59: =AC57 -> 2.5 | AE59: =IF(V59="NÃO",0,((Z60/(MODELAGEM!R49))*(AC59*2/100)+AB59)*W60) -> 0 | AF59: =AE59*AA59 -> 0
W60: =IF(V59="SIM","1","0") -> 0 | Z60: =Z58 -> 20
T62: =MODELAGEM!H56 -> MOLDE 6 | U62: =U59+1 -> 21 | V62: =MODELAGEM!K56 -> NÃO | W62: =MODELAGEM!H57 -> NOME | Y62: =MODELAGEM!M56 -> Forro | AA62: =MODELAGEM!N56 -> 19.9 | AB62: =IF(V62="NÃO",0,((Z63*MODELAGEM!P56/(MODELAGEM!R56/MODELAGEM!L56))/100)) -> 0 | AC62: =AC59 -> 2.5 | AE62: =IF(V62="NÃO",0,((Z63/(MODELAGEM!R56))*(AC62*2/100)+AB62)*W63) -> 0 | AF62: =AE62*AA62 -> 0 | AG62: =IF(V62="SIM",1,IF(V64="SIM",1,IF(V66="SIM",1,0))) -> 0
W63: =IF(V62="SIM","1","0") -> 0 | Z63: =Z58 -> 20
U64: =U62+1 -> 22 | V64: =MODELAGEM!K58 -> NÃO | W64: ' ' | Y64: =MODELAGEM!M58 -> Entretela | AA64: =MODELAGEM!N58 -> 16 | AB64: =IF(V64="NÃO",0,((Z65*MODELAGEM!P58/(MODELAGEM!R58/MODELAGEM!L58))/100)) -> 0 | AC64: =AC62 -> 2.5 | AE64: =IF(V64="NÃO",0,((Z65/(MODELAGEM!R58))*(AC64*2/100)+AB64)*W65) -> 0 | AF64: =AE64*AA64 -> 0
W65: =IF(V64="SIM","1","0") -> 0 | Z65: =Z63 -> 20
U66: =U64+1 -> 23 | V66: =MODELAGEM!K60 -> NÃO | W66: ' ' | Y66: =MODELAGEM!M60 -> Forro | AA66: =MODELAGEM!N60 -> 19.9 | AB66: =IF(V66="NÃO",0,((Z67*MODELAGEM!P60/(MODELAGEM!R60/MODELAGEM!L60))/100)) -> 0 | AC66: =AC64 -> 2.5 | AE66: =IF(V66="NÃO",0,((Z67/(MODELAGEM!R60))*(AC66*2/100)+AB66)*W67) -> 0 | AF66: =AE66*AA66 -> 0
W67: =IF(V66="SIM","1","0") -> 0 | Z67: =Z65 -> 20
U68: =U66+1 -> 24 | V68: =MODELAGEM!K62 -> NÃO | W68: ' ' | Y68: =MODELAGEM!M62 -> Forro | AA68: =MODELAGEM!N62 -> 19.9 | AB68: =IF(V68="NÃO",0,((Z69*MODELAGEM!P62/(MODELAGEM!R62/MODELAGEM!L62))/100)) -> 0 | AC68: =AC66 -> 2.5 | AE68: =IF(V68="NÃO",0,((Z69/(MODELAGEM!R57))*(AC68*2/100)+AB68)*W69) -> 0 | AF68: =AE68*AA68 -> 0
W69: =IF(V68="SIM","1","0") -> 0 | Z69: =Z67 -> 20
T71: =MODELAGEM!H65 -> MOLDE 7 | U71: =U68+1 -> 25 | V71: =MODELAGEM!K65 -> NÃO | W71: =MODELAGEM!H66 -> NOME | Y71: =MODELAGEM!M65 -> Forro | AA71: =MODELAGEM!N65 -> 19.9 | AB71: =IF(V71="NÃO",0,((Z72*MODELAGEM!P65/(MODELAGEM!R65/MODELAGEM!L65))/100)) -> 0 | AC71: =AC68 -> 2.5 | AE71: =IF(V71="NÃO",0,((Z72/(MODELAGEM!R65))*(AC71*2/100)+AB71)*W72) -> 0 | AF71: =AE71*AA71 -> 0 | AG71: =IF(V71="SIM",1,IF(V73="SIM",1,IF(V75="SIM",1,0))) -> 0
W72: =IF(V71="SIM","1","0") -> 0 | Z72: =Z67 -> 20
U73: =U71+1 -> 26 | V73: =MODELAGEM!K67 -> NÃO | W73: ' ' | Y73: =MODELAGEM!M67 -> Tec. Externo | AA73: =MODELAGEM!N67 -> 49.9 | AB73: =IF(V73="NÃO",0,((Z74*MODELAGEM!P67/(MODELAGEM!R67/MODELAGEM!L67))/100)) -> 0 | AC73: =AC71 -> 2.5 | AE73: =IF(V73="NÃO",0,((Z74/(MODELAGEM!R67))*(AC73*2/100)+AB73)*W74) -> 0 | AF73: =AE73*AA73 -> 0
W74: =IF(V73="SIM","1","0") -> 0 | Z74: =Z72 -> 20
U75: =U73+1 -> 27 | V75: =MODELAGEM!K69 -> NÃO | W75: ' ' | Y75: =MODELAGEM!M69 -> Entretela | AA75: =MODELAGEM!N69 -> 16 | AB75: =IF(V75="NÃO",0,((Z76*MODELAGEM!P69/(MODELAGEM!R69/MODELAGEM!L69))/100)) -> 0 | AC75: =AC73 -> 2.5 | AE75: =IF(V75="NÃO",0,((Z76/(MODELAGEM!R69))*(AC75*2/100)+AB75)*W76) -> 0 | AF75: =AE75*AA75 -> 0
W76: =IF(V75="SIM","1","0") -> 0 | Z76: =Z74 -> 20
U77: =U75+1 -> 28 | V77: =MODELAGEM!K71 -> NÃO | W77: ' ' | Y77: =MODELAGEM!M71 -> Forro | AA77: =MODELAGEM!N71 -> 19.9 | AB77: =IF(V77="NÃO",0,((Z78*MODELAGEM!P71/(MODELAGEM!R71/MODELAGEM!L71))/100)) -> 0 | AC77: =AC75 -> 2.5 | AE77: =IF(V77="NÃO",0,((Z78/(MODELAGEM!R65))*(AC77*2/100)+AB77)*W78) -> 0 | AF77: =AE77*AA77 -> 0
W78: =IF(V77="SIM","1","0") -> 0 | Z78: =Z76 -> 20
T80: =MODELAGEM!H74 -> MOLDE 8 | U80: =U77+1 -> 29 | V80: =MODELAGEM!K74 -> NÃO | W80: =MODELAGEM!H75 -> NOME | Y80: =MODELAGEM!M74 -> Tec. Externo | AA80: =MODELAGEM!N74 -> 49.9 | AB80: =IF(V80="NÃO",0,((Z81*MODELAGEM!P74/(MODELAGEM!R74/MODELAGEM!L74))/100)) -> 0 | AC80: =AC77 -> 2.5 | AE80: =IF(V80="NÃO",0,((Z81/(MODELAGEM!R74))*(AC80*2/100)+AB80)*W81) -> 0 | AF80: =AE80*AA80 -> 0 | AG80: =IF(V80="SIM",1,IF(V82="SIM",1,IF(V84="SIM",1,0))) -> 0
W81: =IF(V80="SIM","1","0") -> 0 | Z81: =Z76 -> 20
U82: =U80+1 -> 30 | V82: =MODELAGEM!K76 -> NÃO | W82: ' ' | Y82: =MODELAGEM!M76 -> Entretela | AA82: =MODELAGEM!N76 -> 16 | AB82: =IF(V82="NÃO",0,((Z83*MODELAGEM!P76/(MODELAGEM!R76/MODELAGEM!L76))/100)) -> 0 | AC82: =AC80 -> 2.5 | AE82: =IF(V82="NÃO",0,((Z83/(MODELAGEM!R76))*(AC82*2/100)+AB82)*W83) -> 0 | AF82: =AE82*AA82 -> 0
W83: =IF(V82="SIM","1","0") -> 0 | Z83: =Z81 -> 20
U84: =U82+1 -> 31 | V84: =MODELAGEM!K78 -> NÃO | W84: ' ' | Y84: =MODELAGEM!M78 -> Tec. Externo | AA84: =MODELAGEM!N78 -> 49.9 | AB84: =IF(V84="NÃO",0,((Z85*MODELAGEM!P78/(MODELAGEM!R78/MODELAGEM!L78))/100)) -> 0 | AC84: =AC82 -> 2.5 | AE84: =IF(V84="NÃO",0,((Z85/(MODELAGEM!R78))*(AC84*2/100)+AB84)*W85) -> 0 | AF84: =AE84*AA84 -> 0
W85: =IF(V84="SIM","1","0") -> 0 | Z85: =Z83 -> 20
U86: =U84+1 -> 32 | V86: =MODELAGEM!K80 -> NÃO | W86: ' ' | Y86: =MODELAGEM!M80 -> Forro | AA86: =MODELAGEM!N80 -> 19.9 | AB86: =IF(V86="NÃO",0,((Z87*MODELAGEM!P80/(MODELAGEM!R80/MODELAGEM!L80))/100)) -> 0 | AC86: =AC84 -> 2.5 | AE86: =IF(V86="NÃO",0,((Z87/(MODELAGEM!R80))*(AC86*2/100)+AB86)*W87) -> 0 | AF86: =AE86*AA86 -> 0
W87: =IF(V86="SIM","1","0") -> 0 | Z87: =Z85 -> 20
T89: =MODELAGEM!H83 -> MOLDE 9 | U89: =U86+1 -> 33 | V89: =MODELAGEM!K83 -> NÃO | W89: =MODELAGEM!H84 -> NOME | Y89: =MODELAGEM!M83 -> Forro | AA89: =MODELAGEM!N83 -> 19.9 | AB89: =IF(V89="NÃO",0,((Z90*MODELAGEM!P83/(MODELAGEM!R83/MODELAGEM!L83))/100)) -> 0 | AC89: =AC86 -> 2.5 | AE89: =IF(V89="NÃO",0,((Z90/(MODELAGEM!R83))*(AC89*2/100)+AB89)*W90) -> 0 | AF89: =AE89*AA89 -> 0 | AG89: =IF(V89="SIM",1,IF(V91="SIM",1,IF(V93="SIM",1,0))) -> 0
W90: =IF(V89="SIM","1","0") -> 0 | Z90: =Z85 -> 20
U91: =U89+1 -> 34 | V91: =MODELAGEM!K85 -> NÃO | W91: ' ' | Y91: =MODELAGEM!M85 -> Entretela | AA91: =MODELAGEM!N85 -> 16 | AB91: =IF(V91="NÃO",0,((Z92*MODELAGEM!P85/(MODELAGEM!R85/MODELAGEM!L85))/100)) -> 0 | AC91: =AC89 -> 2.5 | AE91: =IF(V91="NÃO",0,((Z92/(MODELAGEM!R85))*(AC91*2/100)+AB91)*W92) -> 0 | AF91: =AE91*AA91 -> 0
W92: =IF(V91="SIM","1","0") -> 0 | Z92: =Z90 -> 20
U93: =U91+1 -> 35 | V93: =MODELAGEM!K87 -> NÃO | W93: ' ' | Y93: =MODELAGEM!M87 -> Tec. Externo | AA93: =MODELAGEM!N87 -> 49.9 | AB93: =IF(V93="NÃO",0,((Z94*MODELAGEM!P87/(MODELAGEM!R87/MODELAGEM!L87))/100)) -> 0 | AC93: =AC91 -> 2.5 | AE93: =IF(V93="NÃO",0,((Z94/(MODELAGEM!R87))*(AC93*2/100)+AB93)*W94) -> 0 | AF93: =AE93*AA93 -> 0
W94: =IF(V93="SIM","1","0") -> 0 | Z94: =Z92 -> 20
U95: =U93+1 -> 36 | V95: =MODELAGEM!K89 -> NÃO | W95: ' ' | Y95: =MODELAGEM!M89 -> Forro | AA95: =MODELAGEM!N89 -> 19.9 | AB95: =IF(V95="NÃO",0,((Z96*MODELAGEM!P89/(MODELAGEM!R89/MODELAGEM!L89))/100)) -> 0 | AC95: =AC93 -> 2.5 | AE95: =IF(V95="NÃO",0,((Z96/(MODELAGEM!R89))*(AC95*2/100)+AB95)*W96) -> 0 | AF95: =AE95*AA95 -> 0
W96: =IF(V95="SIM","1","0") -> 0 | Z96: =Z94 -> 20
T98: =MODELAGEM!H92 -> MOLDE 10 | U98: =U95+1 -> 37 | V98: =MODELAGEM!K92 -> NÃO | W98: =MODELAGEM!H93 -> NOME | Y98: =MODELAGEM!M92 -> Forro | AA98: =MODELAGEM!N92 -> 19.9 | AB98: =IF(V98="NÃO",0,((Z99*MODELAGEM!P92/(MODELAGEM!R92/MODELAGEM!L92))/100)) -> 0 | AC98: =AC95 -> 2.5 | AE98: =IF(V98="NÃO",0,((Z99/(MODELAGEM!R92))*(AC98*2/100)+AB98)*W99) -> 0 | AF98: =AE98*AA98 -> 0 | AG98: =IF(V98="SIM",1,IF(V100="SIM",1,IF(V102="SIM",1,0))) -> 0
W99: =IF(V98="SIM","1","0") -> 0 | Z99: =Z94 -> 20
U100: =U98+1 -> 38 | V100: =MODELAGEM!K94 -> NÃO | W100: ' ' | Y100: =MODELAGEM!M94 -> Tec. Externo | AA100: =MODELAGEM!N94 -> 49.9 | AB100: =IF(V100="NÃO",0,((Z101*MODELAGEM!P94/(MODELAGEM!R94/MODELAGEM!L94))/100)) -> 0 | AC100: =AC98 -> 2.5 | AE100: =IF(V100="NÃO",0,((Z101/(MODELAGEM!R94))*(AC100*2/100)+AB100)*W101) -> 0 | AF100: =AE100*AA100 -> 0
W101: =IF(V100="SIM","1","0") -> 0 | Z101: =Z99 -> 20
U102: =U100+1 -> 39 | V102: =MODELAGEM!K96 -> NÃO | W102: ' ' | Y102: =MODELAGEM!M96 -> Tec. Externo | AA102: =MODELAGEM!N96 -> 49.9 | AB102: =IF(V102="NÃO",0,((Z103*MODELAGEM!P96/(MODELAGEM!R96/MODELAGEM!L96))/100)) -> 0 | AC102: =AC100 -> 2.5 | AE102: =IF(V102="NÃO",0,((Z103/(MODELAGEM!R96))*(AC102*2/100)+AB102)*W103) -> 0 | AF102: =AE102*AA102 -> 0
W103: =IF(V102="SIM","1","0") -> 0 | Z103: =Z101 -> 20
U104: =U102+1 -> 40 | V104: =MODELAGEM!K98 -> NÃO | W104: ' ' | Y104: =MODELAGEM!M98 -> Forro | AA104: =MODELAGEM!N98 -> 19.9 | AB104: =IF(V104="NÃO",0,((Z105*MODELAGEM!P98/(MODELAGEM!R98/MODELAGEM!L98))/100)) -> 0 | AC104: =AC102 -> 2.5 | AE104: =IF(V104="NÃO",0,((Z105/(MODELAGEM!R98))*(AC104*2/100)+AB104)*W105) -> 0 | AF104: =AE104*AA104 -> 0
W105: =IF(V104="SIM","1","0") -> 0 | Z105: =Z103 -> 20
T107: =MODELAGEM!H101 -> MOLDE 11 | U107: =U104+1 -> 41 | V107: =MODELAGEM!K101 -> NÃO | W107: =MODELAGEM!H102 -> NOME | Y107: =MODELAGEM!M101 -> Forro | AA107: =MODELAGEM!N101 -> 19.9 | AB107: =IF(V107="NÃO",0,((Z108*MODELAGEM!P101/(MODELAGEM!R101/MODELAGEM!L101))/100)) -> 0 | AC107: =AC104 -> 2.5 | AE107: =IF(V107="NÃO",0,((Z108/(MODELAGEM!R101))*(AC107*2/100)+AB107)*W108) -> 0 | AF107: =AE107*AA107 -> 0 | AG107: =IF(V107="SIM",1,IF(V109="SIM",1,IF(V111="SIM",1,0))) -> 0
W108: =IF(V107="SIM","1","0") -> 0 | Z108: =Z103 -> 20
...

Sheet ETIQUETA
E1: MOLDES GERAIS
E2: 1 | F2: ='Programação Individual'!B21 -> VMORDEKAI | K2: =E2+1 -> 2 | L2: =F2 -> VMORDEKAI | Q2: =K2+1 -> 3 | R2: =L2 -> VMORDEKAI
E3: =MODELAGEM!U11 -> 1 | F3: =MODELAGEM!J4 -> REF. NOME + Nº - 15H x 10B x 5L (cm) | K3: =MODELAGEM!U20 -> 0 | L3: =F3 -> REF. NOME + Nº - 15H x 10B x 5L (cm) | Q3: =MODELAGEM!U29 -> 0 | R3: =L3 -> REF. NOME + Nº - 15H x 10B x 5L (cm)
F4: PARTE: | G4: =MODELAGEM!H12 -> CORPO | L4: PARTE: | M4: =MODELAGEM!H21 -> NOME | R4: PARTE: | S4: =MODELAGEM!H30 -> NOME
F5: CORTAR: | G5: =IF(MODELAGEM!K11="NÃO","",IF(MODELAGEM!L11>0,MODELAGEM!L11,"")) -> 1 | H5: =IF(MODELAGEM!K11="NÃO","","×") -> × | I5: =IF(MODELAGEM!K11="NÃO","",MODELAGEM!M11) -> Tec. Externo | L5: CORTAR: | M5: =IF(MODELAGEM!K20="NÃO","",IF(MODELAGEM!L20>0,MODELAGEM!L20,"")) | N5: =IF(MODELAGEM!K20="NÃO","","×") | O5: =IF(MODELAGEM!K20="NÃO","",MODELAGEM!M20) | R5: CORTAR: | S5: =IF(MODELAGEM!K29="NÃO","",IF(MODELAGEM!L29>0,MODELAGEM!L29,"")) | T5: =IF(MODELAGEM!K29="NÃO","","×") | U5: =IF(MODELAGEM!K29="NÃO","",MODELAGEM!M29)
G6: =IF(MODELAGEM!K13="NÃO","",IF(MODELAGEM!L13>0,MODELAGEM!L13,"")) -> 1 | H6: =IF(MODELAGEM!K13="NÃO","","×") -> × | I6: =IF(MODELAGEM!K13="NÃO","",MODELAGEM!M13) -> Reforço | M6: =IF(MODELAGEM!K22="NÃO","",IF(MODELAGEM!L22>0,MODELAGEM!L22,"")) | N6: =IF(MODELAGEM!K22="NÃO","","×") | O6: =IF(MODELAGEM!K22="NÃO","",MODELAGEM!M22) | S6: =IF(MODELAGEM!K31="NÃO","",IF(MODELAGEM!L31>0,MODELAGEM!L31,"")) | T6: =IF(MODELAGEM!K31="NÃO","","×") | U6: =IF(MODELAGEM!K31="NÃO","",MODELAGEM!M31)
G7: =IF(MODELAGEM!K15="NÃO","",IF(MODELAGEM!L15>0,MODELAGEM!L15,"")) -> 1 | H7: =IF(MODELAGEM!K15="NÃO","","×") -> × | I7: =IF(MODELAGEM!K15="NÃO","",MODELAGEM!M15) -> Reforço | M7: =IF(MODELAGEM!K24="NÃO","",IF(MODELAGEM!L24>0,MODELAGEM!L24,"")) | N7: =IF(MODELAGEM!K24="NÃO","","×") | O7: =IF(MODELAGEM!K24="NÃO","",MODELAGEM!M24) | S7: =IF(MODELAGEM!K33="NÃO","",IF(MODELAGEM!L33>0,MODELAGEM!L33,"")) | T7: =IF(MODELAGEM!K33="NÃO","","×") | U7: =IF(MODELAGEM!K33="NÃO","",MODELAGEM!M33)
G8: =IF(MODELAGEM!K17="NÃO","",IF(MODELAGEM!L17>0,MODELAGEM!L17,"")) | H8: =IF(MODELAGEM!K17="NÃO","","×") | I8: =IF(MODELAGEM!K17="NÃO","",MODELAGEM!M17) | M8: =IF(MODELAGEM!K26="NÃO","",IF(MODELAGEM!L26>0,MODELAGEM!L26,"")) | N8: =IF(MODELAGEM!K26="NÃO","","×") | O8: =IF(MODELAGEM!K26="NÃO","",MODELAGEM!M26) | S8: =IF(MODELAGEM!K35="NÃO","",IF(MODELAGEM!L35>0,MODELAGEM!L35,"")) | T8: =IF(MODELAGEM!K35="NÃO","","×") | U8: =IF(MODELAGEM!K35="NÃO","",MODELAGEM!M35)
F10: D (cm): | G10: =IF(MODELAGEM!U11=0,"-",MODELAGEM!P11) -> 34.4 | H10: C | I10: =IF(MODELAGEM!U11=0,"-",MODELAGEM!Q11) -> 58.3 | J10: L | L10: D (cm): | M10: =IF(MODELAGEM!U20=0,"-",MODELAGEM!P20) -> - | N10: C | O10: =IF(MODELAGEM!U20=0,"-",MODELAGEM!Q20) -> - | P10: L | R10: D (cm): | S10: =IF(MODELAGEM!U29=0,"-",MODELAGEM!P29) -> - | T10: C | U10: =IF(MODELAGEM!U29=0,"-",MODELAGEM!Q29) -> - | V10: L
F11: Nº | G11: =IF(MODELAGEM!U11=0,"-",MODELAGEM!U11) -> 1 | H11: / | I11: =MODELAGEM!T250 -> 2 | L11: Nº | M11: =IF(MODELAGEM!U20=0,"-",SUM(MODELAGEM!U11:U20)) -> - | N11: / | O11: =I11 -> 2 | R11: Nº | S11: =IF(MODELAGEM!U29=0,"-",SUM(MODELAGEM!U11:U29)) -> - | T11: / | U11: =O11 -> 2
F12: MODELISTA: | H12: ='NOME + Nº'!J4 -> Victor Ferreira | L12: MODELISTA: | N12: =H12 -> Victor Ferreira | R12: MODELISTA: | T12: =N12 -> Victor Ferreira
F13: DATA: | G13: ='NOME + Nº'!L4 -> 45182 | L13: DATA: | M13: =G13 -> 45182 | R13: DATA: | S13: =G13 -> 45182
F14: OBS: | G14: =IF(MODELAGEM!I18=0," ",MODELAGEM!I18) | L14: OBS: | M14: =IF(MODELAGEM!I27=0," ",MODELAGEM!I27) | R14: OBS: | S14: =IF(MODELAGEM!I36=0," ",MODELAGEM!I36)
E16: =E2+3 -> 4 | F16: =F2 -> VMORDEKAI | K16: =E16+1 -> 5 | L16: =F16 -> VMORDEKAI | Q16: =K16+1 -> 6 | R16: =L16 -> VMORDEKAI
E17: =MODELAGEM!U38 -> 0 | F17: =F3 -> REF. NOME + Nº - 15H x 10B x 5L (cm) | K17: =MODELAGEM!U47 -> 0 | L17: =F17 -> REF. NOME + Nº - 15H x 10B x 5L (cm) | Q17: =MODELAGEM!U56 -> 0 | R17: =F17 -> REF. NOME + Nº - 15H x 10B x 5L (cm)
F18: PARTE: | G18: =MODELAGEM!H39 -> NOME | L18: PARTE: | M18: =MODELAGEM!H48 -> NOME | R18: PARTE: | S18: =MODELAGEM!H57 -> NOME
F19: CORTAR: | G19: =IF(MODELAGEM!K38="NÃO","",IF(MODELAGEM!L38>0,MODELAGEM!L38,"")) | H19: =IF(MODELAGEM!K38="NÃO","","×") | I19: =IF(MODELAGEM!K38="NÃO","",MODELAGEM!M38) | L19: CORTAR: | M19: =IF(MODELAGEM!K47="NÃO","",IF(MODELAGEM!L47>0,MODELAGEM!L47,"")) | N19: =IF(MODELAGEM!K47="NÃO","","×") | O19: =IF(MODELAGEM!K47="NÃO","",MODELAGEM!M47) | R19: CORTAR: | S19: =IF(MODELAGEM!K56="NÃO","",IF(MODELAGEM!L56>0,MODELAGEM!L56,"")) | T19: =IF(MODELAGEM!K56="NÃO","","×") | U19: =IF(MODELAGEM!K56="NÃO","",MODELAGEM!M56)
G20: =IF(MODELAGEM!K40="NÃO","",IF(MODELAGEM!L40>0,MODELAGEM!L40,"")) | H20: =IF(MODELAGEM!K40="NÃO","","×") | I20: =IF(MODELAGEM!K40="NÃO","",MODELAGEM!M40) | M20: =IF(MODELAGEM!K49="NÃO","",IF(MODELAGEM!L49>0,MODELAGEM!L49,"")) | N20: =IF(MODELAGEM!K49="NÃO","","×") | O20: =IF(MODELAGEM!K49="NÃO","",MODELAGEM!M49) | S20: =IF(MODELAGEM!K58="NÃO","",IF(MODELAGEM!L58>0,MODELAGEM!L58,"")) | T20: =IF(MODELAGEM!K58="NÃO","","×") | U20: =IF(MODELAGEM!K58="NÃO","",MODELAGEM!M58)
G21: =IF(MODELAGEM!K42="NÃO","",IF(MODELAGEM!L42>0,MODELAGEM!L42,"")) | H21: =IF(MODELAGEM!K42="NÃO","","×") | I21: =IF(MODELAGEM!K42="NÃO","",MODELAGEM!M42) | M21: =IF(MODELAGEM!K51="NÃO","",IF(MODELAGEM!L51>0,MODELAGEM!L51,"")) | N21: =IF(MODELAGEM!K51="NÃO","","×") | O21: =IF(MODELAGEM!K51="NÃO","",MODELAGEM!M51) | S21: =IF(MODELAGEM!K60="NÃO","",IF(MODELAGEM!L60>0,MODELAGEM!L60,"")) | T21: =IF(MODELAGEM!K60="NÃO","","×") | U21: =IF(MODELAGEM!K60="NÃO","",MODELAGEM!M60)
G22: =IF(MODELAGEM!K44="NÃO","",IF(MODELAGEM!L44>0,MODELAGEM!L44,"")) | H22: =IF(MODELAGEM!K44="NÃO","","×") | I22: =IF(MODELAGEM!K44="NÃO","",MODELAGEM!M44) | M22: =IF(MODELAGEM!K53="NÃO","",IF(MODELAGEM!L53>0,MODELAGEM!L53,"")) | N22: =IF(MODELAGEM!K53="NÃO","","×") | O22: =IF(MODELAGEM!K53="NÃO","",MODELAGEM!M53) | S22: =IF(MODELAGEM!K62="NÃO","",IF(MODELAGEM!L62>0,MODELAGEM!L62,"")) | T22: =IF(MODELAGEM!K62="NÃO","","×") | U22: =IF(MODELAGEM!K62="NÃO","",MODELAGEM!M62)
F24: D (cm): | G24: =IF(MODELAGEM!U38=0,"-",MODELAGEM!P38) -> - | H24: C | I24: =IF(MODELAGEM!U38=0,"-",MODELAGEM!Q38) -> - | J24: L | L24: D (cm): | M24: =IF(MODELAGEM!U47=0,"-",MODELAGEM!P47) -> - | N24: C | O24: =IF(MODELAGEM!U47=0,"-",MODELAGEM!Q47) -> - | P24: L | R24: D (cm): | S24: =IF(MODELAGEM!U56=0,"-",MODELAGEM!P56) -> - | T24: C | U24: =IF(MODELAGEM!U56=0,"-",MODELAGEM!Q56) -> - | V24: L
F25: Nº | G25: =IF(MODELAGEM!U38=0,"-",SUM(MODELAGEM!U11:U38)) -> - | H25: / | I25: =I11 -> 2 | L25: Nº | M25: =IF(MODELAGEM!U47=0,"-",SUM(MODELAGEM!U11:U47)) -> - | N25: / | O25: =I25 -> 2 | R25: Nº | S25: =IF(MODELAGEM!U56=0,"-",SUM(MODELAGEM!U11:U56)) -> - | T25: / | U25: =O25 -> 2
F26: MODELISTA: | H26: =H12 -> Victor Ferreira | L26: MODELISTA: | N26: =H26 -> Victor Ferreira | R26: MODELISTA: | T26: =N26 -> Victor Ferreira
F27: DATA: | G27: =G13 -> 45182 | L27: DATA: | M27: =G27 -> 45182 | R27: DATA: | S27: =G27 -> 45182
F28: OBS: | G28: =IF(MODELAGEM!I45=0," ",MODELAGEM!I45) | L28: OBS: | M28: =IF(MODELAGEM!I54=0," ",MODELAGEM!I54) | R28: OBS: | S28: =IF(MODELAGEM!I63=0," ",MODELAGEM!I63)
E30: =E16+3 -> 7 | F30: =F16 -> VMORDEKAI | K30: =E30+1 -> 8 | L30: =F30 -> VMORDEKAI | Q30: =K30+1 -> 9 | R30: =L30 -> VMORDEKAI
E31: =MODELAGEM!U65 -> 0 | F31: =F17 -> REF. NOME + Nº - 15H x 10B x 5L (cm) | K31: =MODELAGEM!U74 -> 0 | L31: =F31 -> REF. NOME + Nº - 15H x 10B x 5L (cm) | Q31: =MODELAGEM!U83 -> 0 | R31: =F31 -> REF. NOME + Nº - 15H x 10B x 5L (cm)
F32: PARTE: | G32: =MODELAGEM!H66 -> NOME | L32: PARTE: | M32: =MODELAGEM!H75 -> NOME | R32: PARTE: | S32: =MODELAGEM!H84 -> NOME
F33: CORTAR: | G33: =IF(MODELAGEM!K65="NÃO","",IF(MODELAGEM!L65>0,MODELAGEM!L65,"")) | H33: =IF(MODELAGEM!K65="NÃO","","×") | I33: =IF(MODELAGEM!K65="NÃO","",MODELAGEM!M65) | L33: CORTAR: | M33: =IF(MODELAGEM!K74="NÃO","",IF(MODELAGEM!L74>0,MODELAGEM!L74,"")) | N33: =IF(MODELAGEM!K74="NÃO","","×") | O33: =IF(MODELAGEM!K74="NÃO","",MODELAGEM!M74) | R33: CORTAR: | S33: =IF(MODELAGEM!K83="NÃO","",IF(MODELAGEM!L83>0,MODELAGEM!L83,"")) | T33: =IF(MODELAGEM!K83="NÃO","","×") | U33: =IF(MODELAGEM!K83="NÃO","",MODELAGEM!M83)
G34: =IF(MODELAGEM!K67="NÃO","",IF(MODELAGEM!L67>0,MODELAGEM!L67,"")) | H34: =IF(MODELAGEM!K67="NÃO","","×") | I34: =IF(MODELAGEM!K67="NÃO","",MODELAGEM!M67) | M34: =IF(MODELAGEM!K76="NÃO","",IF(MODELAGEM!L76>0,MODELAGEM!L76,"")) | N34: =IF(MODELAGEM!K76="NÃO","","×") | O34: =IF(MODELAGEM!K76="NÃO","",MODELAGEM!M76) | S34: =IF(MODELAGEM!K85="NÃO","",IF(MODELAGEM!L85>0,MODELAGEM!L85,"")) | T34: =IF(MODELAGEM!K85="NÃO","","×") | U34: =IF(MODELAGEM!K85="NÃO","",MODELAGEM!M85)
G35: =IF(MODELAGEM!K69="NÃO","",IF(MODELAGEM!L69>0,MODELAGEM!L69,"")) | H35: =IF(MODELAGEM!K69="NÃO","","×") | I35: =IF(MODELAGEM!K69="NÃO","",MODELAGEM!M69) | M35: =IF(MODELAGEM!K78="NÃO","",IF(MODELAGEM!L78>0,MODELAGEM!L78,"")) | N35: =IF(MODELAGEM!K78="NÃO","","×") | O35: =IF(MODELAGEM!K78="NÃO","",MODELAGEM!M78) | S35: =IF(MODELAGEM!K87="NÃO","",IF(MODELAGEM!L87>0,MODELAGEM!L87,"")) | T35: =IF(MODELAGEM!K87="NÃO","","×") | U35: =IF(MODELAGEM!K87="NÃO","",MODELAGEM!M87)
G36: =IF(MODELAGEM!K71="NÃO","",IF(MODELAGEM!L71>0,MODELAGEM!L71,"")) | H36: =IF(MODELAGEM!K71="NÃO","","×") | I36: =IF(MODELAGEM!K71="NÃO","",MODELAGEM!M71) | M36: =IF(MODELAGEM!K80="NÃO","",IF(MODELAGEM!L80>0,MODELAGEM!L80,"")) | N36: =IF(MODELAGEM!K80="NÃO","","×") | O36: =IF(MODELAGEM!K80="NÃO","",MODELAGEM!M80) | S36: =IF(MODELAGEM!K89="NÃO","",IF(MODELAGEM!L89>0,MODELAGEM!L89,"")) | T36: =IF(MODELAGEM!K89="NÃO","","×") | U36: =IF(MODELAGEM!K89="NÃO","",MODELAGEM!M89)
F38: D (cm): | G38: =IF(MODELAGEM!U65=0,"-",MODELAGEM!P65) -> - | H38: C | I38: =IF(MODELAGEM!U65=0,"-",MODELAGEM!Q65) -> - | J38: L | L38: D (cm): | M38: =IF(MODELAGEM!U74=0,"-",MODELAGEM!P74) -> - | N38: C | O38: =IF(MODELAGEM!U74=0,"-",MODELAGEM!Q74) -> - | P38: L | R38: D (cm): | S38: =IF(MODELAGEM!U83=0,"-",MODELAGEM!P83) -> - | T38: C | U38: =IF(MODELAGEM!U83=0,"-",MODELAGEM!Q83) -> - | V38: L
F39: Nº | G39: =IF(MODELAGEM!U65=0,"-",SUM(MODELAGEM!U11:U65)) -> - | H39: / | I39: =I25 -> 2 | L39: Nº | M39: =IF(MODELAGEM!U74=0,"-",SUM(MODELAGEM!U11:U74)) -> - | N39: / | O39: =I39 -> 2 | R39: Nº | S39: =IF(MODELAGEM!U83=0,"-",SUM(MODELAGEM!U11:U83)) -> - | T39: / | U39: =O39 -> 2
F40: MODELISTA: | H40: =H26 -> Victor Ferreira | L40: MODELISTA: | N40: =H40 -> Victor Ferreira | R40: MODELISTA: | T40: =N40 -> Victor Ferreira
F41: DATA: | G41: =G27 -> 45182 | L41: DATA: | M41: =G41 -> 45182 | R41: DATA: | S41: =G41 -> 45182
F42: OBS: | G42: =IF(MODELAGEM!I72=0," ",MODELAGEM!I72) | L42: OBS: | M42: =IF(MODELAGEM!I81=0," ",MODELAGEM!I81) | R42: OBS: | S42: =IF(MODELAGEM!I90=0," ",MODELAGEM!I90)
E44: =E30+3 -> 10 | F44: =F30 -> VMORDEKAI | K44: =E44+1 -> 11 | L44: =F44 -> VMORDEKAI | Q44: =K44+1 -> 12 | R44: =L44 -> VMORDEKAI
E45: =MODELAGEM!U92 -> 0 | F45: =F31 -> REF. NOME + Nº - 15H x 10B x 5L (cm) | K45: =MODELAGEM!U101 -> 0 | L45: =F45 -> REF. NOME + Nº - 15H x 10B x 5L (cm) | Q45: =MODELAGEM!U110 -> 0 | R45: =F45 -> REF. NOME + Nº - 15H x 10B x 5L (cm)
F46: PARTE: | G46: =MODELAGEM!H93 -> NOME | L46: PARTE: | M46: =MODELAGEM!H102 -> NOME | R46: PARTE: | S46: =MODELAGEM!H111 -> NOME
